Workbook

Sheet Bitacora
B2: PENALIZACION NIVEL DE SERVICIO ENE - AGO 2025 | D2: =D5-W5 -> 3.207253e+08 | H2: =H5-J5 -> 1.936889e+08 | K2: =K5-D7-D8 -> 1.9389838e+08 | S2: =R5-W5 -> 5874640.1
B3: Autorizado por direcciones comerciales | W3: =D5-W5 -> 3.207253e+08
G4: =G5-Z5-G7-G8 -> 2.184201e+08 | H4: =G9-H9 -> 1637510.6 | S4: =D4-O4-W4 -> 0 | T4: =E4-X4-P4 -> 0 | U4: =F4-Y4-Q4 -> 0
C5: =SUBTOTAL(3,C7:C438) -> 432 | D5: =SUBTOTAL(9,D7:D438) -> 3.6979601e+08 | E5: =SUBTOTAL(9,E7:E438) -> 6790563.2 | F5: =SUBTOTAL(9,F7:F438) -> 39326912 | G5: =SUBTOTAL(9,G7:G438) -> 4.1591348e+08 | H5: =SUBTOTAL(9,H7:H438) -> 1.936889e+08 | I5: =SUBTOTAL(9,I7:I438) -> 3.2065458e+08 | J5: =SUBTOTAL(9,J7:J438) -> 0 | K5: =SUBTOTAL(9,K7:K438) -> 3.2065458e+08 | ... Z5: =SUBTOTAL(9,Z7:Z438) -> 57208713 | AC5: =SUBTOTAL(9,AC7:AC438) -> 3.6979601e+08 | AD5: =SUBTOTAL(9,AD7:AD438) -> 4.1602438e+08 | AE5: =SUBTOTAL(9,AE7:AE438) -> -110898.08 | AN5: =SUBTOTAL(9,AN7:AN438) -> 2.1767891e+08 | AP5: =SUBTOTAL(9,AP7:AP1048576) -> 152 | AR5: =SUBTOTAL(3,AR7:AR1048576) -> 75 | AX5: Forma de contacto proveedor
B6: Proveedor | C6: Nombre | D6: Cargo Publicado en Portal | E6: IEPS | F6: IVA | G6: Penalizacion con Imptos | H6: Aplicado en cuenta de proveedor (incluye imptos) | I6: total por aplicar (antes imptos) | J6: Reembolso (antes imptos) | K6: Final (antes imptos) | L6: total por aplicar (inlcuye imtpos) | M6: Reembolso con Imptos | N6: Final con imptos | O6: Aceptado (antes impto) | P6: IEPS aceptado | Q6: IVA aceptado | R6: Aceptado con Imptos | S6: Pendiente (antes impto) | T6: IEPS pendiente | U6: IVA pendiente | V6: Pendiente con Imptos | W6: Soportado (no procede antes impto) | X6: IEPS no procede | Y6: IVA no procede | Z6: Soportado con Imptos | AA6: NS 2020-2024 antes de impuestos | AB6: Tipo Proveedor | AC6: TOTAL (antes impto) | AD6: TOTAL (con impto) | AE6: dif | AF6: Parcialidad | AG6: Accionable | AH6: Avisos en Portal | AI6: Correos de seguimiento | AJ6: Observación actual | AK6: contacto | AL6: ESTATUS_1 | AM6: Asignación | AN6: Importe reclama proveedor | AO6: Solicita Proveedor en aclaración | AP6: Folios en aclaración | AQ6: Soporte en poratl | AR6: Fecha Contacto | AS6: Fecha se envió detalle | AT6: Confirmacion recibo | AU6: Fecha reunión | AV6: Comentarios | AW6: ESTATUS | AX6: Aclaracion Portal | AY6: Correo auditor | AZ6: Comercial | BA6: Observacion | BB6: Liga contacto
B7: 66738 | C7: MONDELEZ MEXICO S DE RL DE CV | D7: 89585265 | E7: 2507350.6 | F7: 5074446 | G7: 97167062 | H7: 0 | I7: =O7+S7 -> 89585265 | K7: =I7-J7 -> 89585265 | L7: =R7+V7 -> 97167062 | N7: =L7-M7 -> 97167062 | R7: =SUM(O7:Q7) -> 0 | S7: =D7-O7-W7 -> 89585265 | T7: =E7-X7-P7 -> 2507350.6 | U7: =F7-Y7-Q7 -> 5074446 | V7: =SUM(S7:U7) -> 97167062 | Z7: =SUM(W7:Y7) -> 0 | AA7: 72733062 | AB7: TOP - Aclaracion | AC7: =O7+S7+W7 -> 89585265 | AD7: =R7+V7+Z7 -> 97167062 | AE7: =G7-AD7 -> -0.10609704 | AF7: =D7-S7 -> 0 | AG7: Revisión | AH7: 4 | AI7: 3 | AJ7: Proveedor indica se validará con Dirección el saldo de esta Auditoria. | AK7: CON CONTACTO | AL7: DEFINICION FINANZAS | AM7: Perla | AN7: 97167062 | AR7: 46041 | AS7: 46041 | AV7: En validaciòn por parte de Proveedor, se tiene programada reuniòn el 26 de enero, en espera de confirmaciòn de horario. Negativa de proveedor. | BA7: En validaciòn por parte de Proveedor, se tiene programada reuniòn el 26 de enero, en espera de confirmaciòn de horario. | BB7: =VLOOKUP(B7,contactos!$A$1:$D$484,4,FALSE) -> julioarturo.gomez@mdlz.com
B8: 9647 | C8: FRABEL S.A. DE C.V. | D8: 37170940 | E8: 0 | F8: 5946668.2 | G8: 43117610 | H8: 0 | I8: =O8+S8 -> 37170940 | K8: =I8-J8 -> 37170940 | L8: =R8+V8 -> 43117608 | N8: =L8-M8 -> 43117608 | R8: =SUM(O8:Q8) -> 0 | S8: =D8-O8-W8 -> 37170940 | T8: =E8-X8-P8 -> 0 | U8: =F8-Y8-Q8 -> 5946668.2 | V8: =SUM(S8:U8) -> 43117608 | Z8: =SUM(W8:Y8) -> 0 | AA8: 1.5056482e+08 | AB8: TOP - Aclaracion | AC8: =O8+S8+W8 -> 37170940 | AD8: =R8+V8+Z8 -> 43117608 | AE8: =G8-AD8 -> 1.3499264 | AF8: =D8-S8 -> 0 | AG8: Revisión | AH8: 4 | AI8: 3 | AJ8: Tema interno | AK8: CON CONTACTO | AL8: NEGATIVA ACLARACIONES | AM8: Raul | AN8: 43117609 | AO8: DETALLE DE LOS CARGOS EN EL PORTAL | AR8: 46043 | AS8: 46043 | AV8: Se le aclara a proveedor el periodo de revisión | AW8: Casos abiertos( En proceso) | AX8: X | BB8: =VLOOKUP(B8,contactos!$A$1:$D$484,4,FALSE) -> pablo.candelas@loreal.com
B9: 24232 | C9: GRISI HNOS SA DE CV | D9: 17089111 | E9: 15021.684 | F9: 2502789.4 | G9: 19606922 | H9: 17969411 | I9: =O9+S9 -> 16495305 | K9: =I9-J9 -> 16495305 | L9: =R9+V9 -> 18918922 | N9: =L9-M9 -> 18918922 | O9: 2911551.2 | P9: 0 | Q9: 325961.06 | R9: =SUM(O9:Q9) -> 3237512.2 | S9: =D9-O9-W9 -> 13583754 | T9: =E9-X9-P9 -> 15021.684 | U9: =F9-Y9-Q9 -> 2082634.2 | V9: =SUM(S9:U9) -> 15681410 | W9: 593806.06 | X9: 0 | Y9: 94194.14 | Z9: =SUM(W9:Y9) -> 688000.2 | AA9: 19425853 | AB9: TOP - Aclaracion | AC9: =O9+S9+W9 -> 17089111 | AD9: =R9+V9+Z9 -> 19606922 | AE9: =G9-AD9 -> -0.50646909 | AG9: Aplicar | AH9: 4 | AI9: 10 | AJ9: 20-feb-2026 se comparte con proveedor saldo improcedente por 688K de acuerdo con soportes validados, en espera de soportes y respuesta del saldo restante (proveedor manda correo a Dir Comercial con la afectación al margen en caso de que se cobre el saldo) | AK9: CON CONTACTO | AL9: PDTE POR PROVEEDOR | AM9: Samuel | AO9: SOLICITA DETALLE DE 3 RAZONES QUE MANEJA (GRISI,COMBE,DIGRIMEX) | AR9: 46042 | AS9: 46042 | AV9: Proveedor pide prorroga | AY9: X | BA9: Se revisan evidencias enviadas por proveedor, pero no soportan la imprcedencia del saldo | BB9: =VLOOKUP(B9,contactos!$A$1:$D$484,4,FALSE) -> alberto.saenz@grisi.com
B10: 4077 | C10: BDF MEXICO S.A DE C.V | D10: 15564009 | E10: 0 | F10: 2488527.7 | G10: 18052536 | H10: 18052536 | I10: =O10+S10 -> 15564009 | K10: =I10-J10 -> 15564009 | L10: =R10+V10 -> 18052537 | N10: =L10-M10 -> 18052537 | O10: =D10 -> 15564009 | P10: 0 | Q10: =F10 -> 2488527.7 | R10: =SUM(O10:Q10) -> 18052537 | S10: =D10-O10-W10 -> 0 | T10: =E10-X10-P10 -> 0 | U10: =F10-Y10-Q10 -> 0 | V10: =SUM(S10:U10) -> 0 | Z10: =SUM(W10:Y10) -> 0 | AA10: 24076668 | AB10: TOP - Aclaracion | AC10: =O10+S10+W10 -> 15564009 | AD10: =R10+V10+Z10 -> 18052537 | AE10: =G10-AD10 -> -0.34516056 | AG10: Cerrado/Aplicar | AH10: 4 | AI10: 0 | AJ10: 0 | AK10: CON CONTACTO | AL10: CERRADO | AM10: Yessenia | AN10: 18052536 | AO10: DETALLE DE LOS CARGOS EN EL PORTAL | AR10: 46045 | AS10: 46045 | AV10: Proveedor acepta parte del monto $18,022,712.44 y quedado es espera de soporte de no aceptado de $29,823.79 | AW10: Casos cerrados | AX10: X | BA10: correo compartido por Ambriz Ruiz Jair Alejandro <jairar@soriana.com> | BB10: =VLOOKUP(B10,contactos!$A$1:$D$484,4,FALSE) -> josemiguel.migoya@beiersdorf.com
B11: 76471 | C11: NEWELL BRANDS DE MEXICO SA DE CV | D11: 11585559 | E11: 0 | F11: 1853689.4 | G11: 13439248 | H11: 13439248 | I11: =O11+S11 -> 4720981.4 | J11: 0 | K11: =I11-J11 -> 4720981.4 | L11: =R11+V11 -> 5476338.4 | M11: 0 | N11: =L11-M11 -> 5476338.4 | R11: =SUM(O11:Q11) -> 0 | S11: =D11-O11-W11 -> 4720981.4 | T11: =E11-X11-P11 -> 0 | U11: =F11-Y11-Q11 -> 755357.03 | V11: =SUM(S11:U11) -> 5476338.4 | W11: 6864577.3 | X11: 0 | Y11: =W11*0.16 -> 1098332.4 | Z11: =SUM(W11:Y11) -> 7962909.7 | AA11: 22858397 | AB11: TOP - Sin aclaracion | AC11: =O11+S11+W11 -> 11585559 | AD11: =R11+V11+Z11 -> 13439248 | AE11: =G11-AD11 -> -0.11216746 | AF11: =D11-S11 -> 6864577.3 | AG11: Aplicar | AH11: 4 | AI11: 1 | AJ11: Sin comentarios del proveedor. | AK11: CON CONTACTO | AL11: SIN ACLARACION | AM11: Olfi | AS11: 46050 | AV11: Se le manda correo al proveedor, informandole sobre la auditoria del 2025 | BB11: =VLOOKUP(B11,contactos!$A$1:$D$484,4,FALSE) -> luis.quesadamoreno@newellco.com
B12: 99457 | C12: ESSITY HIGIENE Y SALUD MEXICO SA DE | D12: 10217048 | E12: 0 | F12: 959842.67 | G12: 11176891 | H12: 2355255 | I12: =O12+S12 -> 2126670.9 | K12: =I12-J12 -> 2126670.9 | L12: =R12+V12 -> 2355254.9 | N12: =L12-M12 -> 2355254.9 | O12: 2126670.9 | Q12: 228584.06 | R12: =SUM(O12:Q12) -> 2355254.9 | S12: =D12-O12-W12 -> 0.0024101967 | T12: =E12-X12-P12 -> 0 | U12: =F12-Y12-Q12 -> -0.00067947659 | V12: =SUM(S12:U12) -> 0.0017307201 | W12: 8090377.5 | Y12: 731258.61 | Z12: =SUM(W12:Y12) -> 8821636.1 | AA12: 15169011 | AB12: TOP - Aclaracion | AC12: =O12+S12+W12 -> 10217048 | AD12: =R12+V12+Z12 -> 11176891 | AE12: =G12-AD12 -> -0.37633072 | AG12: Cerrado/Aplicar | AH12: 4 | AI12: 0 | AJ12: 0 | AK12: CON CONTACTO | AL12: CERRADO | AM12: Luis | AN12: 9215790.6 | AR12: 46049 | AS12: 46049 | AT12: 46049 | AV12: Proveedor se contacta con Ana Ruth/Ruben/Tere para solicitar prórroga de los saldos publicados en portal | AX12: X | BB12: =VLOOKUP(B12,contactos!$A$1:$D$484,4,FALSE) -> antonio.palacios@essity.com
B13: 8593 | C13: VISION COMERCIAL DEPORTIVA SA DE CV | D13: 8613844.6 | E13: 0 | F13: 1378215.1 | G13: 9992059.6 | H13: 9992059.6 | I13: =O13+S13 -> 3291014.8 | J13: 0 | K13: =I13-J13 -> 3291014.8 | L13: =R13+V13 -> 3817577.2 | M13: 0 | N13: =L13-M13 -> 3817577.2 | R13: =SUM(O13:Q13) -> 0 | S13: =D13-O13-W13 -> 3291014.8 | T13: =E13-X13-P13 -> 0 | U13: =F13-Y13-Q13 -> 526562.37 | V13: =SUM(S13:U13) -> 3817577.2 | W13: 5322829.8 | Y13: 851652.77 | Z13: =SUM(W13:Y13) -> 6174482.6 | AA13: 6020406 | AB13: TOP - Aclaracion | AC13: =O13+S13+W13 -> 8613844.6 | AD13: =R13+V13+Z13 -> 9992059.8 | AE13: =G13-AD13 -> -0.15727409 | AF13: =D13-S13 -> 5322829.8 | AG13: Aplicar | AH13: 4 | AI13: 8 | AJ13: Proveedor menciona tiene reunión con dirección comercial Soriana el 19 de febrero. Al dia de hoy sin comentarios o soportes por parte del proveedor. | AK13: CON CONTACTO | AL13: PDTE POR PROVEEDOR | AM13: Samuel | AN13: 9992059.6 | AO13: CARGOS YA APLICADOS ANTERIORMENTE (CARGO IMPROCEDENTE) | AP13: 11 | AR13: 46042 | AS13: 46045 | AV13: En validación de información, proveedor solicita reunión 28-ene-26. Proveedor argumenta que los cargos no proceden porque le han hecho otros cargos improcedentes. | AX13: X | BB13: =VLOOKUP(B13,contactos!$A$1:$D$484,4,FALSE) -> victorsanchez@wsports.mx
B14: 90738 | C14: ESSITY HIGIENE Y SALUD MEXICO SA DE | D14: 7245863.5 | E14: 0 | F14: 1159338.2 | G14: 8405201.7 | H14: 3749488 | I14: =O14+S14 -> 3232317.2 | K14: =I14-J14 -> 3232317.2 | L14: =R14+V14 -> 3749488.2 | N14: =L14-M14 -> 3749488.2 | O14: 3232317.2 | Q14: 517170.75 | R14: =SUM(O14:Q14) -> 3749488 | S14: =D14-O14-W14 -> -0.002259267 | T14: =E14-X14-P14 -> 0 | U14: =F14-Y14-Q14 -> 0.21754143 | V14: =SUM(S14:U14) -> 0.21528216 | W14: 4013546.3 | Y14: 642167.2 | Z14: =SUM(W14:Y14) -> 4655713.5 | AA14: 14487404 | AB14: TOP - Aclaracion | AC14: =O14+S14+W14 -> 7245863.5 | AD14: =R14+V14+Z14 -> 8405201.7 | AE14: =G14-AD14 -> -0.0048821624 | AG14: Cerrado/Aplicar | AH14: 4 | AI14: 0 | AJ14: 0 | AK14: CON CONTACTO | AL14: CERRADO | AM14: Luis | AN14: 4650882.8 | AR14: 46049 | AS14: 46049 | AT14: 46049 | AV14: Proveedor se contacta con Ruben/Tere para solicitar prórroga de los saldos publicados en portal | AX14: X | BB14: =VLOOKUP(B14,contactos!$A$1:$D$484,4,FALSE) -> claudia.morales@essity.com
B15: 20125 | C15: MIDEA MEXICO S DE RL DE CV | D15: 7139158.7 | E15: 0 | F15: 1142265.4 | G15: 8281424.2 | H15: 3000000 | I15: =O15+S15 -> 4948440.3 | K15: =I15-J15 -> 4948440.3 | L15: =R15+V15 -> 5740190.7 | N15: =L15-M15 -> 5740190.7 | R15: =SUM(O15:Q15) -> 0 | S15: =D15-O15-W15 -> 4948440.3 | T15: =E15-X15-P15 -> 0 | U15: =F15-Y15-Q15 -> 791750.45 | V15: =SUM(S15:U15) -> 5740190.7 | W15: 2190718.5 | X15: 0 | Y15: 350514.95 | Z15: =SUM(W15:Y15) -> 2541233.4 | AA15: 4964584.1 | AB15: TOP - Sin aclaracion | AC15: =O15+S15+W15 -> 7139158.7 | AD15: =R15+V15+Z15 -> 8281424.1 | AE15: =G15-AD15 -> 0.0020169588 | AG15: Aplicar | AH15: 4 | AI15: 3 | AJ15: 03 Contactos 28 ene: correo de contacto inicial 04 feb: reunión vía TEAMS 06 feb El proveedor envia soportes que desestima $2,541 incluido impuesto. Proveedor solicita 10 días adicionales para recabar el monto $5,740 incluido impuestos. El Proveedor copia área Comercial solicitando apoyo en los 10 días | AK15: CON CONTACTO | AL15: PDTE POR PROVEEDOR | AM15: Andrea | AN15: 544291.47 | AO15: ERROR EN EL CALCULO DEL CARGO SOLICTA EL REEMBOLSO | AP15: 6 | AR15: 46056 | AS15: 46050 | AU15: 46057 | AV15: Se envía correo informando que el comunicado de cargo NS correspondiente al periodo de enero a agosto de 2025 ya se encuentra publicado en el Portal. El detalle del mismo también está disponible desglosado en el Portal. Se adjunta manual de visualizacion de Cargos.//03 FEB el area de Aclaraciones envia correo, se contacta al Proveedor y se realizara reunion el dia 04 feb para revisar el detalle que presenta diferencias y confirmar el monto a favor de Soriana.//04 feb se realiza reunion con Equipo de Midea, quienes presentan diferencias en unidades pedidas segun su sistema, hacemos el ejercicio de revisar puntualmente 5 Ordenes de compra e identifcamos que la cantidad que tiene en su archivo Midea es la real Facturada, por lo que validaran internamente el restante de las ordenes de compra.// 05 feb El proveedor envió correos informando que los camiones permanecieron en el CEDI por más de 30 horas sin que se les pudiera recibir. Asimismo, compartieron un correo con el equipo Comercial de Soriana notificando esta situación y solicitando, por favor, que las órdenes de compra (OC) fueran excluidas de la penalización por nivel de servicio (NS). Proveedor relaciona en excel el valor de $2,541,233.37 pero solo envia soportes de $1,742,928.70// 06 feb El proveedor correo soporte de dos ordenes de compra adicional, por lo tanto no procede el monto de $2.541.233.37 impuestos incluidos. | AW15: Casos abiertos( En proceso) | AX15: X | BB15: =VLOOKUP(B15,contactos!$A$1:$D$484,4,FALSE) -> marco.heredia@midea.com
B16: 56150 | C16: Hershey Mexico SA de CV | D16: 5860104.4 | E16: 417698.04 | F16: 0 | G16: 6277802.3 | H16: 4920449.6 | I16: =O16+S16 -> 4598868.4 | K16: =I16-J16 -> 4598868.4 | L16: =R16+V16 -> 4920449.6 | N16: =L16-M16 -> 4920449.6 | O16: 4598868.4 | P16: 321581.11 | Q16: 0 | R16: =+O16+P16 -> 4920449.6 | S16: 0 | U16: =F16-Q16-Y16 -> 0 | V16: =SUM(S16:U16) -> 0 | W16: =+D16-O16 -> 1261236 | X16: =+E16-P16 -> 96116.929 | Y16: 0 | Z16: =SUM(W16:Y16) -> 1357352.9 | AA16: 17817198 | AB16: TOP - Aclaracion | AC16: =O16+S16+W16 -> 5860104.4 | AD16: =R16+V16+Z16 -> 6277802.5 | AE16: =G16-AD16 -> -0.17458287 | AG16: Cerrado/Aplicar | AH16: 4 | AI16: 0 | AJ16: 0 | AK16: CON CONTACTO | AL16: CERRADO | AM16: Jessica | AN16: 6277802.3 | AO16: DETALLE DE LOS CARGOS EN EL PORTAL | AR16: 46042 | AS16: =TODAY() -> 46212 | AV16: Proveedor acepto de manera parcial, envio soportes para su validacion | AX16: X | BA16: En reunión proveedor nos comenta que ya descargo la información del portal sin embargo requiere la fecha pedido | BB16: =VLOOKUP(B16,contactos!$A$1:$D$484,4,FALSE) -> srosas@hersheys.com
B17: 81653 | C17: HEINZ MEXICO SA DE CV | D17: 5448761.5 | E17: 8396.2742 | F17: 1307.9177 | G17: 5458465.7 | H17: 4134827.1 | I17: =O17+S17 -> 5448761.5 | K17: =I17-J17 -> 5448761.5 | L17: =R17+V17 -> 5458465.7 | N17: =L17-M17 -> 5458465.7 | R17: =SUM(O17:Q17) -> 0 | S17: 5448761.5 | T17: =E17-X17 -> 8396.2742 | U17: =F17-Y17 -> 1307.9177 | V17: =SUM(S17:U17) -> 5458465.7 | Z17: =SUM(W17:Y17) -> 0 | AA17: 4400579.5 | AB17: TOP - Sin aclaracion | AC17: =O17+S17+W17 -> 5448761.5 | AD17: =R17+V17+Z17 -> 5458465.7 | AE17: =G17-AD17 -> -0.017394756 | AF17: =D17-S17 -> 0 | AG17: Aplicar | AH17: 4 | AI17: 1 | AJ17: Sin comentarios del proveedor.(1 correo seguimiento) | AK17: CON CONTACTO | AL17: SIN ACLARACION | AM17: Yessica | AS17: 46050 | AV17: Se envia Manual y detalle NS 2025 | BA17: Se envia Manual y detalle NS 2025 | BB17: =VLOOKUP(B17,contactos!$A$1:$D$484,4,FALSE) -> juan.hernandez@kraftheinz.com
B18: 61713 | C18: MALTA TEXO DE MEXICO SA DE CV | D18: 4432996.1 | E18: 0 | F18: 709279.41 | G18: 5142275.5 | H18: 2790756.5 | I18: =O18+S18 -> 2938945.2 | K18: =I18-J18 -> 2938945.2 | L18: =R18+V18 -> 3409176.4 | N18: =L18-M18 -> 3409176.4 | O18: 2405824.6 | Q18: 384931.93 | R18: =SUM(O18:Q18) -> 2790756.5 | S18: 533120.62 | T18: =E18-X18 -> 0 | U18: =S18*16% -> 85299.299 | V18: =SUM(S18:U18) -> 618419.92 | W18: 1494050.9 | Y18: 239048.17 | Z18: =SUM(W18:Y18) -> 1733099.1 | AA18: 9975341.2 | AB18: TOP - Sin aclaracion | AC18: =O18+S18+W18 -> 4432996.2 | AD18: =R18+V18+Z18 -> 5142275.5 | AE18: =G18-AD18 -> -0.019200001 | AG18: Revisión | AH18: 4 | AI18: 5 | AJ18: Proveedor quedó en compartir evidencia adicional esta semana 23-feb-2026, aprobacion de compras Soriana de omisión de cobros. | AK18: CON CONTACTO | AL18: PDTE POR PROVEEDOR | AM18: Raul | AS18: 46050 | AV18: Se le manda correo al proveedor, informandole sobre la auditoria del 2025 | AW18: Casos abiertos( En proceso) | BB18: =VLOOKUP(B18,contactos!$A$1:$D$484,4,FALSE) -> Oscar Daniel Rios Garcia
B19: 398024 | C19: PINSA COMERCIAL SA DE CV | D19: 4901364.6 | E19: 0 | F19: 0 | G19: 4901364.6 | H19: 4901364.6 | I19: =O19+S19 -> 1444913.9 | J19: 0 | K19: =I19-J19 -> 1444913.9 | L19: =R19+V19 -> 1444913.9 | M19: 0 | N19: =L19-M19 -> 1444913.9 | R19: =SUM(O19:Q19) -> 0 | S19: =G19-W19 -> 1444913.9 | T19: =E19-X19 -> 0 | U19: =F19-Y19 -> 0 | V19: =SUM(S19:U19) -> 1444913.9 | W19: 3456450.7 | Y19: =W19*0 -> 0 | Z19: =SUM(W19:Y19) -> 3456450.7 | AA19: 20851675 | AB19: TOP - Sin aclaracion | AC19: =O19+S19+W19 -> 4901364.6 | AD19: =R19+V19+Z19 -> 4901364.6 | AE19: =G19-AD19 -> 0 | AF19: =D19-S19 -> 3456450.7 | AG19: Aplicar | AH19: 4 | AI19: 1 | AJ19: 0 | AK19: CON CONTACTO | AL19: SIN ACLARACION | AM19: Yessenia | BB19: =VLOOKUP(B19,contactos!$A$1:$D$484,4,FALSE) -> lcedillo@pinsa.com
B20: 34934 | C20: CARVAJAL EDUCACION S.A. DE C.V. | D20: 4076300.2 | E20: 0 | F20: 652208.03 | G20: 4728508.2 | H20: 0 | I20: =O20+S20 -> 1718185 | K20: =I20-J20 -> 1718185 | L20: =R20+V20 -> 1993094.6 | N20: =L20-M20 -> 1993094.6 | O20: 1718185 | P20: 0 | Q20: 274909.6 | R20: =SUM(O20:Q20) -> 1993094.6 | S20: 0 | T20: 0 | U20: =S20*16% -> 0 | V20: =SUM(S20:U20) -> 0 | W20: 2358115 | X20: 0 | Y20: 377298.43 | Z20: =SUM(W20:Y20) -> 2735413.4 | AA20: 11263016 | AB20: TOP - Aclaracion | AC20: =O20+S20+W20 -> 4076300 | AD20: =R20+V20+Z20 -> 4728508 | AE20: =G20-AD20 -> 0.2 | AG20: Revisión | AH20: 4 | AI20: 6 | AJ20: 03-03-2026 - En reunión presencial con el proveedor, este presenta soportes que disminuyen el valor de la diferencia presentada - se hace recalculo y se vuelve a enviar al proveedor para su aceptación 16-feb-2026 se informa a proveedor que el soporte que envia (Oleaje, resurtidos) no especicifa los pedidos publicados. | AK20: CON CONTACTO | AL20: PDTE POR PROVEEDOR | AM20: Marcela | AN20: 4728508.2 | AO20: REEMBOLSO DEL CARGO | AP20: 6 | AR20: 46050 | AS20: 46050 | AV20: Proveedor comparte soportes del no cobro de NS | AX20: X | BB20: =VLOOKUP(B20,contactos!$A$1:$D$484,4,FALSE) -> OMAR.JURADO@CARVAJAL.COM
B21: 38893 | C21: ABSORMEX CMPC TISSUE SA DE CV | D21: 3414125.4 | E21: 0 | F21: 546260.19 | G21: 3960385.4 | H21: 3960385.6 | I21: =O21+S21 -> 3414125.4 | K21: =I21-J21 -> 3414125.4 | L21: =R21+V21 -> 3960385.6 | N21: =L21-M21 -> 3960385.6 | R21: =SUM(O21:Q21) -> 0 | S21: 3414125.4 | T21: =E21-X21 -> 0 | U21: =F21-Y21 -> 546260.19 | V21: =SUM(S21:U21) -> 3960385.6 | Z21: =SUM(W21:Y21) -> 0 | AA21: 10412714 | AB21: TOP - Sin aclaracion | AC21: =O21+S21+W21 -> 3414125.4 | AD21: =R21+V21+Z21 -> 3960385.6 | AE21: =G21-AD21 -> -0.144361 | AF21: =D21-S21 -> 0 | AG21: Revisión | AH21: 4 | AI21: 8 | AJ21: 08 contactos 29 ene: Agenda de reunion via TEAMs 03 feb: reunion via TEAMS donde se deja claro que el tiempo estimado para NS2025 no se mueve. 04 feb: Proveedor indica que la metodologia de liquidacion presenta diferencias.Se solicita compartir el detalle. 10 feb : Proveedor envia detalle 18-feb-2026 se aclaró con proveedor la metodología del calculo y se solicitó enviar evidencias. 25 feb: Se envia correo al Proveedor solicitando la revisión e informando que debemos cerrar en febrero 2026. 27 feb 2026: El proveedor envia correo informando que esta revisando que le demos al finalizar la próxima semana 27 feb 2026: Auditoria envia correo solicitando nos compartan las revisiones que ya tengan listas, dado que se otorgo una prorroga al 04 de marzo para cerrar. | AK21: CON CONTACTO | AL21: PDTE POR PROVEEDOR | AM21: Yessenia | AS21: 46051 | AU21: 46056 | AV21: 29 ene 2026: el proveedor envia correo informando que esta revisando el detalle y requiere una plazo de 30 dias. Auditoria envia respuesta informando que no es posible ampliar el plazo dado que es un proceso a nivel institucional, no obstante estamos en disposición de apoyar en cualquier inquietud, duda o información adicional.//03 feb reunión con Proveedor se informo que el plazo no se puede extender y quedaron de enviar soportes en la tarde/ | AW21: Casos abiertos( En proceso) | AY21: SI | BA21: Se acercó el proveedor con Andrea solicitando el detalle correspondiente. | BB21: =VLOOKUP(B21,contactos!$A$1:$D$484,4,FALSE) -> irais.quiroga@softys.com
B22: 44040 | C22: LA MADRILENA, S.A. | D22: 2578675.1 | E22: 692321.96 | F22: 523359.53 | G22: 3794356.6 | H22: 0 | I22: =O22+S22 -> 359743.56 | K22: =I22-J22 -> 359743.56 | L22: =R22+V22 -> 532146.53 | N22: =L22-M22 -> 532146.53 | R22: =SUM(O22:Q22) -> 0 | S22: 359743.56 | T22: 99003.45 | U22: 73399.52 | V22: =SUM(S22:U22) -> 532146.53 | W22: 2218931.6 | X22: 593318.51 | Y22: 449960.01 | Z22: =SUM(W22:Y22) -> 3262210.1 | AA22: 3854818.9 | AB22: TOP - Sin aclaracion | AC22: =O22+S22+W22 -> 2578675.1 | AD22: =R22+V22+Z22 -> 3794356.6 | AE22: =G22-AD22 -> -0.010000004 | AG22: Revisión | AH22: 4 | AI22: 8 | AJ22: Se envìo correo el 20-feb-26 nitificando el resultado despues de realizar la revisión de la inforamación recibida,se solicto soportes del saldo pendiente S informa al proveedor el importe pendiente de soportes con el resultado final del analisis segun información recibida, se obtienes respuesta de su parte confirmando la información recibida | AK22: CON CONTACTO | AL22: PDTE POR PROVEEDOR | AM22: Olfi | AS22: 46050 | AT22: Si | AV22: Se le manda correo al proveedor, informandole sobre la auditoria del 2025 Se revisa soportes recibidos los cuales no son procedentes, se soliciat soportes que validen el archivo adjunto y se vuelve a enviar la información Proveedor envia estado de cuenta donde se visualizan los pedidos con pagos aplicados de lo que se reclaman, se realiza cruce de archivo de salida con soporte y se descarga el resultado de SAP para cotejar la información | AY22: X | BB22: =VLOOKUP(B22,contactos!$A$1:$D$484,4,FALSE) -> mrgarciac@bepensa.com
B23: 54569 | C23: FERRERO DE MEXICO SA DE CV | D23: 3454984.1 | E23: 266374.18 | F23: 0 | G23: 3721358.3 | H23: 0 | I23: =O23+S23 -> 3454984.1 | K23: =I23-J23 -> 3454984.1 | L23: =R23+V23 -> 3721358.3 | N23: =L23-M23 -> 3721358.3 | R23: =SUM(O23:Q23) -> 0 | S23: 3454984.1 | T23: =E23-X23 -> 266374.18 | U23: =F23-Y23 -> 0 | V23: =SUM(S23:U23) -> 3721358.3 | Z23: =SUM(W23:Y23) -> 0 | AA23: 9146362.9 | AB23: TOP - Sin aclaracion | AC23: =O23+S23+W23 -> 3454984.1 | AD23: =R23+V23+Z23 -> 3721358.3 | AE23: =G23-AD23 -> -0.034031139 | AF23: =D23-S23 -> 0 | AG23: Revisión | AH23: 4 | AI23: 2 | AJ23: 05 de marzo - se envia correo de seguimiento al proveedor, solicitando respuesta, e informado que de no recibir respuesta se aplicará el cargo 24 de febrero - se envia al proveedor detalle del importe publicado 20 de febrero Carmen de aclaraciones solicita nos acerquemos con proveedor para compartir detalle de pedidos, se manda información a proveedor información el 24 de febrero | AK23: CON CONTACTO | AL23: PDTE POR AUDITORIA | AM23: Marcela | AP23: 12 | AR23: 46076 | AS23: 46050 | AV23: 28 de enero: Se envía correo con información de detalle de ns. 23 de febereo 2026: proveedor revisa con depto. de servicio a proveedores algunas aclaraciones y solicitó detalle del cargo publicado e ingreso el 19 de febrero folios de aclaración. | BB23: =VLOOKUP(B23,contactos!$A$1:$D$484,4,FALSE) -> danielrodrigo.alonso@ferrero.com
B24: 17921 | C24: PRODUCTOS INTERNACIONALES MABE S.A. | D24: 3189882.4 | E24: 0 | F24: 510061.55 | G24: 3699944 | H24: 1438808 | I24: =O24+S24 -> 3189882.4 | K24: =I24-J24 -> 3189882.4 | L24: =R24+V24 -> 3699944 | N24: =L24-M24 -> 3699944 | R24: =SUM(O24:Q24) -> 0 | S24: 3189882.4 | T24: =E24-X24 -> 0 | U24: =F24-Y24 -> 510061.55 | V24: =SUM(S24:U24) -> 3699944 | Z24: =SUM(W24:Y24) -> 0 | AA24: 7893271.1 | AB24: TOP - Sin aclaracion | AC24: =O24+S24+W24 -> 3189882.4 | AD24: =R24+V24+Z24 -> 3699944 | AE24: =G24-AD24 -> 0.055542002 | AF24: =D24-S24 -> 0 | AG24: Revisión | AH24: 4 | AI24: 8 | AJ24: 08 contactos 29 ene: Agenda de reunion via TEAMs 03 feb: reunion via TEAMS donde se deja claro que el tiempo estimado para NS2025 no se mueve. 04 feb: Proveedor indica que la metodologia de liquidacion presenta diferencias.Se solicita compartir el detalle. 10 feb : Proveedor envia detalle 18-feb-2026 se aclaró con proveedor la metodología del calculo y se solicitó enviar evidencias. 25 feb: Se envia correo al Proveedor solicitando la revisión e informando que debemos cerrar en febrero 2026. 27 feb 2026: El proveedor envia correo informando que esta revisando que le demos al finalizar la próxima semana 27 feb 2026: Auditoria envia correo solicitando nos compartan las revisiones que ya tengan listas, dado que se otorgo una prorroga al 04 de marzo para cerrar. | AK24: CON CONTACTO | AL24: PDTE POR PROVEEDOR | AM24: Sareé | AS24: 46050 | AV24: Se le manda correo al proveedor, informandole sobre la auditoria del 2025// 29 ene 2026: el proveedor envia correo informando que esta revisando el detalle y requiere una plazo de 30 dias. Auditoria envia respuesta informando que no es posible ampliar el plazo dado que es un proceso a nivel institucional, no obstante estamos en disposición de apoyar en cualquier inquietud, duda o información adicional.//03 feb reunión con Proveedor se informo que el plazo no se puede extender y quedaron de enviar soportes en la tarde./04 feb : el proveedor envia correo informando que presenta diferencia en la metodologia y que tiene un valor de $868k de ordenes no canceladas y $263K cantidad cancelada menor a la que se reclama. El proveedor solicita el detalle que indique lo que no se entrego. Auditoria envia el archivo de NS ene- ago 2025 de NS donde se detalla por OC la penalizacion y se solicita coloque una columna donde marque las incidencias y otra columna donde realice el calculo segun su metodologia. | AW24: Casos abiertos( En proceso) | AY24: SI | BB24: =VLOOKUP(B24,contactos!$A$1:$D$484,4,FALSE) -> javierhernando.rodriguez@softys.com
B25: 9381 | C25: CHURCH & DWIGHT,S. DE R.L. DE C.V. | D25: 2846318.2 | E25: 0 | F25: 454431.78 | G25: 3300750 | H25: 3300750 | I25: =O25+S25 -> 2846318.2 | K25: =I25-J25 -> 2846318.2 | L25: =R25+V25 -> 3300750 | N25: =L25-M25 -> 3300750 | R25: =SUM(O25:Q25) -> 0 | S25: 2846318.2 | T25: =E25-X25 -> 0 | U25: =F25-Y25 -> 454431.78 | V25: =SUM(S25:U25) -> 3300750 | Z25: =SUM(W25:Y25) -> 0 | AA25: 5586012.1 | AB25: TOP - Aclaracion | AC25: =O25+S25+W25 -> 2846318.2 | AD25: =R25+V25+Z25 -> 3300750 | AE25: =G25-AD25 -> 0.046534983 | AF25: =D25-S25 -> 0 | AG25: Aplicar | AH25: 4 | AI25: 3 | AJ25: 29 ene: Agenda de reunion via TEAMs | AK25: CON CONTACTO | AL25: PDTE POR PROVEEDOR | AM25: Francisco | AR25: 46044 | AS25: 46044 | AV25: Proveedor se acercò a revisar la Auditoria 20-24 y solicitar lo que respecta al 2025, se encuentra en validaciòn. 20feb2026 Lo esta haciendo a nivel pedido. | AY25: X | BA25: Proveedor se acercò a revisar la Auditoria 20-24 y solicitar lo que respecta al 2025, se encuentra en validaciòn | BB25: =VLOOKUP(B25,contactos!$A$1:$D$484,4,FALSE) -> jesus.vidales@churchdwight.com
B26: 24489 | C26: REGALOS SIGLO XXI | D26: 2734026.4 | E26: 0 | F26: 437444.47 | G26: 3171470.8 | H26: 3171470.9 | I26: =O26+S26 -> 2734026.4 | K26: =I26-J26 -> 2734026.4 | L26: =R26+V26 -> 3171470.9 | N26: =L26-M26 -> 3171470.9 | R26: =SUM(O26:Q26) -> 0 | S26: 2734026.4 | T26: =E26-X26 -> 0 | U26: =F26-Y26 -> 437444.47 | V26: =SUM(S26:U26) -> 3171470.9 | Z26: =SUM(W26:Y26) -> 0 | AA26: 2280092.9 | AB26: TOP - Sin aclaracion | AC26: =O26+S26+W26 -> 2734026.4 | AD26: =R26+V26+Z26 -> 3171470.9 | AE26: =G26-AD26 -> -0.11107753 | AF26: =D26-S26 -> 0 | AG26: Aplicar | AH26: 4 | AI26: 4 | AJ26: 03 feb: reunion via TEAMS donde se deja claro que el tiempo estimado para NS2025 no se mueve. | AK26: CON CONTACTO | AL26: SIN ACLARACION | AM26: Raul | AS26: 46050 | AV26: Se le manda correo al proveedor, informandole sobre la auditoria del 2025 | BB26: =VLOOKUP(B26,contactos!$A$1:$D$484,4,FALSE) -> nayellivl@regalossigloxxi.com.mx
B27: 71217 | C27: EDGEWELL PERSONAL CARE MEXICO | D27: 2714666.1 | E27: 0 | F27: 430920.01 | G27: 3145586 | H27: 0 | I27: =O27+S27 -> 2714666.1 | K27: =I27-J27 -> 2714666.1 | L27: =R27+V27 -> 3145586.1 | N27: =L27-M27 -> 3145586.1 | O27: =D27 -> 2714666.1 | Q27: =F27 -> 430920.01 | R27: =SUM(O27:Q27) -> 3145586.1 | S27: 0 | T27: =E27-X27 -> 0 | U27: 0 | V27: =SUM(S27:U27) -> 0 | Z27: =SUM(W27:Y27) -> 0 | AA27: 5458542 | AB27: TOP - Aclaracion | AC27: =O27+S27+W27 -> 2714666.1 | AD27: =R27+V27+Z27 -> 3145586.1 | AE27: =G27-AD27 -> -0.090790675 | AF27: =D27-S27 -> 2714666.1 | AG27: Aplicar | AH27: 4 | AI27: 4 | AJ27: 06 Marzo. Proveedor indica no cuenta con dudas respecto al cargo de la Auditoria por NS 2025. | AK27: CON CONTACTO | AL27: PDTE POR PROVEEDOR | AM27: Mario | AR27: 46048 | AS27: 46048 | AV27: Se tuvo reuniòn con Proveedor para revisar la parte del 20-24 y se presentò lo del 2025, se encuentran en proceso de descarga de los pedidos penalziados. | AY27: X | BA27: Se tuvo reuniòn con Proveedor para revisar la parte del 20-24 y se presentò lo del 2025, se encuentran en proceso de descarga de los pedidos penalziados. | BB27: =VLOOKUP(B27,contactos!$A$1:$D$484,4,FALSE) -> mauriciorene.perez@edgewell.com
B28: 80622 | C28: 3M MEXICO SA DE CV | D28: 2556718.5 | E28: 0 | F28: 409074.99 | G28: 2965793.5 | H28: 2310641.6 | I28: =O28+S28 -> 1991932.4 | K28: =I28-J28 -> 1991932.4 | L28: =R28+V28 -> 2310641.6 | N28: =L28-M28 -> 2310641.6 | O28: =R28/1.16 -> 1991932.4 | Q28: =R28-O28 -> 318709.19 | R28: 2310641.6 | S28: 0 | T28: =E28-X28 -> 0 | U28: 0 | V28: =SUM(S28:U28) -> 0 | W28: 564786.06 | Y28: =W28*16% -> 90365.77 | Z28: =SUM(W28:Y28) -> 655151.83 | AA28: 6887053.2 | AB28: TOP - Sin aclaracion | AC28: =O28+S28+W28 -> 2556718.5 | AD28: =R28+V28+Z28 -> 2965793.5 | AE28: =G28-AD28 -> 0.02845608 | AF28: =D28-S28 -> 2556718.5 | AG28: Revisión | AH28: 4 | AI28: 0 | AJ28: Proveedor envía soporte de lo no procedente y se confirma por parte de la Auditoria el resultado aceptaod. | AK28: CON CONTACTO | AL28: PDTE POR AUDITORIA | AM28: Perla | AN28: 2362760 | AO28: EL PEDIDO FUE CANCELADO EN TIEMPO, NO PROCEDE | AP28: 4 | AR28: 46058 | AS28: 46051 | AV28: EN validaciòn de soporte | BB28: =VLOOKUP(B28,contactos!$A$1:$D$484,4,FALSE) -> aespinosacruz@mmm.com
B29: 7875 | C29: LINGERIX SA DE CV | D29: 2514428.2 | E29: 0 | F29: 402308.46 | G29: 2916736.6 | H29: 1259442.8 | I29: =O29+S29 -> 2514428.2 | K29: =I29-J29 -> 2514428.2 | L29: =R29+V29 -> 2916736.6 | N29: =L29-M29 -> 2916736.6 | R29: =SUM(O29:Q29) -> 0 | S29: 2514428.2 | T29: =E29-X29 -> 0 | U29: =F29-Y29 -> 402308.46 | V29: =SUM(S29:U29) -> 2916736.6 | Z29: =SUM(W29:Y29) -> 0 | AA29: 1864880.4 | AB29: TOP - Sin aclaracion | AC29: =O29+S29+W29 -> 2514428.2 | AD29: =R29+V29+Z29 -> 2916736.6 | AE29: =G29-AD29 -> -0.032818869 | AF29: =D29-S29 -> 0 | AG29: Aplicar | AH29: 4 | AI29: 1 | AJ29: 18-feb-2026 se aclaró con proveedor la metodología del calculo y se solicitó enviar evidencias. | AK29: CON CONTACTO | AL29: SIN ACLARACION | AM29: Yessica | AS29: 46050 | AT29: 29-01-2026 | AV29: Se envia Manual y detalle NS 2025 | BA29: PROVEEDOR CONFIRMA RECIBIDO Y SOLICITÓ AMPLIACION DE PLAZO | BB29: =VLOOKUP(B29,contactos!$A$1:$D$484,4,FALSE) -> favalle@assatex.com
B30: 313387 | C30: NATURASOL S.A. DE C.V. | D30: 2678050.9 | E30: 145825.82 | F30: 0 | G30: 2823876.7 | H30: 2823876.7 | I30: =O30+S30 -> 2678050.9 | K30: =I30-J30 -> 2678050.9 | L30: =R30+V30 -> 2823876.7 | N30: =L30-M30 -> 2823876.7 | R30: =SUM(O30:Q30) -> 0 | S30: 2678050.9 | T30: =E30-X30 -> 145825.82 | U30: =F30-Y30 -> 0 | V30: =SUM(S30:U30) -> 2823876.7 | Z30: =SUM(W30:Y30) -> 0 | AA30: 7033118.2 | AB30: TOP - Sin aclaracion | AC30: =O30+S30+W30 -> 2678050.9 | AD30: =R30+V30+Z30 -> 2823876.7 | AE30: =G30-AD30 -> -0.00036524329 | AF30: =D30-S30 -> 0 | AG30: Aplicar | AH30: 4 | AI30: 1 | AJ30: 25 feb: Se envia correo al Proveedor solicitando la revisión e informando que debemos cerrar en febrero 2026. | AK30: CON CONTACTO | AL30: SIN ACLARACION | AM30: Sareé | AS30: 46050 | AV30: Se le manda correo al proveedor, informandole sobre la auditoria del 2025 | BB30: =VLOOKUP(B30,contactos!$A$1:$D$484,4,FALSE) -> montserrat.buendia@naturasol.com.mx
B31: 308421 | C31: PEDRO DOMECQ SA DE CV | D31: 1612446.7 | E31: 790165.74 | F31: 384417.99 | G31: 2787030.5 | H31: 2787030.5 | I31: =O31+S31 -> 175079.38 | J31: 0 | K31: =I31-J31 -> 175079.38 | L31: =R31+V31 -> 293132.01 | M31: 0 | N31: =L31-M31 -> 293132.01 | R31: =SUM(O31:Q31) -> 0 | S31: =D31-W31 -> 175079.38 | T31: =E31-X31 -> 77620.624 | U31: =F31-Y31 -> 40432.001 | V31: =SUM(S31:U31) -> 293132.01 | W31: 1437367.3 | X31: 712545.12 | Y31: 343985.99 | Z31: =SUM(W31:Y31) -> 2493898.4 | AA31: 1083868.5 | AB31: TOP - Sin aclaracion | AC31: =O31+S31+W31 -> 1612446.7 | AD31: =R31+V31+Z31 -> 2787030.4 | AE31: =G31-AD31 -> 0.11877878 | AF31: =D31-S31 -> 1437367.3 | AG31: Aplicar | AH31: 4 | AI31: 1 | AJ31: 27 feb 2026: El proveedor envia correo informando que esta revisando que le demos al finalizar la próxima semana | AK31: CON CONTACTO | AL31: SIN ACLARACION | AM31: Belem | BB31: =VLOOKUP(B31,contactos!$A$1:$D$484,4,FALSE) -> jamador@pedrodomecq.com
B32: 82511 | C32: HENKEL CAPITAL SA DE CV | D32: 2380059.3 | E32: 0 | F32: 380809.51 | G32: 2760868.8 | H32: 2760868.8 | I32: =O32+S32 -> 2380059.3 | K32: =I32-J32 -> 2380059.3 | L32: =R32+V32 -> 2760868.8 | N32: =L32-M32 -> 2760868.8 | R32: =SUM(O32:Q32) -> 0 | S32: 2380059.3 | T32: =E32-X32 -> 0 | U32: =F32-Y32 -> 380809.51 | V32: =SUM(S32:U32) -> 2760868.8 | Z32: =SUM(W32:Y32) -> 0 | AA32: 8524572 | AB32: TOP - Sin aclaracion | AC32: =O32+S32+W32 -> 2380059.3 | AD32: =R32+V32+Z32 -> 2760868.8 | AE32: =G32-AD32 -> -0.01879867 | AF32: =D32-S32 -> 0 | AG32: Aplicar | AH32: 4 | AI32: 1 | AJ32: 27 feb 2026: Auditoria envia correo solicitando nos compartan las revisiones que ya tengan listas, dado que se otorgo una prorroga al 04 de marzo para cerrar. | AK32: CON CONTACTO | AL32: SIN ACLARACION | AM32: raul | AS32: 46050 | AV32: Se le manda correo al proveedor, informandole sobre la auditoria del 2025 | BB32: =VLOOKUP(B32,contactos!$A$1:$D$484,4,FALSE) -> #N/A
B33: 21943 | C33: HENKEL CAPITAL SA DE CV | D33: 2292934.1 | E33: 0 | F33: 366869.46 | G33: 2659803.7 | H33: 2659803.7 | I33: =O33+S33 -> 2292934.1 | K33: =I33-J33 -> 2292934.1 | L33: =R33+V33 -> 2659803.6 | N33: =L33-M33 -> 2659803.6 | R33: =SUM(O33:Q33) -> 0 | S33: 2292934.1 | T33: =E33-X33 -> 0 | U33: =F33-Y33 -> 366869.46 | V33: =SUM(S33:U33) -> 2659803.6 | Z33: =SUM(W33:Y33) -> 0 | AA33: 17985209 | AB33: TOP - Sin aclaracion | AC33: =O33+S33+W33 -> 2292934.1 | AD33: =R33+V33+Z33 -> 2659803.6 | AE33: =G33-AD33 -> 0.059903516 | AF33: =D33-S33 -> 0 | AG33: Aplicar | AH33: 4 | AI33: 1 | AJ33: 1 contacto se le informa de la auditoria | AK33: CON CONTACTO | AL33: SIN ACLARACION | AM33: Raul | AS33: 46050 | AV33: Se le manda correo al proveedor, informandole sobre la auditoria del 2025 | BB33: =VLOOKUP(B33,contactos!$A$1:$D$484,4,FALSE) -> loreto.zalapa@henkel.com
B34: 364 | C34: MARINDUSTRIAS S.A. DE C.V. | D34: 2535880.7 | E34: 0 | F34: 0 | G34: 2535881.1 | H34: 2535880.7 | I34: =O34+S34 -> 2535880.7 | K34: =I34-J34 -> 2535880.7 | L34: =R34+V34 -> 2535880.7 | N34: =L34-M34 -> 2535880.7 | R34: =SUM(O34:Q34) -> 0 | S34: 2535880.7 | T34: =E34-X34 -> 0 | U34: =F34-Y34 -> 0 | V34: =SUM(S34:U34) -> 2535880.7 | Z34: =SUM(W34:Y34) -> 0 | AA34: 18199055 | AB34: TOP - Sin aclaracion | AC34: =O34+S34+W34 -> 2535880.7 | AD34: =R34+V34+Z34 -> 2535880.7 | AE34: =G34-AD34 -> 0.37418238 | AF34: =D34-S34 -> 0 | AG34: Aplicar | AH34: 4 | AI34: 1 | AJ34: 6 - feb -2026, Sin respuesta al dia hoy, se le solicito los soportes de cancelacion (1 correos de Seguimiento) | AK34: CON CONTACTO | AL34: PDTE POR PROVEEDOR | AM34: Yessenia | AN34: 260797.11 | AO34: REEMBOLOS DEBIDO A QUE EL PEDIDO NUCA SE VIO REFLEJADO | AP34: 1 | AR34: 46059 | AV34: compartió soportes que no justifican la improcedencia, se le informo sus soportes no son validos. Sin respuesta. | BB34: =VLOOKUP(B34,contactos!$A$1:$D$484,4,FALSE) -> hperalta@grupomar.mx
B35: 11914 | C35: HALEON CONSUMER HEALTHCARE MEXICO | D35: 2177336.9 | E35: 0 | F35: 348373.9 | G35: 2525710.9 | H35: 0 | I35: =O35+S35 -> 1721832.9 | J35: 0 | K35: =I35-J35 -> 1721832.9 | L35: =R35+V35 -> 2108224.7 | M35: 0 | N35: =L35-M35 -> 2108224.7 | O35: 1610934.5 | Q35: 257749.52 | R35: =SUM(O35:Q35) -> 1868684 | S35: =D35-(O35+W35) -> 110898.44 | T35: =E35-(P35+X35) -> 0 | U35: =G35-(R35+Z35) -> 128642.3 | V35: =SUM(S35:U35) -> 239540.74 | W35: 455503.97 | X35: 0 | Y35: 72880.64 | Z35: =SUM(W35:Y35) -> 528384.61 | AA35: 1195941.8 | AB35: TOP - Sin aclaracion | AC35: =O35+S35+W35 -> 2177336.9 | AD35: =R35+V35+Z35 -> 2636609.3 | AE35: =G35-AD35 -> -110898.44 | AF35: =D35-S35 -> 2066438.4 | AG35: Revisión | AH35: 4 | AI35: 5 | AJ35: Reunión con proveedor 24 feb 26, menciona saldo procedente, y confirmación de soportes que amparan improcedencia de 110K antes de imp, se dieron 3 seguimiento, una reunión presencial y una sesión | AK35: CON CONTACTO | AL35: PDTE POR AUDITORIA | AM35: Luis | AS35: 46050 | AV35: Se envía correo con información de detalle de ns | BB35: =VLOOKUP(B35,contactos!$A$1:$D$484,4,FALSE) -> mateo.x.mendoza@haleon.com
B36: 51698 | C36: BARDAHL DE MEXICO S. A. DE C. V. | D36: 2017199.9 | E36: 0 | F36: 322752 | G36: 2339951.9 | H36: 1207074.1 | I36: =O36+S36 -> 2017199.9 | K36: =I36-J36 -> 2017199.9 | L36: =R36+V36 -> 2339951.9 | N36: =L36-M36 -> 2339951.9 | R36: =SUM(O36:Q36) -> 0 | S36: 2017199.9 | T36: =E36-X36 -> 0 | U36: =F36-Y36 -> 322752 | V36: =SUM(S36:U36) -> 2339951.9 | Z36: =SUM(W36:Y36) -> 0 | AA36: 1820258.9 | AB36: TOP - Sin aclaracion | AC36: =O36+S36+W36 -> 2017199.9 | AD36: =R36+V36+Z36 -> 2339951.9 | AE36: =G36-AD36 -> 0.04752231 | AF36: =D36-S36 -> 0 | AG36: Aplicar | AH36: 4 | AI36: 1 | AJ36: Proveedor no mandas soportes de improcedencia se tuvo un contacto en correo el 28 de enero en el que se compartió la información de pedidos, en seguimiento del 2020-2024 proveedor hace una llamada el 20 de febrero pero no menciona nada con relación al ejercicio 2025 | AK36: CON CONTACTO | AL36: SIN ACLARACION | AM36: Marcela | AS36: 46050 | AV36: Se envía correo con información de detalle de ns | BB36: =VLOOKUP(B36,contactos!$A$1:$D$484,4,FALSE) -> francisca.lopez@bardahl.com.mx
B37: 12480 | C37: DETERGENTES Y JABONES SASIL SAPI SA | D37: 1963610.8 | E37: 0 | F37: 314177.73 | G37: 2277788.4 | H37: 1055297.2 | I37: =O37+S37 -> 1963610.8 | K37: =I37-J37 -> 1963610.8 | L37: =R37+V37 -> 2277788.5 | N37: =L37-M37 -> 2277788.5 | R37: =SUM(O37:Q37) -> 0 | S37: =+D37 -> 1963610.8 | T37: =E37-X37 -> 0 | U37: =F37-Y37 -> 314177.73 | V37: =SUM(S37:U37) -> 2277788.5 | Z37: =SUM(W37:Y37) -> 0 | AA37: 2552379.4 | AB37: TOP - Aclaracion | AC37: =O37+S37+W37 -> 1963610.8 | AD37: =R37+V37+Z37 -> 2277788.5 | AE37: =G37-AD37 -> -0.094975847 | AF37: =D37-S37 -> 0 | AG37: Aplicar | AH37: 4 | AI37: 5 | AJ37: Se enviò correo el 17-feb-26 indicando que se requiere la autorización del area comercial para desestimar unos pedidos que indican que se realizó una solicitud de configuración | AK37: CON CONTACTO | AL37: PDTE POR PROVEEDOR | AM37: Olfi | AN37: 2277788.4 | AO37: DETALLE DE LOS CARGOS EN EL PORTAL | AR37: 46038 | AS37: 46041 | AT37: Si | AV37: Proveedor solicito detalle y se le hizo llegar Se Indica que es necesario la solicitud de la autorización del area comercial para el tema de configuración de unos pedidos, proveedor tiene un seguimiento de esta solicitud | AW37: Casos abiertos( En proceso) | AY37: X | BA37: Raul Castillo recibio correo en cuenta soriana | BB37: =VLOOKUP(B37,contactos!$A$1:$D$484,4,FALSE) -> EESCAMILLA@SASIL.MX
B38: 11042 | C38: BEBIDAS INTERNACIONALES BEPENSA SA | D38: 1539286 | E38: 407910.77 | F38: 311551.54 | G38: 2258748.2 | H38: 0 | I38: =O38+S38 -> 1467671.4 | K38: =I38-J38 -> 1467671.4 | L38: =R38+V38 -> 2153661 | N38: =L38-M38 -> 2153661 | R38: =SUM(O38:Q38) -> 0 | S38: =D38-W38 -> 1467671.4 | T38: =E38-X38 -> 388932.9 | U38: =F38-Y38 -> 297056.74 | V38: =SUM(S38:U38) -> 2153661 | W38: 71614.62 | X38: 18977.87 | Y38: 14494.8 | Z38: =SUM(W38:Y38) -> 105087.29 | AA38: 1267567.6 | AB38: TOP - Sin aclaracion | AC38: =O38+S38+W38 -> 1539286 | AD38: =R38+V38+Z38 -> 2258748.3 | AE38: =G38-AD38 -> -0.12480254 | AG38: Revisión | AH38: 4 | AI38: 3 | AJ38: En revisión OC restantes | AK38: CON CONTACTO | AL38: PDTE POR PROVEEDOR | AM38: Sareé | AS38: 46050 | AV38: Proveedor envía soporte de OC ya cobradas | BB38: =VLOOKUP(B38,contactos!$A$1:$D$484,4,FALSE) -> dagarciad@bepensa.com
B39: 307988 | C39: 4E GLOBAL SAPI DE CV | D39: 1768456.2 | E39: 0 | F39: 282953 | G39: 2051409.4 | H39: 2051409.2 | I39: =O39+S39 -> 1768456.2 | K39: =I39-J39 -> 1768456.2 | L39: =R39+V39 -> 2051409.2 | N39: =L39-M39 -> 2051409.2 | R39: =SUM(O39:Q39) -> 0 | S39: 1768456.2 | T39: =E39-X39 -> 0 | U39: =F39-Y39 -> 282953 | V39: =SUM(S39:U39) -> 2051409.2 | Z39: =SUM(W39:Y39) -> 0 | AA39: 3579101.2 | AB39: TOP - Sin aclaracion | AC39: =O39+S39+W39 -> 1768456.2 | AD39: =R39+V39+Z39 -> 2051409.2 | AE39: =G39-AD39 -> 0.1417 | AF39: =D39-S39 -> 0 | AG39: Aplicar | AH39: 4 | AI39: 1 | AJ39: 0 | AK39: CON CONTACTO | AL39: SIN ACLARACION | AM39: Yessenia | BB39: =VLOOKUP(B39,contactos!$A$1:$D$484,4,FALSE) -> esilva@4eglobal.com
B40: 319178 | C40: NISSIN FOODS DE MEXICO SA DE CV | D40: 1899275.9 | E40: 0 | F40: 0 | G40: 1899275.9 | H40: 1307819.1 | I40: =O40+S40 -> 1307819.2 | K40: =I40-J40 -> 1307819.2 | L40: =R40+V40 -> 1307819.2 | N40: =L40-M40 -> 1307819.2 | R40: =SUM(O40:Q40) -> 0 | S40: =D40-O40-W40 -> 1307819.2 | T40: =E40-X40-P40 -> 0 | U40: =F40-Y40-Q40 -> 0 | V40: =SUM(S40:U40) -> 1307819.2 | W40: 591456.77 | X40: 0 | Y40: 0 | Z40: =SUM(W40:Y40) -> 591456.77 | AA40: 1312735.7 | AB40: TOP - Aclaracion | AC40: =O40+S40+W40 -> 1899275.9 | AD40: =R40+V40+Z40 -> 1899275.9 | AE40: =G40-AD40 -> -0.028144169 | AG40: Revisión | AH40: 4 | AI40: 4 | AJ40: En revisión OC restantes | AK40: CON CONTACTO | AL40: PDTE POR PROVEEDOR | AM40: Sareé | AR40: 46042 | AS40: 46043 | AV40: Proveedor comparte evidencia de OC ya cobradas por sistema. | AY40: X | BA40: Se contactó con Raúl vía correo solicitando el detalle | BB40: =VLOOKUP(B40,contactos!$A$1:$D$484,4,FALSE) -> CPERAZA@NISSINFOODS.COM.MX
B41: 7410 | C41: PRODUCTOS INTERNACIONALES MABE S.A. | D41: 1677791 | E41: 0 | F41: 220404.51 | G41: 1898195.6 | H41: 181552.84 | I41: =O41+S41 -> 1677791 | K41: =I41-J41 -> 1677791 | L41: =R41+V41 -> 1898195.5 | N41: =L41-M41 -> 1898195.5 | R41: =SUM(O41:Q41) -> 0 | S41: 1677791 | T41: =E41-X41 -> 0 | U41: =F41-Y41 -> 220404.51 | V41: =SUM(S41:U41) -> 1898195.5 | Z41: =SUM(W41:Y41) -> 0 | AA41: 6080952.8 | AB41: TOP - Sin aclaracion | AC41: =O41+S41+W41 -> 1677791 | AD41: =R41+V41+Z41 -> 1898195.5 | AE41: =G41-AD41 -> 0.071853234 | AF41: =D41-S41 -> 0 | AG41: Revisión | AH41: 4 | AI41: 8 | AJ41: 08 contactos 29 ene: Agenda de reunion via TEAMs 03 feb: reunion via TEAMS donde se deja claro que el tiempo estimado para NS2025 no se mueve. 04 feb: Proveedor indica que la metodologia de liquidacion presenta diferencias.Se solicita compartir el detalle. 10 feb : Proveedor envia detalle 18-feb-2026 se aclaró con proveedor la metodología del calculo y se solicitó enviar evidencias. 25 feb: Se envia correo al Proveedor solicitando la revisión e informando que debemos cerrar en febrero 2026. 27 feb 2026: El proveedor envia correo informando que esta revisando que le demos al finalizar la próxima semana 27 feb 2026: Auditoria envia correo solicitando nos compartan las revisiones que ya tengan listas, dado que se otorgo una prorroga al 04 de marzo para cerrar. | AK41: CON CONTACTO | AL41: PDTE POR PROVEEDOR | AM41: Andrea | AS41: 46050 | AV41: Se envía correo informando que el comunicado de cargo NS correspondiente al periodo de enero a agosto de 2025 ya se encuentra publicado en el Portal. El detalle del mismo también está disponible desglosado en el Portal. Se adjunta manual de visualizacion de Cargos.// 29 ene 2026: el proveedor envia correo informando que esta revisando el detalle y requiere una plazo de 30 dias. Auditoria envia respuesta informando que no es posible ampliar el plazo dado que es un proceso a nivel institucional, no obstante estamos en disposición de apoyar en cualquier inquietud, duda o información adicional.//03 feb reunión con Proveedor se informo que el plazo no se puede extender y quedaron de enviar soportes en la tarde./04 feb : el proveedor envia correo informando que presenta diferencia en la metodologia y que tiene un valor de $868k de ordenes no canceladas y $263K cantidad cancelada menor a la que se reclama. El proveedor solicita el detalle que indique lo que no se entrego. Auditoria envia el archivo de NS ene- ago 2025 de NS donde se detalla por OC la penalizacion y se solicita coloque una columna donde marque las incidencias y otra columna donde realice el calculo segun su metodologia. | AW41: Casos abiertos( En proceso) | AY41: SI | BB41: =VLOOKUP(B41,contactos!$A$1:$D$484,4,FALSE) -> javierhernando.rodriguez@softys.com
B42: 303974 | C42: Sales del Istmo SA de CV | D42: 1805198.3 | E42: 0 | F42: 0 | G42: 1805198.3 | H42: 1799385 | I42: =O42+S42 -> 1799385 | K42: =I42-J42 -> 1799385 | L42: =R42+V42 -> 1799385 | N42: =L42-M42 -> 1799385 | O42: 1799385 | R42: =SUM(O42:Q42) -> 1799385 | S42: 0 | T42: =E42-X42 -> 0 | U42: =F42-Y42 -> 0 | V42: =SUM(S42:U42) -> 0 | W42: 5813 | Z42: =SUM(W42:Y42) -> 5813 | AA42: 1301552.5 | AB42: TOP - Aclaracion | AC42: =O42+S42+W42 -> 1805198 | AD42: =R42+V42+Z42 -> 1805198 | AE42: =G42-AD42 -> 0.33 | AG42: Cerrado/Aplicar | AH42: 4 | AI42: 0 | AJ42: 0 | AK42: CON CONTACTO | AL42: CERRADO | AM42: Raul | AN42: 1805198.3 | AO42: DETALLE DE LOS CARGOS EN EL PORTAL | AP42: 16 | AQ42: NO | AR42: 46041 | AS42: 46041 | AV42: Proveedor comparte el resultado de su revisión | AW42: Casos abiertos( En proceso) | AX42: X | BA42: Se tiene reunión con Marco y comenta que el dia 29 de Enero dara un avance | BB42: =VLOOKUP(B42,contactos!$A$1:$D$484,4,FALSE) -> oscar.guzman@cydsa.com
B43: 29272 | C43: PRODUCTOS ALIMENTICIOS LA MODERNA S | D43: 1802449.2 | E43: 0 | F43: 0 | G43: 1802449.2 | H43: 1802449.2 | I43: =O43+S43 -> 1802449.2 | K43: =I43-J43 -> 1802449.2 | L43: =R43+V43 -> 1802449.2 | N43: =L43-M43 -> 1802449.2 | R43: =SUM(O43:Q43) -> 0 | S43: 1802449.2 | T43: =E43-X43 -> 0 | U43: =F43-Y43 -> 0 | V43: =SUM(S43:U43) -> 1802449.2 | Z43: =SUM(W43:Y43) -> 0 | AA43: 4135198.9 | AB43: TOP - Sin aclaracion | AC43: =O43+S43+W43 -> 1802449.2 | AD43: =R43+V43+Z43 -> 1802449.2 | AE43: =G43-AD43 -> -0.0033360324 | AF43: =D43-S43 -> 0 | AG43: Aplicar | AH43: 4 | AI43: 1 | AJ43: 28 de enero se envió correo de que se tenian 15 días para la revisión no se ha recibido respuesta | AK43: CON CONTACTO | AL43: SIN ACLARACION | AM43: Francisco | AS43: 46050 | AT43: 46050 | AV43: Proveedor requiere prorroga para terminar de valdiar informaciòn. | BB43: =VLOOKUP(B43,contactos!$A$1:$D$484,4,FALSE) -> aaviles@lamoderna.com.mx
B44: 21367 | C44: RB HEALTH MEXICO SA DE CV | D44: 1641249.7 | E44: 0 | F44: 84613.103 | G44: 1725862.8 | H44: 215041.48 | I44: =O44+S44 -> 1641249.7 | K44: =I44-J44 -> 1641249.7 | L44: =R44+V44 -> 1725862.8 | N44: =L44-M44 -> 1725862.8 | O44: 624456.69 | Q44: 63085.57 | R44: =SUM(O44:Q44) -> 687542.26 | S44: 1016793 | T44: =E44-X44 -> 0 | U44: =F44-Q44-Y44 -> 21527.533 | V44: =SUM(S44:U44) -> 1038320.6 | Z44: =SUM(W44:Y44) -> 0 | AA44: 3848800.8 | AB44: TOP - Sin aclaracion | AC44: =O44+S44+W44 -> 1641249.7 | AD44: =R44+V44+Z44 -> 1725862.8 | AE44: =G44-AD44 -> -0.0087244995 | AG44: Aplicar | AH44: 4 | AI44: 3 | AJ44: Se envio ultima notificación el 20 de feb con el resultado del analisis y se solicito soportes de lo que esta pendiente | AK44: CON CONTACTO | AL44: PDTE POR PROVEEDOR | AM44: Olfi | AS44: 46043 | AT44: SI | AU44: 46050 | AV44: Se tiene junta con proveedor, pendiente envio de bitacora. Se solicitó soportes a proveedor, aun sin respuesta, solo responde sobre un excel no adjunta evidencias. Se envia solicitud nuevamente de soportes de lo que no tiene evidencias | AY44: x | BB44: =VLOOKUP(B44,contactos!$A$1:$D$484,4,FALSE) -> MARGARITAGUADALUPE.GONZALEZ@RECKITT.COM
B45: 13835 | C45: PASTEURIZADORA MAULEC SA DE CV | D45: 1695399.3 | E45: 0 | F45: 0 | G45: 1695399.2 | H45: 1565314.2 | I45: =O45+S45 -> 1565314.3 | K45: =I45-J45 -> 1565314.3 | L45: =R45+V45 -> 1565314.3 | N45: =L45-M45 -> 1565314.3 | O45: =D45-W45 -> 1565314.3 | R45: =SUM(O45:Q45) -> 1565314.3 | T45: =E45-X45 -> 0 | U45: =F45-Y45 -> 0 | V45: =SUM(S45:U45) -> 0 | W45: 130085 | X45: 0 | Y45: 0 | Z45: =SUM(W45:Y45) -> 130085 | AA45: 3102758 | AB45: TOP - Sin aclaracion | AC45: =O45+S45+W45 -> 1695399.3 | AD45: =R45+V45+Z45 -> 1695399.3 | AE45: =G45-AD45 -> -0.0019490798 | AG45: Cerrado/Aplicar | AH45: 4 | AI45: 0 | AJ45: 0 | AK45: CON CONTACTO | AL45: CERRADO | AM45: Perla | AS45: 46051 | AV45: Proveedor otorga soporte de descatalogaciòn de SKU. | BB45: =VLOOKUP(B45,contactos!$A$1:$D$484,4,FALSE) -> lorenzol@maulec.com.mx
B46: 327197 | C46: H.U.T. INTERNACIONAL S.A. DE C.V. | D46: 1454493.1 | E46: 0 | F46: 232718.9 | G46: 1687212 | H46: 1191009.9 | I46: =O46+S46 -> 1026732.7 | K46: =I46-J46 -> 1026732.7 | L46: =R46+V46 -> 1191009.9 | N46: =L46-M46 -> 1191009.9 | O46: =D46-W46 -> 1026732.7 | Q46: 164277.23 | R46: =SUM(O46:Q46) -> 1191009.9 | T46: =E46-X46 -> 0 | U46: =F46-Q46-Y46 -> 0.0028253258 | V46: =SUM(S46:U46) -> 0.0028253258 | W46: 427760.43 | Y46: 68441.67 | Z46: =SUM(W46:Y46) -> 496202.1 | AA46: 427760.43 | AB46: TOP - Aclaracion | AC46: =O46+S46+W46 -> 1454493.1 | AD46: =R46+V46+Z46 -> 1687212 | AE46: =G46-AD46 -> 0.0082663875 | AG46: Cerrado/Aplicar | AH46: 4 | AI46: 0 | AJ46: 0 | AK46: CON CONTACTO | AL46: CERRADO | AM46: Yessica | AN46: 1228466.7 | AO46: NO APLICA EL CARGO DE NIVEL DE SERVICIO | AP46: 9 | AR46: 46049 | AS46: 46050 | AT46: 28-01-2026 | AU46: 29-01-2026 | AV46: Proveedor -acepta cargo despues de analisis de documentacion presentada argumenta no procede cargo porque cumplio a nivel orden de compra, se le aclaro el calculo es por codigo. | AX46: X | BA46: ENVIA DCOUMENTOS CON SOPORTES se tiene reunion con Se le informa que aquellos pedidos que indican no son proceden lo estan haciendo por el total de la orden de compra mas no el total del pedido - se tiene docuemnto detalle con comentarios | BB46: =VLOOKUP(B46,contactos!$A$1:$D$484,4,FALSE) -> msoto@hut.com.mx
B47: 16747 | C47: HOME TEXTILE DESIGNS SA DE CV | D47: 1363627.6 | E47: 0 | F47: 218180.43 | G47: 1581808 | H47: 0 | I47: =O47+S47 -> 1363627.6 | K47: =I47-J47 -> 1363627.6 | L47: =R47+V47 -> 1581808 | N47: =L47-M47 -> 1581808 | R47: =SUM(O47:Q47) -> 0 | S47: 1363627.6 | T47: =E47-X47 -> 0 | U47: =F47-Y47 -> 218180.43 | V47: =SUM(S47:U47) -> 1581808 | Z47: =SUM(W47:Y47) -> 0 | AA47: 3158791.8 | AB47: TOP - Aclaracion | AC47: =O47+S47+W47 -> 1363627.6 | AD47: =R47+V47+Z47 -> 1581808 | AE47: =G47-AD47 -> 0.012317 | AF47: =D47-S47 -> 0 | AG47: Aplicar | AH47: 4 | AI47: 2 | AJ47: 28-ene-2026 , se solicitó a proveedor los folios de aportacion del pago y evidencia de la omisión del cobro de otros pedidos. Sin respuesta al dia de hoy 23feb2026 | AK47: CON CONTACTO | AL47: PDTE POR PROVEEDOR | AM47: Yessenia | AN47: 1581808 | AO47: DETALLE DE LOS CARGOS EN EL PORTAL | AP47: 1 | AR47: 46041 | AS47: 46041 | AV47: Proveedor argumenta haber pagado por Aportaciones algunos pedidos. Otros soportes son Cancelación y ampliación de pedidos. No se identifica autorizacion por parte del área comercial, en espera de soporte firmado por parte del proveedor. | AX47: X | BA47: correo compartido por Ambriz Ruiz Jair Alejandro <jairar@soriana.com> | BB47: =VLOOKUP(B47,contactos!$A$1:$D$484,4,FALSE) -> ventas@homtex.com.mx
B48: 83394 | C48: MARINTER, SA DE C.V | D48: 1061916 | E48: 298798.97 | F48: 207398.18 | G48: 1568113.2 | H48: 82743.26 | I48: =O48+S48 -> 76727.77 | K48: =I48-J48 -> 76727.77 | L48: =R48+V48 -> 82743.287 | N48: =L48-M48 -> 82743.287 | O48: 76727.77 | P48: 3495.93 | Q48: 2519.59 | R48: =SUM(O48:Q48) -> 82743.29 | T48: =E48-P48-X48 -> 0.0040086854 | U48: =F48-Q48-Y48 -> -0.0074996305 | V48: =SUM(S48:U48) -> -0.0034909451 | W48: 985188.19 | X48: 295303.04 | Y48: 204878.6 | Z48: =SUM(W48:Y48) -> 1485369.8 | AA48: 1061916 | AB48: TOP - Aclaracion | AC48: =O48+S48+W48 -> 1061916 | AD48: =R48+V48+Z48 -> 1568113.1 | AE48: =G48-AD48 -> 0.053490945 | AG48: Cerrado/Aplicar | AH48: 4 | AI48: 0 | AJ48: 0 | AK48: CON CONTACTO | AL48: CERRADO | AM48: Yessica | AN48: 1484390.6 | AO48: DETALLE DE LOS CARGOS EN EL PORTAL | AP48: 2 | AR48: 46042 | AS48: 46042 | AV48: Mando soportes de productos descatalogados, no se ha identificado confirmacion del área comercial. el proveedor acepta monto por valor de $82,743.28 | AX48: X | BA48: correo compartido por Ambriz Ruiz Jair Alejandro <jairar@soriana.com> | BB48: =VLOOKUP(B48,contactos!$A$1:$D$484,4,FALSE) -> mrivas@marinter.com.mx
B49: 305 | C49: PEPSICO STRAUSS FRESH DIPS & SPREAD | D49: 1561609.4 | E49: 0 | F49: 0 | G49: 1561608.6 | H49: 0 | I49: =O49+S49 -> 1561609.4 | K49: =I49-J49 -> 1561609.4 | L49: =R49+V49 -> 1561609.4 | N49: =L49-M49 -> 1561609.4 | R49: =SUM(O49:Q49) -> 0 | S49: 1561609.4 | T49: =E49-X49 -> 0 | U49: =F49-Y49 -> 0 | V49: =SUM(S49:U49) -> 1561609.4 | Z49: =SUM(W49:Y49) -> 0 | AA49: 205657.02 | AB49: TOP - Sin aclaracion | AC49: =O49+S49+W49 -> 1561609.4 | AD49: =R49+V49+Z49 -> 1561609.4 | AE49: =G49-AD49 -> -0.83949741 | AF49: =D49-S49 -> 0 | AG49: Aplicar | AH49: 4 | AI49: 1 | AJ49: Sin contacto de proveedor | AK49: CON CONTACTO | AL49: SIN ACLARACION | AM49: Mario | AS49: 46051 | AV49: Auditoría ha enviado correo la información correspondiente para su confirmación de recibo | BB49: =VLOOKUP(B49,contactos!$A$1:$D$484,4,FALSE) -> mariana.espinoza@pepsico.com
B50: 34801 | C50: KOBLENZ ELECTRICA SA DE CV | D50: 1340024.6 | E50: 0 | F50: 214403.94 | G50: 1554428.6 | H50: 454253.26 | I50: =O50+S50 -> 1340024.6 | K50: =I50-J50 -> 1340024.6 | L50: =R50+V50 -> 1554428.6 | N50: =L50-M50 -> 1554428.6 | R50: =SUM(O50:Q50) -> 0 | S50: 1340024.6 | T50: =E50-X50 -> 0 | U50: =F50-Y50 -> 214403.94 | V50: =SUM(S50:U50) -> 1554428.6 | Z50: =SUM(W50:Y50) -> 0 | AA50: 830451.08 | AB50: TOP - Sin aclaracion | AC50: =O50+S50+W50 -> 1340024.6 | AD50: =R50+V50+Z50 -> 1554428.6 | AE50: =G50-AD50 -> 0.0208 | AF50: =D50-S50 -> 0 | AG50: Aplicar | AH50: 4 | AI50: 1 | AJ50: 1 contacto se le informa de la publicación de pedidos en el portal | AK50: CON CONTACTO | AL50: SIN ACLARACION | AM50: Erika | AS50: 46050 | AV50: Se le manda correo al proveedor, informandole sobre la auditoria del 2025 | BB50: =VLOOKUP(B50,contactos!$A$1:$D$484,4,FALSE) -> godoyl@koblenz.com
B51: 312231 | C51: ABBOTT LABORATORIES DE MEXICO SA DE | D51: 1362282.3 | E51: 0 | F51: 184002.29 | G51: 1546284.5 | H51: 1546284.5 | I51: =O51+S51 -> 1362282.3 | K51: =I51-J51 -> 1362282.3 | L51: =R51+V51 -> 1546284.6 | N51: =L51-M51 -> 1546284.6 | R51: =SUM(O51:Q51) -> 0 | S51: 1362282.3 | T51: =E51-X51 -> 0 | U51: =F51-Y51 -> 184002.29 | V51: =SUM(S51:U51) -> 1546284.6 | Z51: =SUM(W51:Y51) -> 0 | AB51: TOP - Aclaracion | AC51: =O51+S51+W51 -> 1362282.3 | AD51: =R51+V51+Z51 -> 1546284.6 | AE51: =G51-AD51 -> -0.1044 | AF51: =D51-S51 -> 0 | AG51: Aplicar | AH51: 4 | AI51: 3 | AJ51: Soporte incompleto no justifica la no entrega, no esta autorizado por comercial. | AK51: CON CONTACTO | AL51: PDTE POR PROVEEDOR | AM51: Yessica | AR51: 46042 | AS51: 46042 | AV51: proveedor envia correos soportes donde Se revisó la conciliación y varios soportes no son válidos por falta de firma del área Comercial, por lo que las penalizaciones siguen procedentes. También se solicita evidencia de entrega para los casos donde se indica que la mercancía fue recibida al 100%. | AY51: X | BA51: Correo directo a cuenta del auditor | BB51: =VLOOKUP(B51,contactos!$A$1:$D$484,4,FALSE) -> angelariel.becerra@abbott.com
B52: 75390 | C52: RAGASA INDUSTRIAS SA DE CV | D52: 1455353.9 | E52: 0 | F52: 0 | G52: 1455353.9 | H52: 1384859.8 | I52: =O52+S52 -> 1384859.8 | K52: =I52-J52 -> 1384859.8 | L52: =R52+V52 -> 1384859.8 | N52: =L52-M52 -> 1384859.8 | R52: =SUM(O52:Q52) -> 0 | S52: 1384859.8 | T52: =E52-X52 -> 0 | U52: =F52-Y52 -> 0 | V52: =SUM(S52:U52) -> 1384859.8 | W52: 70494.15 | Z52: =SUM(W52:Y52) -> 70494.15 | AA52: 7322257.6 | AB52: TOP - Aclaracion | AC52: =O52+S52+W52 -> 1455353.9 | AD52: =R52+V52+Z52 -> 1455353.9 | AE52: =G52-AD52 -> 0 | AG52: Aplicar | AH52: 4 | AI52: 5 | AJ52: 19-feb-2026 Correo de área comercial Soriana, no está de acuerdo con los margenes del sistema y del cálculo. | AK52: CON CONTACTO | AL52: PDTE POR PROVEEDOR | AM52: Raul | AR52: 46041 | AS52: 46041 | AV52: Proveedor argumenta margenes diferentes a lo pactado, formato cocina no aplica NS y 4 pedidos cobrados por el sistema en automatico | AY52: X | BB52: =VLOOKUP(B52,contactos!$A$1:$D$484,4,FALSE) -> acaballero@ragasa.com.mx
B53: 379495 | C53: CORPORACION BEKAX SA DE CV | D53: 1308098.3 | E53: 92146.032 | F53: 6112.632 | G53: 1406356.8 | H53: 1406356.9 | I53: =O53+S53 -> 1308098.3 | K53: =I53-J53 -> 1308098.3 | L53: =R53+V53 -> 1406356.9 | N53: =L53-M53 -> 1406356.9 | R53: =SUM(O53:Q53) -> 0 | S53: 1308098.3 | T53: =E53-X53 -> 92146.032 | U53: =F53-Y53 -> 6112.632 | V53: =SUM(S53:U53) -> 1406356.9 | Z53: =SUM(W53:Y53) -> 0 | AA53: 2593149.7 | AB53: TOP - Sin aclaracion | AC53: =O53+S53+W53 -> 1308098.3 | AD53: =R53+V53+Z53 -> 1406356.9 | AE53: =G53-AD53 -> -0.084 | AF53: =D53-S53 -> 0 | AG53: Aplicar | AH53: 4 | AI53: 1 | AJ53: 0 | AK53: CON CONTACTO | AL53: SIN ACLARACION | AM53: Belem | BB53: =VLOOKUP(B53,contactos!$A$1:$D$484,4,FALSE) -> igonzalez@sinaxcorp.com
B54: 51987 | C54: CUETARA DISTRIBUCION SA DE CV | D54: 1298565.3 | E54: 103885.25 | F54: 0 | G54: 1402450.6 | H54: 1402450.5 | I54: =O54+S54 -> 1298565.3 | K54: =I54-J54 -> 1298565.3 | L54: =R54+V54 -> 1402450.6 | N54: =L54-M54 -> 1402450.6 | R54: =SUM(O54:Q54) -> 0 | S54: 1298565.3 | T54: =E54-X54 -> 103885.25 | U54: =F54-Y54 -> 0 | V54: =SUM(S54:U54) -> 1402450.6 | Z54: =SUM(W54:Y54) -> 0 | AA54: 3341364.5 | AB54: TOP - Sin aclaracion | AC54: =O54+S54+W54 -> 1298565.3 | AD54: =R54+V54+Z54 -> 1402450.6 | AE54: =G54-AD54 -> 0.0653985 | AF54: =D54-S54 -> 0 | AG54: Aplicar | AH54: 4 | AI54: 1 | AJ54: 1 contacto se le informa de la auditoria | AK54: CON CONTACTO | AL54: SIN ACLARACION | AM54: Raul | AS54: 46050 | AV54: Se le manda correo al proveedor, informandole sobre la auditoria del 2025 | BB54: =VLOOKUP(B54,contactos!$A$1:$D$484,4,FALSE) -> htorres@gcuetara.com.mx
B55: 14833 | C55: CIA SHERWIN WILLIAMS SA DE CV | D55: 1202006.4 | E55: 0 | F55: 192321.03 | G55: 1394327.6 | H55: 438343 | I55: =O55+S55 -> 1202006.4 | K55: =I55-J55 -> 1202006.4 | L55: =R55+V55 -> 1394327.4 | N55: =L55-M55 -> 1394327.4 | R55: =SUM(O55:Q55) -> 0 | S55: 1202006.4 | T55: =E55-X55 -> 0 | U55: =F55-Y55 -> 192321.03 | V55: =SUM(S55:U55) -> 1394327.4 | Z55: =SUM(W55:Y55) -> 0 | AA55: 989331.12 | AB55: TOP - Sin aclaracion | AC55: =O55+S55+W55 -> 1202006.4 | AD55: =R55+V55+Z55 -> 1394327.4 | AE55: =G55-AD55 -> 0.145944 | AF55: =D55-S55 -> 0 | AG55: Aplicar | AH55: 4 | AI55: 1 | AJ55: 0 | AK55: CON CONTACTO | AL55: SIN ACLARACION | AM55: Belem | BB55: =VLOOKUP(B55,contactos!$A$1:$D$484,4,FALSE) -> #N/A
B56: 55780 | C56: CLOROX DE MEXICO S DE RL DE CV | D56: 1199171 | E56: 0 | F56: 191867.47 | G56: 1391038.6 | H56: 1391038.6 | I56: =O56+S56 -> 1199171 | K56: =I56-J56 -> 1199171 | L56: =R56+V56 -> 1391038.4 | N56: =L56-M56 -> 1391038.4 | R56: =SUM(O56:Q56) -> 0 | S56: 1199171 | T56: =E56-X56 -> 0 | U56: =F56-Y56 -> 191867.47 | V56: =SUM(S56:U56) -> 1391038.4 | Z56: =SUM(W56:Y56) -> 0 | AA56: 5114529.1 | AB56: TOP - Sin aclaracion | AC56: =O56+S56+W56 -> 1199171 | AD56: =R56+V56+Z56 -> 1391038.4 | AE56: =G56-AD56 -> 0.11615165 | AF56: =D56-S56 -> 0 | AG56: Aplicar | AH56: 4 | AI56: 1 | AJ56: 01 contacto: envio de correo incial informando el detalle y adjuntando manual | AK56: CON CONTACTO | AL56: SIN ACLARACION | AM56: Andrea | AS56: 46050 | AV56: Se envía correo informando que el comunicado de cargo NS correspondiente al periodo de enero a agosto de 2025 ya se encuentra publicado en el Portal. El detalle del mismo también está disponible desglosado en el Portal. Se adjunta manual de visualizacion de Cargos. | AW56: Casos abiertos( En proceso) | BB56: =VLOOKUP(B56,contactos!$A$1:$D$484,4,FALSE) -> almagabriela.gomez@clorox.com
B57: 325258 | C57: SCHETTINO HERMANOS S DE RL DE CV | D57: 1374858.2 | E57: 0 | F57: 4352.8736 | G57: 1379211 | H57: 408636.88 | I57: =O57+S57 -> 323466.15 | K57: =I57-J57 -> 323466.15 | L57: =R57+V57 -> 326883.88 | N57: =L57-M57 -> 326883.88 | O57: 323466.15 | P57: 0 | Q57: 3417.73 | R57: =SUM(O57:Q57) -> 326883.88 | S57: =D57-O57-W57 -> -0.0016015626 | T57: =E57-X57-P57 -> 0 | U57: =F57-Y57-Q57 -> 0.0036 | V57: =SUM(S57:U57) -> 0.0019984374 | W57: 1051392 | X57: 0 | Y57: 935.14 | Z57: =SUM(W57:Y57) -> 1052327.1 | AA57: 1543899.4 | AB57: TOP - Sin aclaracion | AC57: =O57+S57+W57 -> 1374858.2 | AD57: =R57+V57+Z57 -> 1379211 | AE57: =G57-AD57 -> -0.0019984373 | AG57: Revisión | AH57: 4 | AI57: 4 | AJ57: En revisión OC que se cobran 100% | AK57: CON CONTACTO | AL57: PDTE POR PROVEEDOR | AM57: Sareé | AS57: 46050 | AV57: Se envían comentarios de auditoría para la parte restante | AY57: x | BB57: =VLOOKUP(B57,contactos!$A$1:$D$484,4,FALSE) -> jorgeperez@schettino.com.mx
B58: 137 | C58: SPECTRUM BRANDS DE MEXICO SA DE CV | D58: 1171057.7 | E58: 0 | F58: 187369.24 | G58: 1358427 | H58: 1358427 | I58: =O58+S58 -> 1171057.7 | K58: =I58-J58 -> 1171057.7 | L58: =R58+V58 -> 1358427 | N58: =L58-M58 -> 1358427 | R58: =SUM(O58:Q58) -> 0 | S58: 1171057.7 | T58: =E58-X58 -> 0 | U58: =F58-Y58 -> 187369.24 | V58: =SUM(S58:U58) -> 1358427 | Z58: =SUM(W58:Y58) -> 0 | AA58: 1717579.8 | AB58: TOP - Sin aclaracion | AC58: =O58+S58+W58 -> 1171057.7 | AD58: =R58+V58+Z58 -> 1358427 | AE58: =G58-AD58 -> 0.02907 | AF58: =D58-S58 -> 0 | AG58: Aplicar | AH58: 4 | AI58: 2 | AJ58: Proveedor no da respuesta, no presenta soportes, un seguimiento con la notificación del importe | AK58: CON CONTACTO | AL58: PDTE POR AUDITORIA | AM58: Luis | AS58: 46050 | AV58: Se envía correo con información de detalle de ns | BB58: =VLOOKUP(B58,contactos!$A$1:$D$484,4,FALSE) -> claudia.gutierrez2@la.spectrumbrands.com
B59: 389783 | C59: COMPA¥IA COMERCIALIZADORA PRODIN CE | D59: 1044840 | E59: 0 | F59: 167174.4 | G59: 1212014.4 | H59: 835771.34 | I59: =O59+S59 -> 1044840 | K59: =I59-J59 -> 1044840 | L59: =R59+V59 -> 1212014.4 | N59: =L59-M59 -> 1212014.4 | R59: =SUM(O59:Q59) -> 0 | S59: 1044840 | T59: =E59-X59 -> 0 | U59: =F59-Y59 -> 167174.4 | V59: =SUM(S59:U59) -> 1212014.4 | Z59: =SUM(W59:Y59) -> 0 | AA59: 857399.01 | AB59: TOP - Sin aclaracion | AC59: =O59+S59+W59 -> 1044840 | AD59: =R59+V59+Z59 -> 1212014.4 | AE59: =G59-AD59 -> 0.0046600001 | AF59: =D59-S59 -> 0 | AG59: Aplicar | AH59: 4 | AI59: 1 | AJ59: 1 contacto, se le informa al proveedor de la auditoria, proveedor comenta que si tiene alguna duda nos contacta. | AK59: CON CONTACTO | AL59: SIN ACLARACION | AM59: Sareé | AS59: 46050 | AV59: Se le manda correo al proveedor, informandole sobre la auditoria del 2025 | BB59: =VLOOKUP(B59,contactos!$A$1:$D$484,4,FALSE) -> #N/A
B60: 397984 | C60: COMARKET S.A. DE C.V. | D60: 1009288.6 | E60: 0 | F60: 161486.17 | G60: 1170774.8 | H60: 0 | I60: =O60+S60 -> 963290.75 | J60: 0 | K60: =I60-J60 -> 963290.75 | L60: =R60+V60 -> 1117417.3 | M60: 0 | N60: =L60-M60 -> 1117417.3 | R60: =SUM(O60:Q60) -> 0 | S60: =D60-W60 -> 963290.75 | T60: =E60-X60 -> 0 | U60: =F60-Y60 -> 154126.51 | V60: =SUM(S60:U60) -> 1117417.3 | W60: 45997.84 | X60: 0 | Y60: 7359.66 | Z60: =SUM(W60:Y60) -> 53357.5 | AA60: 7876893 | AB60: TOP - Sin aclaracion | AC60: =O60+S60+W60 -> 1009288.6 | AD60: =R60+V60+Z60 -> 1170774.8 | AE60: =G60-AD60 -> -0.0078369875 | AG60: Aplicado | AH60: 4 | AI60: 0 | AJ60: 0 | AK60: CON CONTACTO | AL60: PDTE POR PROVEEDOR | AM60: Yessenia | AN60: 1170774.8 | AO60: NO PROCEDE EL CARGO DEBIDO A QUE EL PROVEEDOR PIDIO LA AMPLIACION DEL PEDIDO | AP60: 6 | AR60: 46058 | AS60: 46059 | AT60: 46059 | AV60: presenta folio de aclaraiones de todos los importes , donde de los soportes presnetados no proceden 15,335.45 con impuestos incluidos, el resto se solicito soporte contundente | BB60: =VLOOKUP(B60,contactos!$A$1:$D$484,4,FALSE) -> armandoaguilar@comarket.com.mx
B61: 383349 | C61: CAPICO DISTRIBUCION S.A. DE C.V. | D61: 1141554 | E61: 0 | F61: 0 | G61: 1141554 | H61: 0 | I61: =O61+S61 -> 1141554 | K61: =I61-J61 -> 1141554 | L61: =R61+V61 -> 1141554 | N61: =L61-M61 -> 1141554 | R61: =SUM(O61:Q61) -> 0 | S61: 1141554 | T61: =E61-X61 -> 0 | U61: =F61-Y61 -> 0 | V61: =SUM(S61:U61) -> 1141554 | Z61: =SUM(W61:Y61) -> 0 | AB61: TOP - Aclaracion | AC61: =O61+S61+W61 -> 1141554 | AD61: =R61+V61+Z61 -> 1141554 | AE61: =G61-AD61 -> 0.0057528 | AF61: =D61-S61 -> 0 | AG61: Aplicar | AH61: 4 | AI61: 4 | AJ61: Proveedor información no contundente, dice tener un convenio actualizado de no negociación de FR se solicitó y aún no lo envía | AK61: CON CONTACTO | AL61: PDTE POR PROVEEDOR | AM61: Francisco | AR61: 46048 | AS61: 46048 | AV61: Proveedor otorga convenio en donde indica cancelaciòn, se esta validando la informaciòn | AY61: X | BA61: Proveedor se contacta para ver la Auditoria del 2020 -2024, posterior a esto se notifica la diferencia del ejercicio 2025. | BB61: =VLOOKUP(B61,contactos!$A$1:$D$484,4,FALSE) -> diego.fraustro@capico.com.mx
B62: 5330 | C62: NOVELTY CORP.DE MEXICO S.A. DE C.V. | D62: 961798.11 | E62: 0 | F62: 153887.7 | G62: 1115685.8 | H62: 1115685.8 | I62: =O62+S62 -> 961798.11 | K62: =I62-J62 -> 961798.11 | L62: =R62+V62 -> 1115685.8 | N62: =L62-M62 -> 1115685.8 | R62: =SUM(O62:Q62) -> 0 | S62: 961798.11 | T62: =E62-X62 -> 0 | U62: =F62-Y62 -> 153887.7 | V62: =SUM(S62:U62) -> 1115685.8 | Z62: =SUM(W62:Y62) -> 0 | AA62: 748824.76 | AB62: TOP - Aclaracion | AC62: =O62+S62+W62 -> 961798.11 | AD62: =R62+V62+Z62 -> 1115685.8 | AE62: =G62-AD62 -> 0.0124 | AF62: =D62-S62 -> 0 | AG62: Aplicar | AH62: 4 | AI62: 3 | AJ62: Proveedor no presenta soportes de improcedenica, ultima fecha de seguimiento 20 de febrero 2026, tres correos de seguimiento | AK62: CON CONTACTO | AL62: PDTE POR PROVEEDOR | AM62: Luis | AN62: 1115685.8 | AO62: DETALLE DE LOS CARGOS EN EL PORTAL | AP62: 3 | AQ62: NO | AR62: 46041 | AS62: 46041 | AT62: 46041 | AV62: Proveedor se encuentra en revisión del saldo compartido | AX62: X | BA62: Correo compartido por Ambriz Ruiz Jair Alejandro <jairar@soriana.com> | BB62: =VLOOKUP(B62,contactos!$A$1:$D$484,4,FALSE) -> kam3@noveltycorp.com
B63: 21845 | C63: PRODUCTORA MEXICANA DE ARROZ SAPI | D63: 1064364.9 | E63: 0 | F63: 0 | G63: 1064364.9 | H63: 1064364.9 | I63: =O63+S63 -> 1064364.9 | K63: =I63-J63 -> 1064364.9 | L63: =R63+V63 -> 1064364.9 | N63: =L63-M63 -> 1064364.9 | R63: =SUM(O63:Q63) -> 0 | S63: 1064364.9 | T63: =E63-X63 -> 0 | U63: =F63-Y63 -> 0 | V63: =SUM(S63:U63) -> 1064364.9 | Z63: =SUM(W63:Y63) -> 0 | AA63: 926636.9 | AB63: TOP - Sin aclaracion | AC63: =O63+S63+W63 -> 1064364.9 | AD63: =R63+V63+Z63 -> 1064364.9 | AE63: =G63-AD63 -> -7.8436686e-05 | AG63: Aplicar | AH63: 4 | AI63: 1 | AJ63: 0 | AK63: CON CONTACTO | AL63: SIN ACLARACION | AM63: Jessica | BB63: =VLOOKUP(B63,contactos!$A$1:$D$484,4,FALSE) -> #N/A
B64: 22068 | C64: ALTA EXTRACCION SA DE CV | D64: 1060303.7 | E64: 0 | F64: 0 | G64: 1060303.7 | H64: 0 | I64: =O64+S64 -> 1060303.7 | K64: =I64-J64 -> 1060303.7 | L64: =R64+V64 -> 1060303.7 | N64: =L64-M64 -> 1060303.7 | R64: =SUM(O64:Q64) -> 0 | S64: 1060303.7 | T64: =E64-X64 -> 0 | U64: =F64-Y64 -> 0 | V64: =SUM(S64:U64) -> 1060303.7 | Z64: =SUM(W64:Y64) -> 0 | AA64: 1136864.4 | AB64: TOP - Sin aclaracion | AC64: =O64+S64+W64 -> 1060303.7 | AD64: =R64+V64+Z64 -> 1060303.7 | AE64: =G64-AD64 -> 0.0096644519 | AF64: =D64-S64 -> 0 | AG64: Aplicar | AH64: 4 | AI64: 1 | AJ64: 0 | AK64: CON CONTACTO | AL64: SIN ACLARACION | AM64: Belem | BB64: =VLOOKUP(B64,contactos!$A$1:$D$484,4,FALSE) -> #N/A
B65: 58958 | C65: CINSA SA DE CV | D65: 912839.39 | E65: 0 | F65: 146054.36 | G65: 1058893.7 | H65: 76727.9 | I65: =O65+S65 -> 912839.39 | K65: =I65-J65 -> 912839.39 | L65: =R65+V65 -> 1058893.7 | N65: =L65-M65 -> 1058893.7 | R65: =SUM(O65:Q65) -> 0 | S65: 912839.39 | T65: =E65-X65 -> 0 | U65: =F65-Y65 -> 146054.36 | V65: =SUM(S65:U65) -> 1058893.7 | Z65: =SUM(W65:Y65) -> 0 | AA65: 763595.94 | AB65: TOP - Sin aclaracion | AC65: =O65+S65+W65 -> 912839.39 | AD65: =R65+V65+Z65 -> 1058893.7 | AE65: =G65-AD65 -> -0.0559 | AF65: =D65-S65 -> 0 | AG65: Aplicar | AH65: 4 | AI65: 2 | AJ65: Se le informa a proveedor sobre el comunicado dentro del portal | AK65: CON CONTACTO | AL65: SIN ACLARACION | AM65: Sareé | AS65: 46050 | AV65: Se le manda correo al proveedor, informandole sobre la auditoria del 2025 | BB65: =VLOOKUP(B65,contactos!$A$1:$D$484,4,FALSE) -> #N/A
B66: 387183 | C66: CU FOUNDATIONS SA DE CV | D66: 866011.35 | E66: 0 | F66: 138561.24 | G66: 1004572.6 | H66: 1004572.6 | I66: =O66+S66 -> 866011.35 | K66: =I66-J66 -> 866011.35 | L66: =R66+V66 -> 1004572.6 | N66: =L66-M66 -> 1004572.6 | R66: =SUM(O66:Q66) -> 0 | S66: 866011.35 | T66: =E66-X66 -> 0 | U66: =F66-Y66 -> 138561.24 | V66: =SUM(S66:U66) -> 1004572.6 | Z66: =SUM(W66:Y66) -> 0 | AA66: 831703.47 | AB66: TOP - Aclaracion | AC66: =O66+S66+W66 -> 866011.35 | AD66: =R66+V66+Z66 -> 1004572.6 | AE66: =G66-AD66 -> 0.042742154 | AF66: =D66-S66 -> 0 | AG66: Aplicar | AH66: 4 | AI66: 1 | AJ66: 1 contacto se le informa de la publicación de pedidos en el portal | AK66: CON CONTACTO | AL66: PDTE POR PROVEEDOR | AM66: Erika | AN66: 1004572.6 | AO66: DETALLE DE LOS CARGOS EN EL PORTAL | AP66: 7 | AQ66: NO | AR66: 46042 | AS66: =TODAY() -> 46212 | AT66: =TODAY() -> 46212 | AV66: Proveedor solicito detalle y se le hizo llegar | AW66: Casos abiertos( En proceso) | AX66: X | BB66: =VLOOKUP(B66,contactos!$A$1:$D$484,4,FALSE) -> #N/A
B67: 81422 | C67: NO SABE FALLAR S.A DE C.V. | D67: 862425.72 | E67: 0 | F67: 137988.12 | G67: 1000413.8 | H67: 1000413.8 | I67: =O67+S67 -> 862425.72 | K67: =I67-J67 -> 862425.72 | L67: =R67+V67 -> 1000413.8 | N67: =L67-M67 -> 1000413.8 | R67: =SUM(O67:Q67) -> 0 | S67: 862425.72 | T67: =E67-X67 -> 0 | U67: =F67-Y67 -> 137988.12 | V67: =SUM(S67:U67) -> 1000413.8 | Z67: =SUM(W67:Y67) -> 0 | AA67: 1254105.2 | AB67: TOP - Sin aclaracion | AC67: =O67+S67+W67 -> 862425.72 | AD67: =R67+V67+Z67 -> 1000413.8 | AE67: =G67-AD67 -> 0.0048000001 | AG67: Aplicar | AH67: 4 | AI67: 0 | AJ67: 0 | AK67: SIN CONTACTO | AL67: SIN ACLARACION | AM67: Jessica | BB67: =VLOOKUP(B67,contactos!$A$1:$D$484,4,FALSE) -> #N/A
B68: 394189 | C68: US COTTON MEXICO S DE RL DE CV | D68: 861532.13 | E68: 0 | F68: 137845.3 | G68: 999377.42 | H68: 999377.42 | I68: =O68+S68 -> 861532.13 | K68: =I68-J68 -> 861532.13 | L68: =R68+V68 -> 999377.43 | N68: =L68-M68 -> 999377.43 | R68: =SUM(O68:Q68) -> 0 | S68: 861532.13 | T68: =E68-X68 -> 0 | U68: =F68-Y68 -> 137845.3 | V68: =SUM(S68:U68) -> 999377.43 | Z68: =SUM(W68:Y68) -> 0 | AA68: 9004960.8 | AB68: NO ES TOP | AC68: =O68+S68+W68 -> 861532.13 | AD68: =R68+V68+Z68 -> 999377.43 | AE68: =G68-AD68 -> -0.010761643 | AF68: =D68-S68 -> 0 | AG68: Aplicar | AH68: 4 | AI68: 0 | AJ68: Sin acercamiento por parte del proveedor, actualmente pendiente auditoria del 2020-2024 | AK68: SIN CONTACTO | AL68: SIN ACLARACION | AM68: Erika | BB68: =VLOOKUP(B68,contactos!$A$1:$D$484,4,FALSE) -> irais.perez@uscotton.com
B69: 53256 | C69: PRONUA S.A. DE C.V. | D69: 825790.19 | E69: 0 | F69: 132126.43 | G69: 957916.6 | H69: 813643.35 | I69: =O69+S69 -> 701416.7 | K69: =I69-J69 -> 701416.7 | L69: =R69+V69 -> 813643.37 | N69: =L69-M69 -> 813643.37 | O69: =D69-W69 -> 701416.7 | P69: 0 | Q69: 112226.67 | R69: =SUM(O69:Q69) -> 813643.37 | S69: 0 | T69: =E69-X69 -> 0 | U69: =F69-Q69-Y69 -> 0 | V69: =SUM(S69:U69) -> 0 | W69: 124373.49 | X69: 0 | Y69: 19899.76 | Z69: =SUM(W69:Y69) -> 144273.25 | AA69: 969636.03 | AB69: NO ES TOP | AC69: =O69+S69+W69 -> 825790.19 | AD69: =R69+V69+Z69 -> 957916.62 | AE69: =G69-AD69 -> -0.01679028 | AG69: Cerrado/Aplicar | AH69: 4 | AI69: 0 | AJ69: 0 | AK69: CON CONTACTO | AL69: CERRADO | AM69: Sareé | AN69: 268439.49 | AO69: CARGOS ERRONEOS, DEBIDO A QUE SI CANCELARON LA CITA | AP69: 1 | AQ69: SI | AR69: 46048 | AS69: 46048 | AV69: Proveedor solicito detalle y se le hizo llegar. Validado comparte soportes de 3 OC | AW69: Casos cerrados | AX69: X | BB69: =VLOOKUP(B69,contactos!$A$1:$D$484,4,FALSE) -> eochoa@losbelenes.com.mx
B70: 16068 | C70: REPUBLIC NAIL SA DE CV | D70: 821068.11 | E70: 0 | F70: 131370.88 | G70: 952439.07 | H70: 0 | I70: =O70+S70 -> 821068.11 | K70: =I70-J70 -> 821068.11 | L70: =R70+V70 -> 952438.99 | N70: =L70-M70 -> 952438.99 | R70: =SUM(O70:Q70) -> 0 | S70: 821068.11 | T70: =E70-X70 -> 0 | U70: =F70-Y70 -> 131370.88 | V70: =SUM(S70:U70) -> 952438.99 | Z70: =SUM(W70:Y70) -> 0 | AA70: 894050.83 | AB70: NO ES TOP | AC70: =O70+S70+W70 -> 821068.11 | AD70: =R70+V70+Z70 -> 952438.99 | AE70: =G70-AD70 -> 0.078134763 | AF70: =D70-S70 -> 0 | AG70: Aplicado | AH70: 4 | AI70: 0 | AJ70: Sin contacto de proveedor | AK70: SIN CONTACTO | AL70: SIN ACLARACION | AM70: Mario | BB70: =VLOOKUP(B70,contactos!$A$1:$D$484,4,FALSE) -> #N/A
B71: 33571 | C71: GS ALIMENTOS DE MEXICO SA DE CV | D71: 945096.76 | E71: 0 | F71: 0 | G71: 945096.76 | H71: 945096.75 | I71: =O71+S71 -> 945096.76 | K71: =I71-J71 -> 945096.76 | L71: =R71+V71 -> 945096.76 | N71: =L71-M71 -> 945096.76 | R71: =SUM(O71:Q71) -> 0 | S71: 945096.76 | T71: =E71-X71 -> 0 | U71: =F71-Y71 -> 0 | V71: =SUM(S71:U71) -> 945096.76 | Z71: =SUM(W71:Y71) -> 0 | AA71: 832738.77 | AB71: NO ES TOP | AC71: =O71+S71+W71 -> 945096.76 | AD71: =R71+V71+Z71 -> 945096.76 | AE71: =G71-AD71 -> 0 | AG71: Aplicar | AH71: 4 | AI71: 0 | AJ71: 0 | AK71: SIN CONTACTO | AL71: SIN ACLARACION | AM71: Jessica | BB71: =VLOOKUP(B71,contactos!$A$1:$D$484,4,FALSE) -> #N/A
B72: 304196 | C72: ALIMENTOS TRES G SA DE CV | D72: 927389.66 | E72: 0 | F72: 0 | G72: 927389.66 | H72: 39399.81 | I72: =O72+S72 -> 927389.66 | K72: =I72-J72 -> 927389.66 | L72: =R72+V72 -> 927389.66 | N72: =L72-M72 -> 927389.66 | R72: =SUM(O72:Q72) -> 0 | S72: 927389.66 | T72: =E72-X72 -> 0 | U72: =F72-Y72 -> 0 | V72: =SUM(S72:U72) -> 927389.66 | Z72: =SUM(W72:Y72) -> 0 | AA72: 30545.9 | AB72: NO ES TOP | AC72: =O72+S72+W72 -> 927389.66 | AD72: =R72+V72+Z72 -> 927389.66 | AE72: =G72-AD72 -> -2.399995e-05 | AF72: =D72-S72 -> 0 | AG72: Aplicar | AH72: 4 | AI72: 0 | AJ72: 0 | AK72: SIN CONTACTO | AL72: SIN ACLARACION | AM72: Belem | BB72: =VLOOKUP(B72,contactos!$A$1:$D$484,4,FALSE) -> #N/A
B73: 306225 | C73: GIFAN INTERNACIONAL S. DE R.L. DE C | D73: 803396.8 | E73: 6186.5016 | F73: 106913.58 | G73: 916496.61 | H73: 583971.94 | I73: =O73+S73 -> 803396.8 | K73: =I73-J73 -> 803396.8 | L73: =R73+V73 -> 916496.88 | N73: =L73-M73 -> 916496.88 | R73: =SUM(O73:Q73) -> 0 | S73: 803396.8 | T73: =E73-X73 -> 6186.5016 | U73: =F73-Y73 -> 106913.58 | V73: =SUM(S73:U73) -> 916496.88 | Z73: =SUM(W73:Y73) -> 0 | AA73: 1564682.3 | AB73: NO ES TOP | AC73: =O73+S73+W73 -> 803396.8 | AD73: =R73+V73+Z73 -> 916496.88 | AE73: =G73-AD73 -> -0.2724 | AF73: =D73-S73 -> 0 | AG73: Aplicar | AH73: 4 | AI73: 3 | AJ73: Proveedor no presenta soportes de improcedencia, ultima fecha de seguimiento 16 de febrero 2026 | AK73: CON CONTACTO | AL73: SIN ACLARACION | AM73: Luis | BB73: =VLOOKUP(B73,contactos!$A$1:$D$484,4,FALSE) -> trujillo.g@gifan.com.mx
B74: 11361 | C74: COMERCIALIZADORA CANTU SA DE CV | D74: 786706.16 | E74: 0 | F74: 125873.02 | G74: 912579.27 | H74: 1281387.9 | I74: =O74+S74 -> 476899.57 | K74: =I74-J74 -> 476899.57 | L74: =R74+V74 -> 553203.64 | N74: =L74-M74 -> 553203.64 | R74: =SUM(O74:Q74) -> 0 | S74: =D74-W74 -> 476899.57 | T74: =E74-X74 -> 0 | U74: =F74-Y74 -> 76303.979 | V74: =G74-Z74 -> 553203.64 | W74: 309806.59 | X74: 0 | Y74: 49569.04 | Z74: =SUM(W74:Y74) -> 359375.63 | AA74: 4024373 | AB74: NO ES TOP | AC74: =O74+S74+W74 -> 786706.16 | AD74: =R74+V74+Z74 -> 912579.27 | AE74: =G74-AD74 -> 0 | AF74: =D74-S74 -> 309806.59 | AG74: Aplicar | AH74: 4 | AI74: 10 | AJ74: 10 contactos, se involucra Ana Ruth, proveedor informa que no tiene como absorber el saldo pendiente, los demas convenios los acepta | AK74: CON CONTACTO | AL74: PDTE POR PROVEEDOR | AM74: Erika | BB74: =VLOOKUP(B74,contactos!$A$1:$D$484,4,FALSE) -> jaldape@comcantu.com
B75: 384776 | C75: VINUX DE MEXICO SA DE CV | D75: 603036.43 | E75: 160860.25 | F75: 122223.47 | G75: 886120.12 | H75: 0 | I75: =O75+S75 -> 231947.43 | J75: 0 | K75: =I75-J75 -> 231947.43 | L75: =R75+V75 -> 341584.53 | M75: 0 | N75: =L75-M75 -> 341584.53 | O75: 79073 | P75: 21003 | Q75: 16012 | R75: =SUM(O75:Q75) -> 116088 | S75: =D75-(O75+W75) -> 152874.43 | T75: =E75-(P75+X75) -> 41518.663 | U75: =F75-(Q75+Y75) -> 31103.469 | V75: =G75-(R75+Z75) -> 225496.53 | W75: 371089 | X75: 98338.585 | Y75: 75108 | Z75: =SUM(W75:Y75) -> 544535.58 | AA75: 159233.19 | AB75: NO ES TOP | AC75: =O75+S75+W75 -> 603036.43 | AD75: =R75+V75+Z75 -> 886120.12 | AE75: =G75-AD75 -> 0 | AF75: =D75-S75 -> 450162 | AG75: Revisión | AH75: 4 | AI75: 4 | AJ75: Proveedor manda soporte de evidencia de solicitud de omisión , en validación de confirmación, se tuvo 4 correos de seguimiento | AK75: CON CONTACTO | AL75: PDTE POR PROVEEDOR | AM75: Marcela | AN75: 886120.12 | AO75: DETALLE DE LOS CARGOS EN EL PORTAL | AR75: 46042 | AS75: 46042 | AT75: 46043 | AV75: Proveedor autoriza 94 mil pesos. Argumenta entregó lo que se le publico. Proveedor manda soporte de memo de cancelacion pero son pedidos diferentes a los publicados. | AY75: X | BB75: =VLOOKUP(B75,contactos!$A$1:$D$484,4,FALSE) -> ARACELI.REYNAGA@VINUX.COM.MX
B76: 55798 | C76: TOALLERA POPULAR SA DE CV | D76: 742175.07 | E76: 0 | F76: 118748.04 | G76: 860923.08 | H76: 0 | I76: =O76+S76 -> 742175.07 | K76: =I76-J76 -> 742175.07 | L76: =R76+V76 -> 860923.11 | N76: =L76-M76 -> 860923.11 | R76: =SUM(O76:Q76) -> 0 | S76: 742175.07 | T76: =E76-X76 -> 0 | U76: =F76-Y76 -> 118748.04 | V76: =SUM(S76:U76) -> 860923.11 | Z76: =SUM(W76:Y76) -> 0 | AA76: 925108.34 | AB76: NO ES TOP | AC76: =O76+S76+W76 -> 742175.07 | AD76: =R76+V76+Z76 -> 860923.11 | AE76: =G76-AD76 -> -0.026309846 | AF76: =D76-S76 -> 0 | AG76: Aplicar | AH76: 4 | AI76: 0 | AJ76: Proveedor solo ha respondido por diferencias del 20-24 | AK76: SIN CONTACTO | AL76: SIN ACLARACION | AM76: Mario | BB76: =VLOOKUP(B76,contactos!$A$1:$D$484,4,FALSE) -> alejandra.carrion@solatextil.mx
B77: 85902 | C77: COMERCIAL IMPORTADORA S DE RL DE CV | D77: 725653.98 | E77: 0 | F77: 116104.63 | G77: 841758.63 | H77: 841758.63 | I77: =O77+S77 -> 725653.98 | K77: =I77-J77 -> 725653.98 | L77: =R77+V77 -> 841758.61 | N77: =L77-M77 -> 841758.61 | R77: =SUM(O77:Q77) -> 0 | S77: 725653.98 | T77: =E77-X77 -> 0 | U77: =F77-Y77 -> 116104.63 | V77: =SUM(S77:U77) -> 841758.61 | Z77: =SUM(W77:Y77) -> 0 | AA77: 1405532.5 | AB77: NO ES TOP | AC77: =O77+S77+W77 -> 725653.98 | AD77: =R77+V77+Z77 -> 841758.61 | AE77: =G77-AD77 -> 0.021162207 | AF77: =D77-S77 -> 0 | AG77: Aplicado | AH77: 4 | AI77: 0 | AJ77: 0 | AK77: SIN CONTACTO | AL77: SIN ACLARACION | AM77: Erika | BB77: =VLOOKUP(B77,contactos!$A$1:$D$484,4,FALSE) -> algarciag@quakerstate.com.mx
B78: 62760 | C78: APOLO TEXTIL SA DE CV | D78: 721247.01 | E78: 0 | F78: 115399.52 | G78: 836646.49 | H78: 836646.49 | I78: =O78+S78 -> 721247.01 | K78: =I78-J78 -> 721247.01 | L78: =R78+V78 -> 836646.53 | N78: =L78-M78 -> 836646.53 | R78: =SUM(O78:Q78) -> 0 | S78: 721247.01 | T78: =E78-X78 -> 0 | U78: =F78-Y78 -> 115399.52 | V78: =SUM(S78:U78) -> 836646.53 | Z78: =SUM(W78:Y78) -> 0 | AA78: 1305389.2 | AB78: NO ES TOP | AC78: =O78+S78+W78 -> 721247.01 | AD78: =R78+V78+Z78 -> 836646.53 | AE78: =G78-AD78 -> -0.0416 | AG78: Aplicar | AH78: 4 | AI78: 0 | AJ78: 0 | AK78: SIN CONTACTO | AL78: SIN ACLARACION | AM78: Jessica | BB78: =VLOOKUP(B78,contactos!$A$1:$D$484,4,FALSE) -> #N/A
B79: 10348 | C79: CUBETAS Y BA¥OS S.A. DE C.V. | D79: 698397.79 | E79: 0 | F79: 111743.65 | G79: 810141.4 | H79: 810141.43 | I79: =O79+S79 -> 698397.79 | K79: =I79-J79 -> 698397.79 | L79: =R79+V79 -> 810141.44 | N79: =L79-M79 -> 810141.44 | R79: =SUM(O79:Q79) -> 0 | S79: 698397.79 | T79: =E79-X79 -> 0 | U79: =F79-Y79 -> 111743.65 | V79: =SUM(S79:U79) -> 810141.44 | Z79: =SUM(W79:Y79) -> 0 | AA79: 153005.08 | AB79: NO ES TOP | AC79: =O79+S79+W79 -> 698397.79 | AD79: =R79+V79+Z79 -> 810141.44 | AE79: =G79-AD79 -> -0.040059662 | AF79: =D79-S79 -> 0 | AG79: Aplicar | AH79: 4 | AI79: 0 | AJ79: 0 | AK79: SIN CONTACTO | AL79: SIN ACLARACION | AM79: Belem | BB79: =VLOOKUP(B79,contactos!$A$1:$D$484,4,FALSE) -> #N/A
B80: 39057 | C80: DISTRIBUIDORA DE TEXTILES AVANTE S. | D80: 678987.01 | E80: 0 | F80: 108638.07 | G80: 787624.97 | H80: 0 | I80: =O80+S80 -> 678987.01 | K80: =I80-J80 -> 678987.01 | L80: =R80+V80 -> 787625.07 | N80: =L80-M80 -> 787625.07 | R80: =SUM(O80:Q80) -> 0 | S80: 678987.01 | T80: =E80-X80 -> 0 | U80: =F80-Y80 -> 108638.07 | V80: =SUM(S80:U80) -> 787625.07 | Z80: =SUM(W80:Y80) -> 0 | AA80: 644172.1 | AB80: NO ES TOP | AC80: =O80+S80+W80 -> 678987.01 | AD80: =R80+V80+Z80 -> 787625.07 | AE80: =G80-AD80 -> -0.10265426 | AF80: =D80-S80 -> 0 | AG80: Aplicar | AH80: 4 | AI80: 0 | AJ80: sin comentarios del proveedor | AK80: SIN CONTACTO | AL80: SIN ACLARACION | AM80: Marcela | BB80: =VLOOKUP(B80,contactos!$A$1:$D$484,4,FALSE) -> #N/A
B81: 52480 | C81: EMPACADORA LA MERCED SA DE CV | D81: 740317.29 | E81: 0 | F81: 0 | G81: 740317.29 | H81: 740317.28 | I81: =O81+S81 -> 740317.29 | K81: =I81-J81 -> 740317.29 | L81: =R81+V81 -> 740317.29 | N81: =L81-M81 -> 740317.29 | R81: =SUM(O81:Q81) -> 0 | S81: 740317.29 | T81: =E81-X81 -> 0 | U81: =F81-Y81 -> 0 | V81: =SUM(S81:U81) -> 740317.29 | Z81: =SUM(W81:Y81) -> 0 | AA81: 1154248.4 | AB81: NO ES TOP | AC81: =O81+S81+W81 -> 740317.29 | AD81: =R81+V81+Z81 -> 740317.29 | AE81: =G81-AD81 -> 0 | AF81: =D81-S81 -> 0 | AG81: Aplicar | AH81: 4 | AI81: 0 | AJ81: 0 | AK81: SIN CONTACTO | AL81: SIN ACLARACION | AM81: Yessenia | BB81: =VLOOKUP(B81,contactos!$A$1:$D$484,4,FALSE) -> #N/A
B82: 43463 | C82: DISTRIBUIDORA KROMA SA DE CV | D82: 631186.37 | E82: 0 | F82: 100989.87 | G82: 732176.24 | H82: 732176.24 | I82: =O82+S82 -> 631186.37 | K82: =I82-J82 -> 631186.37 | L82: =R82+V82 -> 732176.25 | N82: =L82-M82 -> 732176.25 | R82: =SUM(O82:Q82) -> 0 | S82: 631186.37 | T82: =E82-X82 -> 0 | U82: =F82-Y82 -> 100989.87 | V82: =SUM(S82:U82) -> 732176.25 | Z82: =SUM(W82:Y82) -> 0 | AA82: 914343 | AB82: NO ES TOP | AC82: =O82+S82+W82 -> 631186.37 | AD82: =R82+V82+Z82 -> 732176.25 | AE82: =G82-AD82 -> -0.0043913764 | AF82: =D82-S82 -> 0 | AG82: Aplicar | AH82: 4 | AI82: 0 | AJ82: 0 | AK82: SIN CONTACTO | AL82: SIN ACLARACION | AM82: Francisco | BB82: =VLOOKUP(B82,contactos!$A$1:$D$484,4,FALSE) -> jadiaz@ppg.com
B83: 12995 | C83: PHILIPS MEXICO COMMERCIAL SA DE CV | D83: 630471.07 | E83: 0 | F83: 100875.37 | G83: 731346.26 | H83: 0 | I83: =O83+S83 -> 630471.07 | K83: =I83-J83 -> 630471.07 | L83: =R83+V83 -> 731346.44 | N83: =L83-M83 -> 731346.44 | R83: =SUM(O83:Q83) -> 0 | S83: 630471.07 | T83: =E83-X83 -> 0 | U83: =F83-Y83 -> 100875.37 | V83: =SUM(S83:U83) -> 731346.44 | Z83: =SUM(W83:Y83) -> 0 | AA83: 501100.46 | AB83: NO ES TOP | AC83: =O83+S83+W83 -> 630471.07 | AD83: =R83+V83+Z83 -> 731346.44 | AE83: =G83-AD83 -> -0.17506321 | AF83: =D83-S83 -> 0 | AG83: Aplicar | AH83: 4 | AI83: 0 | AJ83: 0 | AK83: SIN CONTACTO | AL83: SIN ACLARACION | AM83: Francisco | BB83: =VLOOKUP(B83,contactos!$A$1:$D$484,4,FALSE) -> #N/A
B84: 37481 | C84: ORGANIZACION REYNERA SA DE CV | D84: 624993.07 | E84: 0 | F84: 99998.902 | G84: 724991.98 | H84: 724991.97 | I84: =O84+S84 -> 624993.07 | K84: =I84-J84 -> 624993.07 | L84: =R84+V84 -> 724991.97 | N84: =L84-M84 -> 724991.97 | R84: =SUM(O84:Q84) -> 0 | S84: 624993.07 | T84: =E84-X84 -> 0 | U84: =F84-Y84 -> 99998.902 | V84: =SUM(S84:U84) -> 724991.97 | Z84: =SUM(W84:Y84) -> 0 | AA84: 492891.03 | AB84: NO ES TOP | AC84: =O84+S84+W84 -> 624993.07 | AD84: =R84+V84+Z84 -> 724991.97 | AE84: =G84-AD84 -> 0.002486783 | AF84: =D84-S84 -> 0 | AG84: Aplicar | AH84: 4 | AI84: 0 | AJ84: 0 | AK84: SIN CONTACTO | AL84: SIN ACLARACION | AM84: Francisco | BB84: =VLOOKUP(B84,contactos!$A$1:$D$484,4,FALSE) -> #N/A
B85: 318196 | C85: SUNSTAR AMERICAS MEXICO S. de R.L. | D85: 624613.84 | E85: 0 | F85: 99938.289 | G85: 724552.15 | H85: 678432.46 | I85: =O85+S85 -> 584855.57 | K85: =I85-J85 -> 584855.57 | L85: =R85+V85 -> 678432.5 | N85: =L85-M85 -> 678432.5 | O85: =D85-W85 -> 584855.57 | Q85: =O85*0.16 -> 93576.892 | R85: =SUM(O85:Q85) -> 678432.47 | T85: =E85-X85 -> 0 | U85: =F85-Q85-Y85 -> 0.03559936 | V85: =SUM(S85:U85) -> 0.03559936 | W85: 39758.269 | Y85: 6361.3619 | Z85: =SUM(W85:Y85) -> 46119.631 | AA85: 228211.6 | AB85: NO ES TOP | AC85: =O85+S85+W85 -> 624613.84 | AD85: =R85+V85+Z85 -> 724552.13 | AE85: =G85-AD85 -> 0.017773842 | AG85: Cerrado/Aplicar | AH85: 4 | AI85: 2 | AJ85: Autorizado por Proveedor | AK85: CON CONTACTO | AL85: CERRADO | AM85: Andrea | AN85: 724552.15 | AO85: DETALLE DE LOS CARGOS EN EL PORTAL | AP85: 9 | AR85: 46056 | AS85: 46058 | AT85: 46058 | AU85: 46058 | AV85: 03 FEB: el area de Aclaraciones envia correo solicitando atender al Proveedor.// 04 feb Auditoria envia correo invitando a reunion, sin embargo Julio Richardson KAM de Sunstar se comunica telefónicamente e informa que ha revisado el monto mas alto y esta de acuerdo, solo que no ha finalizado, se genero la aclaracion en el Portal, por un error para visualizar las partidas que ya solucionaron. Compartira un correo con el resultado. // 04 FEB Proveedor solicita agenda para el jueve 05 feb 3:00 pm se envia invitación por TEAMS.//05 feb : reunion con el Proveedor donde se explica el detalle de la diferencia y se comparte el archivo en excel, el Proveedor informa que tiene unos casos donde el monto del pedido es bajo y no puede despachar que esta informacion la entregro a Comercial en su momento pero explicaron que deben revisar la parametrizacion del Sistema para que no genere pedidos por montos bajos. el Proveedor revisara y enviara el detalle//05 feb: El proveedor comparte correo informando que esta de acuerdo con el monto de $678,432.55 impuestos incluidos, y no autoriza $46,119.60 incluido impuestos porque indica que estos pedidos se publican de manera erronea, solo reciben pedidos los lunes y miercoles y por el monto bajo no es rentable el envio. Envia correo. | AW85: Casos abiertos( En proceso) | AX85: SI | BB85: =VLOOKUP(B85,contactos!$A$1:$D$484,4,FALSE) -> #N/A
B86: 48298 | C86: IMPULSORA CAMPIRANO SA DE CV | D86: 619104.25 | E86: 0 | F86: 99056.696 | G86: 718160.95 | H86: 400141.22 | I86: =O86+S86 -> 775.26 | J86: 0 | K86: =I86-J86 -> 775.26 | L86: =R86+V86 -> 899.30764 | M86: 0 | N86: =L86-M86 -> 899.30764 | O86: 775.26 | Q86: =O86*0.16 -> 124.0416 | R86: =SUM(O86:Q86) -> 899.3016 | S86: =D86-(O86+W86) -> 0 | T86: =E86-(P86+X86) -> 0 | U86: =F86-(Q86+Y86) -> 0 | V86: =G86-(R86+Z86) -> 0.0060392763 | W86: =D86-O86 -> 618328.99 | Y86: =F86-Q86 -> 98932.655 | Z86: =SUM(W86:Y86) -> 717261.64 | AA86: 954257.95 | AB86: NO ES TOP | AC86: =O86+S86+W86 -> 619104.25 | AD86: =R86+V86+Z86 -> 718160.95 | AE86: =G86-AD86 -> 0 | AG86: Revisión | AH86: 4 | AI86: 10 | AJ86: Compras envía soporte de cancelación de Omisión de NS con fecha de Mayo 2025. | AK86: CON CONTACTO | AL86: PDTE POR PROVEEDOR | AM86: Francisco | AN86: 718160.95 | AO86: DETALLE DE LOS CARGOS EN EL PORTAL | AP86: 3 | AR86: 46042 | AS86: 46042 | AV86: EN validaciòn de soporte | AX86: X | BA86: Envío de manual para validación de ajustes en Portal. Proveedor envìa soporte de cancelaciòn, en proceso de validaciòn. | BB86: =VLOOKUP(B86,contactos!$A$1:$D$484,4,FALSE) -> d.salazar@campirano.com.mx
B87: 44883 | C87: PERNOD RICARD MEXICO, S.A. DE C.V. | D87: 423883.77 | E87: 195142.95 | F87: 99044.275 | G87: 718071.01 | H87: 718071.01 | I87: =O87+S87 -> 423883.77 | K87: =I87-J87 -> 423883.77 | L87: =R87+V87 -> 718071 | N87: =L87-M87 -> 718071 | R87: =SUM(O87:Q87) -> 0 | S87: 423883.77 | T87: =E87-X87 -> 195142.95 | U87: =F87-Y87 -> 99044.275 | V87: =SUM(S87:U87) -> 718071 | Z87: =SUM(W87:Y87) -> 0 | AB87: NO ES TOP | AC87: =O87+S87+W87 -> 423883.77 | AD87: =R87+V87+Z87 -> 718071 | AE87: =G87-AD87 -> 0.0137 | AF87: =D87-S87 -> 0 | AG87: Aplicar | AH87: 4 | AI87: 0 | AJ87: Sin contacto de proveedor | AK87: SIN CONTACTO | AL87: SIN ACLARACION | AM87: Luis | BB87: =VLOOKUP(B87,contactos!$A$1:$D$484,4,FALSE) -> daniela.tijerina@pernod-ricard.com
B88: 316877 | C88: CANADIA DISTRIBUIDORES SA DE CV | D88: 616995.11 | E88: 0 | F88: 98719.211 | G88: 715714.33 | H88: 715714.32 | I88: =O88+S88 -> 616995.11 | K88: =I88-J88 -> 616995.11 | L88: =R88+V88 -> 715714.32 | N88: =L88-M88 -> 715714.32 | R88: =SUM(O88:Q88) -> 0 | S88: 616995.11 | T88: =E88-X88 -> 0 | U88: =F88-Y88 -> 98719.211 | V88: =SUM(S88:U88) -> 715714.32 | Z88: =SUM(W88:Y88) -> 0 | AA88: 581945.18 | AB88: NO ES TOP | AC88: =O88+S88+W88 -> 616995.11 | AD88: =R88+V88+Z88 -> 715714.32 | AE88: =G88-AD88 -> 0.0088000001 | AG88: Aplicar | AH88: 4 | AI88: 0 | AJ88: 0 | AK88: SIN CONTACTO | AL88: SIN ACLARACION | AM88: Jessica | BB88: =VLOOKUP(B88,contactos!$A$1:$D$484,4,FALSE) -> #N/A
B89: 71233 | C89: STEREN PRODUCTO EMPACADO,S.A. DE C. | D89: 611494.4 | E89: 0 | F89: 97839.212 | G89: 709333.64 | H89: 709333.61 | I89: =O89+S89 -> 611494.52 | K89: =I89-J89 -> 611494.52 | L89: =R89+V89 -> 709333.64 | N89: =L89-M89 -> 709333.64 | O89: =+R89/1.16 -> 575387.57 | R89: 667449.58 | S89: 36106.948 | T89: =E89-X89 -> 0 | U89: =S89*0.16 -> 5777.1117 | V89: =SUM(S89:U89) -> 41884.06 | Z89: =SUM(W89:Y89) -> 0 | AA89: 801618.89 | AB89: NO ES TOP | AC89: =O89+S89+W89 -> 611494.52 | AD89: =R89+V89+Z89 -> 709333.64 | AE89: =G89-AD89 -> 0 | AF89: 5 | AG89: Cerrado/Aplicar parcialidad | AH89: 4 | AI89: 3 | AJ89: 03 contactos 23 feb: reunión con el proveedor se encuentra revisando. 24 feb: el proveedor informa que no coincide PVP, por lo que enviara detalle esta tarde. 25 feb: envia correo informando que procede el cargo de NS ene -ago 2025 por un monto de $667,449.58 incluido imp | AK89: CON CONTACTO | AL89: SIN ACLARACION | AM89: Andrea | BB89: =VLOOKUP(B89,contactos!$A$1:$D$484,4,FALSE) -> luis.perea@steren.com.mx
B90: 208892 | C90: EMPACADORA THERBAL S.A. DE C.V. | D90: 686095.39 | E90: 0 | F90: 0 | G90: 686095.39 | H90: 382136.2 | I90: =O90+S90 -> 686095.39 | K90: =I90-J90 -> 686095.39 | L90: =R90+V90 -> 686095.39 | N90: =L90-M90 -> 686095.39 | R90: =SUM(O90:Q90) -> 0 | S90: 686095.39 | T90: =E90-X90 -> 0 | U90: =F90-Y90 -> 0 | V90: =SUM(S90:U90) -> 686095.39 | Z90: =SUM(W90:Y90) -> 0 | AA90: 492503.78 | AB90: NO ES TOP | AC90: =O90+S90+W90 -> 686095.39 | AD90: =R90+V90+Z90 -> 686095.39 | AE90: =G90-AD90 -> -0.0044166491 | AF90: =D90-S90 -> 0 | AG90: Aplicar | AH90: 4 | AI90: 0 | AJ90: Sin acercamiento por parte del proveedor | AK90: SIN CONTACTO | AL90: SIN ACLARACION | AM90: Erika | BB90: =VLOOKUP(B90,contactos!$A$1:$D$484,4,FALSE) -> #N/A
B91: 13860 | C91: PLO POP SA DE CV | D91: 591083.08 | E91: 0 | F91: 94573.293 | G91: 685656.37 | H91: 685656.36 | I91: =O91+S91 -> 591083.08 | K91: =I91-J91 -> 591083.08 | L91: =R91+V91 -> 685656.37 | N91: =L91-M91 -> 685656.37 | R91: =SUM(O91:Q91) -> 0 | S91: 591083.08 | T91: =E91-X91 -> 0 | U91: =F91-Y91 -> 94573.293 | V91: =SUM(S91:U91) -> 685656.37 | Z91: =SUM(W91:Y91) -> 0 | AA91: 1249281.1 | AB91: NO ES TOP | AC91: =O91+S91+W91 -> 591083.08 | AD91: =R91+V91+Z91 -> 685656.37 | AE91: =G91-AD91 -> -0.0039619738 | AF91: =D91-S91 -> 0 | AG91: Aplicar | AH91: 4 | AI91: 1 | AJ91: 1 contacto, proveedor solicita reunión sin embargo no da fecha | AK91: CON CONTACTO | AL91: PDTE POR PROVEEDOR | AM91: Erika | AN91: 685656.37 | AO91: DETALLE DE LOS CARGOS EN EL PORTAL | AR91: 46041 | AS91: 46041 | AV91: Proveedor solicita reunión se le confirma disponibilidad | AW91: Casos abiertos( En proceso) | AX91: X | BB91: =VLOOKUP(B91,contactos!$A$1:$D$484,4,FALSE) -> joser@jmk.com.mx
B92: 64014 | C92: CONAGRA FOODS MEXICO SA DE CV | D92: 665488.12 | E92: 13582.226 | F92: 0 | G92: 679070.34 | H92: 674670 | I92: =O92+S92 -> 661087.93 | K92: =I92-J92 -> 661087.93 | L92: =R92+V92 -> 674670.16 | N92: =L92-M92 -> 674670.16 | O92: 661087.93 | P92: 13582.23 | R92: =SUM(O92:Q92) -> 674670.16 | T92: =E92-P92-X92 -> -0.0035304167 | U92: =F92-Q92-Y92 -> 0 | V92: =SUM(S92:U92) -> -0.0035304167 | W92: 4400.2 | Z92: =SUM(W92:Y92) -> 4400.2 | AB92: NO ES TOP | AC92: =O92+S92+W92 -> 665488.13 | AD92: =R92+V92+Z92 -> 679070.36 | AE92: =G92-AD92 -> -0.021369583 | AG92: Cerrado/Aplicar | AH92: 4 | AI92: 1 | AJ92: 0 | AK92: CON CONTACTO | AL92: CERRADO | AM92: Luis | AN92: 4400.19 | AR92: 46056 | BB92: =VLOOKUP(B92,contactos!$A$1:$D$484,4,FALSE) -> AlmaDelia.Rangel@conagra.com
B93: 21853 | C93: DISTRIBUIDORA COLOSO INTERNACIONAL | D93: 674473.88 | E93: 0 | F93: 0 | G93: 674473.88 | H93: 674473.87 | I93: =O93+S93 -> 674473.88 | K93: =I93-J93 -> 674473.88 | L93: =R93+V93 -> 674473.88 | N93: =L93-M93 -> 674473.88 | R93: =SUM(O93:Q93) -> 0 | S93: 674473.88 | T93: =E93-X93 -> 0 | U93: =F93-Y93 -> 0 | V93: =SUM(S93:U93) -> 674473.88 | Z93: =SUM(W93:Y93) -> 0 | AB93: NO ES TOP | AC93: =O93+S93+W93 -> 674473.88 | AD93: =R93+V93+Z93 -> 674473.88 | AE93: =G93-AD93 -> 0.002309031 | AF93: =D93-S93 -> 0 | AG93: Aplicar | AH93: 4 | AI93: 0 | AJ93: 0 | AK93: SIN CONTACTO | AL93: SIN ACLARACION | AM93: Yessenia | BB93: =VLOOKUP(B93,contactos!$A$1:$D$484,4,FALSE) -> jesus@dcoloso.com.mx
B94: 3137 | C94: LETICIA PAMMY SA DE CV | D94: 578799.47 | E94: 0 | F94: 92607.887 | G94: 671407.36 | H94: 671407.36 | I94: =O94+S94 -> 258104.83 | J94: 0 | K94: =I94-J94 -> 258104.83 | L94: =R94+V94 -> 299401.58 | M94: 0 | N94: =L94-M94 -> 299401.58 | O94: 258104.83 | P94: 0 | Q94: 41296.74 | R94: =SUM(O94:Q94) -> 299401.57 | S94: =D94-(O94+W94) -> -0.0037864969 | T94: =E94-(P94+X94) -> 0 | U94: =F94-(Q94+Y94) -> 0.0067941605 | V94: =G94-(R94+Z94) -> 0.0099999999 | W94: 320694.64 | X94: 0 | Y94: 51311.14 | Z94: =SUM(W94:Y94) -> 372005.78 | AA94: 1024896.4 | AB94: NO ES TOP | AC94: =O94+S94+W94 -> 578799.47 | AD94: =R94+V94+Z94 -> 671407.36 | AE94: =G94-AD94 -> 0 | AG94: Aplicado/Reembolsar | AH94: 4 | AI94: 0 | AJ94: Reembolsar $372,005.78 | AK94: CON CONTACTO | AL94: CERRADO | AM94: Jessica | AS94: 46059 | AT94: 46059 | AV94: Proveedor acepto de manera parcial, envio soportes para su validacion | BB94: =VLOOKUP(B94,contactos!$A$1:$D$484,4,FALSE) -> elias@pammy.com.mx
B95: 86520 | C95: LABORATORIOS AVANT S.A. DE C.V. | D95: 578790.19 | E95: 0 | F95: 92606.431 | G95: 671396.61 | H95: 671396.62 | I95: =O95+S95 -> 578790.19 | K95: =I95-J95 -> 578790.19 | L95: =R95+V95 -> 671396.62 | N95: =L95-M95 -> 671396.62 | R95: =SUM(O95:Q95) -> 0 | S95: 578790.19 | T95: =E95-X95 -> 0 | U95: =F95-Y95 -> 92606.431 | V95: =SUM(S95:U95) -> 671396.62 | Z95: =SUM(W95:Y95) -> 0 | AA95: 415815.22 | AB95: NO ES TOP | AC95: =O95+S95+W95 -> 578790.19 | AD95: =R95+V95+Z95 -> 671396.62 | AE95: =G95-AD95 -> -0.014486959 | AG95: Aplicar | AH95: 4 | AI95: 0 | AJ95: 0 | AK95: SIN CONTACTO | AL95: SIN ACLARACION | AM95: Jessica | BB95: =VLOOKUP(B95,contactos!$A$1:$D$484,4,FALSE) -> #N/A
B96: 306571 | C96: AJEMEX SA DE CV | D96: 597144.21 | E96: 0 | F96: 63014.278 | G96: 660158.44 | H96: 660158.44 | I96: =O96+S96 -> 597144.21 | K96: =I96-J96 -> 597144.21 | L96: =R96+V96 -> 660158.49 | N96: =L96-M96 -> 660158.49 | R96: =SUM(O96:Q96) -> 0 | S96: 597144.21 | T96: =E96-X96 -> 0 | U96: =F96-Y96 -> 63014.278 | V96: =SUM(S96:U96) -> 660158.49 | Z96: =SUM(W96:Y96) -> 0 | AA96: 1033798.4 | AB96: NO ES TOP | AC96: =O96+S96+W96 -> 597144.21 | AD96: =R96+V96+Z96 -> 660158.49 | AE96: =G96-AD96 -> -0.050782651 | AF96: =D96-S96 -> 0 | AG96: Aplicado | AH96: 4 | AI96: 0 | AJ96: 0 | AK96: SIN CONTACTO | AL96: SIN ACLARACION | AM96: Olfi | AN96: =G96 -> 660158.44 | AS96: 46059 | AT96: si | AV96: Proveedor solicita el detalle y se le comparte Proveedor indica que esta en validación de la información,en espera de soportes | AW96: Casos abiertos( En proceso) | AY96: x | BB96: =VLOOKUP(B96,contactos!$A$1:$D$484,4,FALSE) -> #N/A
B97: 13642 | C97: COMERCIALIZADORA CANTU SA DE CV | D97: 556101.18 | E97: 0 | F97: 88976.137 | G97: 645077.31 | H97: 645077.31 | I97: =O97+S97 -> 281284.93 | J97: 0 | K97: =I97-J97 -> 281284.93 | L97: =R97+V97 -> 326290.49 | M97: 0 | N97: =L97-M97 -> 326290.49 | R97: =SUM(O97:Q97) -> 0 | S97: =D97-W97 -> 281284.93 | T97: =E97-X97 -> 0 | U97: =F97-Y97 -> 45005.567 | V97: =G97-Z97 -> 326290.49 | W97: 274816.25 | X97: 0 | Y97: 43970.57 | Z97: =SUM(W97:Y97) -> 318786.82 | AA97: 3106171.6 | AB97: NO ES TOP | AC97: =O97+S97+W97 -> 556101.18 | AD97: =R97+V97+Z97 -> 645077.31 | AE97: =G97-AD97 -> 0 | AF97: =D97-S97 -> 274816.25 | AG97: Aplicar | AH97: 4 | AI97: 4 | AJ97: Sin soporte de proveedor para el ejercicio 2025 | AK97: CON CONTACTO | AL97: PDTE POR PROVEEDOR | AM97: Luis | BB97: =VLOOKUP(B97,contactos!$A$1:$D$484,4,FALSE) -> jaldape@comcantu.com
B98: 21869 | C98: PINSA COMERCIAL SA DE CV | D98: 621522.29 | E98: 0 | F98: 0 | G98: 621522.28 | H98: 621522.28 | I98: =O98+S98 -> 16566.727 | J98: 0 | K98: =I98-J98 -> 16566.727 | L98: =R98+V98 -> 16566.727 | M98: 0 | N98: =L98-M98 -> 16566.727 | R98: =SUM(O98:Q98) -> 0 | S98: =D98-W98 -> 16566.727 | T98: =E98-X98 -> 0 | U98: =F98-Y98 -> 0 | V98: =SUM(S98:U98) -> 16566.727 | W98: 604955.56 | X98: 0 | Y98: 0 | Z98: =SUM(W98:Y98) -> 604955.56 | AB98: NO ES TOP | AC98: =O98+S98+W98 -> 621522.29 | AD98: =R98+V98+Z98 -> 621522.29 | AE98: =G98-AD98 -> -0.0074159519 | AF98: =D98-S98 -> 604955.56 | AG98: Aplicar | AH98: 4 | AI98: 0 | AJ98: 0 | AK98: SIN CONTACTO | AL98: SIN ACLARACION | AM98: Yessenia | BB98: =VLOOKUP(B98,contactos!$A$1:$D$484,4,FALSE) -> lcedillo@pinsa.com
B99: 79087 | C99: GRUPO HB PS S.A. DE C.V. | D99: 532651.81 | E99: 0 | F99: 85224.29 | G99: 617876.11 | H99: 118071.44 | I99: =O99+S99 -> 101785.73 | K99: =I99-J99 -> 101785.73 | L99: =R99+V99 -> 118071.45 | N99: =L99-M99 -> 118071.45 | O99: 101785.73 | P99: 0 | Q99: 16285.72 | R99: =SUM(O99:Q99) -> 118071.45 | S99: 0 | T99: 0 | U99: 0 | V99: =SUM(S99:U99) -> 0 | W99: 430866.08 | Y99: 68938.57 | Z99: =SUM(W99:Y99) -> 499804.65 | AA99: 559777.36 | AB99: NO ES TOP | AC99: =O99+S99+W99 -> 532651.81 | AD99: =R99+V99+Z99 -> 617876.1 | AE99: =G99-AD99 -> 0.0104 | AG99: Aplicar | AH99: 4 | AI99: 6 | AJ99: 20-feb-2026 el proveedor informa y autoriza en reunion por teams el importe de $118,07.45 1 (4 correos de Seguimiento) | AK99: CON CONTACTO | AL99: PDTE POR AUDITORIA | AM99: Yessica | AS99: 46059 | AU99: 46059 | AV99: proveedor acepta importe Se envió la información al proveedor para su validación; quedamos pendientes de recibir la documentación presentada en la reunión. | BB99: =VLOOKUP(B99,contactos!$A$1:$D$484,4,FALSE) -> alejandro.rodriguez@hamiltonbeach.com
B100: 32953 | C100: FREUDENBERG PRODUCTOS DEL HOGAR SA | D100: 526702.41 | E100: 0 | F100: 84272.379 | G100: 610975.08 | H100: 489083.38 | I100: 421623.6 | J100: 0 | K100: =I100-J100 -> 421623.6 | L100: 489083.38 | M100: 0 | N100: =L100-M100 -> 489083.38 | O100: 387264.28 | P100: 0 | Q100: 61962.28 | R100: 449226.56 | S100: =D100-(O100+W100) -> 105078.82 | T100: =E100-(P100+X100) -> 0 | U100: =F100-(Q100+Y100) -> 16812.61 | V100: =S100+U100 -> 121891.43 | W100: 34359.31 | Y100: 5497.4896 | Z100: =SUM(W100:Y100) -> 39856.8 | AA100: 2990546.3 | AB100: NO ES TOP | AC100: =O100+S100+W100 -> 526702.41 | AD100: =R100+V100+Z100 -> 610974.79 | AE100: =G100-AD100 -> 0.2880473 | AG100: Aplicar | AH100: 4 | AI100: 8 | AJ100: cierre con el importe marcado | AK100: CON CONTACTO | AL100: PDTE POR PROVEEDOR | AM100: Jessica | AV100: Proveedor acepto de manera parcial, validacion por su parte del monto pendiente | BB100: =VLOOKUP(B100,contactos!$A$1:$D$484,4,FALSE) -> jose.lopez@fhp-ww.com
B101: 11716 | C101: ARTSANA MEXICO SA DE CV | D101: 507093.83 | E101: 0 | F101: 81134.983 | G101: 588228.75 | H101: 588228.81 | I101: =O101+S101 -> 507093.83 | K101: =I101-J101 -> 507093.83 | L101: =R101+V101 -> 588228.81 | N101: =L101-M101 -> 588228.81 | R101: =SUM(O101:Q101) -> 0 | S101: 507093.83 | T101: =E101-X101 -> 0 | U101: =F101-Y101 -> 81134.983 | V101: =SUM(S101:U101) -> 588228.81 | Z101: =SUM(W101:Y101) -> 0 | AA101: 1724425.1 | AB101: NO ES TOP | AC101: =O101+S101+W101 -> 507093.83 | AD101: =R101+V101+Z101 -> 588228.81 | AE101: =G101-AD101 -> -0.0626 | AF101: =D101-S101 -> 0 | AG101: Aplicar | AH101: 4 | AI101: 0 | AJ101: 0 | AK101: SIN CONTACTO | AL101: SIN ACLARACION | AM101: Belem | BB101: =VLOOKUP(B101,contactos!$A$1:$D$484,4,FALSE) -> #N/A
...

Sheet Resumen
B3: Count Proveedor | C3: Publicado en Portal | D3: Aceptado (antes_impto) | E3: Pendiente (antes_impto) | F3: Soportado (no procede antes_impto) | G3: Penalizacion_con Imptos | H3: Aceptado_con Imptos | I3: Pendiente_con Imptos | J3: Soportado_con Imptos
A4: CON CONTACTO | B4: 117 | C4: 3.2774067e+08 | D4: 48455381 | E4: 2.5010905e+08 | F4: 29176248 | G4: 3.6878422e+08 | H4: 54787016 | I4: 2.8010932e+08 | J4: 33887877
A5: SIN CONTACTO
A6: SIN ACLARACION | B6: 315 | C6: 42055334 | E6: 42055334 | G6: 47129266 | H6: 0 | I6: 47129265 | J6: 0
A7: Grand Total | B7: 432 | C7: 3.6979601e+08 | D7: 48455381 | E7: 2.9216438e+08 | F7: 29176248 | G7: 4.1591348e+08 | H7: 54787016 | I7: 3.2723859e+08 | J7: 33887877

Sheet Detalle Cargos 24Mzo26
E1: =SUBTOTAL(9,E3:E1621) -> 1.936889e+08
A2: Document Number | B2: Account | C2: Document Type | D2: Document Date | E2: Amount in local currency | F2: Local Currency | G2: Clearing Document | H2: aplicado | I2: Text | J2: Payment Block | K2: Clearing date | L2: Net due date | M2: Reference | N2: Reference Key 3 | O2: Company Code | P2: Reference Key 2 | Q2: Reference Key 1 | R2: Payment Method | S2: Assignment | T2: User name
A3: 5100421550 | B3: 137 | C3: RA | D3: 46035 | E3: 293072.27 | F3: MXN | G3: 1500030420 | H3: aplicado | I3: AUD PRGX NIVEL SERVICIO 2025 | K3: 46090 | L3: 46035 | M3: 12025 | N3: ZD33 | O3: 2001 | S3: 514375 | T3: BOT_CARGOPRO
A4: 5100421551 | B4: 137 | C4: RA | D4: 46035 | E4: 104772.03 | F4: MXN | G4: 1500030420 | H4: aplicado | I4: AUD PRGX NIVEL SERVICIO 2025 | K4: 46090 | L4: 46035 | M4: 22025 | N4: ZD33 | O4: 2001 | S4: 514375 | T4: BOT_CARGOPRO
A5: 5100421552 | B5: 137 | C5: RA | D5: 46035 | E5: 74217.98 | F5: MXN | G5: 1500030420 | H5: aplicado | I5: AUD PRGX NIVEL SERVICIO 2025 | K5: 46090 | L5: 46035 | M5: 42025 | N5: ZD33 | O5: 2001 | S5: 514375 | T5: BOT_CARGOPRO
A6: 5100421553 | B6: 137 | C6: RA | D6: 46035 | E6: 467518.42 | F6: MXN | G6: 1500030420 | H6: aplicado | I6: AUD PRGX NIVEL SERVICIO 2025 | K6: 46090 | L6: 46035 | M6: 52025 | N6: ZD33 | O6: 2001 | S6: 514375 | T6: BOT_CARGOPRO
A7: 5100421554 | B7: 137 | C7: RA | D7: 46035 | E7: 156092.31 | F7: MXN | G7: 1500030420 | H7: aplicado | I7: AUD PRGX NIVEL SERVICIO 2025 | K7: 46090 | L7: 46035 | M7: 62025 | N7: ZD33 | O7: 2001 | S7: 514375 | T7: BOT_CARGOPRO
A8: 5100421555 | B8: 137 | C8: RA | D8: 46035 | E8: 260718.21 | F8: MXN | G8: 1500030420 | H8: aplicado | I8: AUD PRGX NIVEL SERVICIO 2025 | K8: 46090 | L8: 46035 | M8: 72025 | N8: ZD33 | O8: 2001 | S8: 514375 | T8: BOT_CARGOPRO
A9: 5100421556 | B9: 137 | C9: RA | D9: 46035 | E9: 1158.06 | F9: MXN | G9: 1500030420 | H9: aplicado | I9: AUD PRGX NIVEL SERVICIO 2025 | K9: 46090 | L9: 46035 | M9: 82025 | N9: ZD33 | O9: 2001 | S9: 514375 | T9: BOT_CARGOPRO
A10: 5100421557 | B10: 137 | C10: RA | D10: 46035 | E10: 877.73 | F10: MXN | G10: 1500030420 | H10: aplicado | I10: AUD PRGX NIVEL SERVICIO 2025 | K10: 46090 | L10: 46035 | M10: 92025 | N10: ZD33 | O10: 2001 | S10: 514375 | T10: BOT_CARGOPRO
A11: 5100422412 | B11: 3137 | C11: RA | D11: 46035 | E11: 2463.99 | F11: MXN | G11: 1500038737 | H11: aplicado | I11: AUD PRGX NIVEL SERVICIO 2025 | K11: 46069 | L11: 46035 | M11: 32025 | N11: ZD33 | O11: 2001 | S11: 0 | T11: BOT_CARGOPRO
A12: 5100422417 | B12: 3137 | C12: RA | D12: 46035 | E12: 168978.54 | F12: MXN | G12: 1500038737 | H12: aplicado | I12: AUD PRGX NIVEL SERVICIO 2025 | K12: 46069 | L12: 46035 | M12: 92025 | N12: ZD33 | O12: 2001 | S12: 0 | T12: BOT_CARGOPRO
A13: 5100422419 | B13: 3137 | C13: RA | D13: 46035 | E13: 31525.22 | F13: MXN | G13: 1500038737 | H13: aplicado | I13: AUD PRGX NIVEL SERVICIO 2025 | K13: 46069 | L13: 46035 | M13: 102025 | N13: ZD33 | O13: 2001 | S13: 0 | T13: BOT_CARGOPRO
A14: 5100422411 | B14: 3137 | C14: RA | D14: 46035 | E14: 53531.7 | F14: MXN | G14: 1500038737 | H14: aplicado | I14: AUD PRGX NIVEL SERVICIO 2025 | K14: 46069 | L14: 46035 | M14: 22025 | N14: ZD33 | O14: 2001 | S14: 514152 | T14: BOT_CARGOPRO
... A19: 5100422418 | B19: 3137 | C19: RA | D19: 46035 | E19: 12545.4 | F19: MXN | G19: 1500038737 | H19: aplicado | I19: AUD PRGX NIVEL SERVICIO 2025 | K19: 46069 | L19: 46035 | M19: 92025 | N19: ZD33 | O19: 2001 | S19: 514152 | T19: BOT_CARGOPRO
A20: 5100423147 | B20: 4077 | C20: RA | D20: 46035 | E20: 166679.09 | F20: MXN | G20: 1500090927 | H20: aplicado | I20: AUD PRGX NIVEL SERVICIO 2025 | J20: 8 | K20: 46072 | L20: 46035 | M20: 12025 | N20: ZD33 | O20: 2001 | S20: PROGRAMACION 2302 | T20: BOT_CARGOPRO
A21: 5100423148 | B21: 4077 | C21: RA | D21: 46035 | E21: 943.61 | F21: MXN | G21: 1500090927 | H21: aplicado | I21: AUD PRGX NIVEL SERVICIO 2025 | J21: 8 | K21: 46072 | L21: 46035 | M21: 22025 | N21: ZD33 | O21: 2001 | S21: PROGRAMACION 2302 | T21: BOT_CARGOPRO
A22: 5100423149 | B22: 4077 | C22: RA | D22: 46035 | E22: 1190734.9 | F22: MXN | G22: 1500090927 | H22: aplicado | I22: AUD PRGX NIVEL SERVICIO 2025 | J22: 8 | K22: 46072 | L22: 46035 | M22: 22025 | N22: ZD33 | O22: 2001 | S22: PROGRAMACION 2302 | T22: BOT_CARGOPRO
A23: 5100423150 | B23: 4077 | C23: RA | D23: 46035 | E23: 9767.24 | F23: MXN | G23: 1500090927 | H23: aplicado | I23: AUD PRGX NIVEL SERVICIO 2025 | J23: 8 | K23: 46072 | L23: 46035 | M23: 32025 | N23: ZD33 | O23: 2001 | S23: PROGRAMACION 2302 | T23: BOT_CARGOPRO
A24: 5100423151 | B24: 4077 | C24: RA | D24: 46035 | E24: 4960880.8 | F24: MXN | G24: 1500090927 | H24: aplicado | I24: AUD PRGX NIVEL SERVICIO 2025 | J24: 8 | K24: 46072 | L24: 46035 | M24: 32025 | N24: ZD33 | O24: 2001 | S24: PROGRAMACION 2302 | T24: BOT_CARGOPRO
A25: 5100423152 | B25: 4077 | C25: RA | D25: 46035 | E25: 1422090.7 | F25: MXN | G25: 1500090927 | H25: aplicado | I25: AUD PRGX NIVEL SERVICIO 2025 | J25: 8 | K25: 46072 | L25: 46035 | M25: 42025 | N25: ZD33 | O25: 2001 | S25: PROGRAMACION 2302 | T25: BOT_CARGOPRO
A26: 5100423153 | B26: 4077 | C26: RA | D26: 46035 | E26: 4803337.5 | F26: MXN | G26: 1500090927 | H26: aplicado | I26: AUD PRGX NIVEL SERVICIO 2025 | J26: 8 | K26: 46072 | L26: 46035 | M26: 52025 | N26: ZD33 | O26: 2001 | S26: PROGRAMACION 2302 | T26: BOT_CARGOPRO
A27: 5100423154 | B27: 4077 | C27: RA | D27: 46035 | E27: 2854759.5 | F27: MXN | G27: 1500090927 | H27: aplicado | I27: AUD PRGX NIVEL SERVICIO 2025 | J27: 8 | K27: 46072 | L27: 46035 | M27: 62025 | N27: ZD33 | O27: 2001 | S27: PROGRAMACION 2302 | T27: BOT_CARGOPRO
A28: 5100423155 | B28: 4077 | C28: RA | D28: 46035 | E28: 1820340.2 | F28: MXN | G28: 1500090927 | H28: aplicado | I28: AUD PRGX NIVEL SERVICIO 2025 | J28: 8 | K28: 46072 | L28: 46035 | M28: 72025 | N28: ZD33 | O28: 2001 | S28: PROGRAMACION 2302 | T28: BOT_CARGOPRO
A29: 5100423156 | B29: 4077 | C29: RA | D29: 46035 | E29: 560361.35 | F29: MXN | G29: 1500090927 | H29: aplicado | I29: AUD PRGX NIVEL SERVICIO 2025 | J29: 8 | K29: 46072 | L29: 46035 | M29: 82025 | N29: ZD33 | O29: 2001 | S29: PROGRAMACION 2302 | T29: BOT_CARGOPRO
A30: 5100423157 | B30: 4077 | C30: RA | D30: 46035 | E30: 53555.81 | F30: MXN | G30: 1500090927 | H30: aplicado | I30: AUD PRGX NIVEL SERVICIO 2025 | J30: 8 | K30: 46072 | L30: 46035 | M30: 82025 | N30: ZD34 | O30: 2001 | S30: PROGRAMACION 2302 | T30: BOT_CARGOPRO
A31: 5100423158 | B31: 4077 | C31: RA | D31: 46035 | E31: 209085.6 | F31: MXN | G31: 1500090927 | H31: aplicado | I31: AUD PRGX NIVEL SERVICIO 2025 | J31: 8 | K31: 46072 | L31: 46035 | M31: 92025 | N31: ZD33 | O31: 2001 | S31: PROGRAMACION 2302 | T31: BOT_CARGOPRO
A32: 5100423356 | B32: 5330 | C32: RA | D32: 46035 | E32: 15146.33 | F32: MXN | G32: 1500034424 | H32: aplicado | I32: AUD PRGX NIVEL SERVICIO 2025 | K32: 46084 | L32: 46035 | M32: 62025 | N32: ZD33 | O32: 2001 | S32: PROGRAMACION 0303 | T32: BOT_CARGOPRO
A33: 5100423357 | B33: 5330 | C33: RA | D33: 46035 | E33: 1093857.5 | F33: MXN | G33: 1500034424 | H33: aplicado | I33: AUD PRGX NIVEL SERVICIO 2025 | K33: 46084 | L33: 46035 | M33: 82025 | N33: ZD33 | O33: 2001 | S33: PROGRAMACION 0303 | T33: BOT_CARGOPRO
A34: 5100423358 | B34: 5330 | C34: RA | D34: 46035 | E34: 6682.01 | F34: MXN | G34: 1500034424 | H34: aplicado | I34: AUD PRGX NIVEL SERVICIO 2025 | K34: 46084 | L34: 46035 | M34: 92025 | N34: ZD33 | O34: 2001 | S34: PROGRAMACION 0303 | T34: BOT_CARGOPRO
A35: 5100423466 | B35: 5766 | C35: RA | D35: 46035 | E35: 107388.26 | F35: MXN | G35: 1500048380 | H35: aplicado | I35: AUD PRGX NIVEL SERVICIO 2025 | K35: 46090 | L35: 46035 | M35: 12025 | N35: ZD33 | O35: 2001 | S35: 515480 | T35: BOT_CARGOPRO
A36: 5100423467 | B36: 5766 | C36: RA | D36: 46035 | E36: 162.82 | F36: MXN | G36: 1500048380 | H36: aplicado | I36: AUD PRGX NIVEL SERVICIO 2025 | K36: 46090 | L36: 46035 | M36: 12025 | N36: ZD33 | O36: 2001 | S36: 515480 | T36: BOT_CARGOPRO
A37: 5100423468 | B37: 5766 | C37: RA | D37: 46035 | E37: 185208.96 | F37: MXN | G37: 1500048380 | H37: aplicado | I37: AUD PRGX NIVEL SERVICIO 2025 | K37: 46090 | L37: 46035 | M37: 32025 | N37: ZD33 | O37: 2001 | S37: 515480 | T37: BOT_CARGOPRO
A38: 5100423469 | B38: 5766 | C38: RA | D38: 46035 | E38: 244057.4 | F38: MXN | G38: 1500048380 | H38: aplicado | I38: AUD PRGX NIVEL SERVICIO 2025 | K38: 46090 | L38: 46035 | M38: 42025 | N38: ZD33 | O38: 2001 | S38: 515480 | T38: BOT_CARGOPRO
A39: 5100423886 | B39: 8593 | C39: RA | D39: 46035 | E39: 29398 | F39: MXN | G39: 1500034317 | H39: aplicado | I39: AUD PRGX NIVEL SERVICIO 2025 | K39: 46104 | L39: 46035 | M39: 12025 | N39: ZD33 | O39: 2001 | S39: PROGRAMACION 2303 | T39: BOT_CARGOPRO
A40: 5100423887 | B40: 8593 | C40: RA | D40: 46035 | E40: 1003621.9 | F40: MXN | G40: 1500034317 | H40: aplicado | I40: AUD PRGX NIVEL SERVICIO 2025 | K40: 46104 | L40: 46035 | M40: 22025 | N40: ZD33 | O40: 2001 | S40: PROGRAMACION 2303 | T40: BOT_CARGOPRO
A41: 5100423888 | B41: 8593 | C41: RA | D41: 46035 | E41: 886194.71 | F41: MXN | G41: 1500034317 | H41: aplicado | I41: AUD PRGX NIVEL SERVICIO 2025 | K41: 46104 | L41: 46035 | M41: 32025 | N41: ZD33 | O41: 2001 | S41: PROGRAMACION 2303 | T41: BOT_CARGOPRO
A42: 5100423889 | B42: 8593 | C42: RA | D42: 46035 | E42: 1125.4 | F42: MXN | G42: 1500034317 | H42: aplicado | I42: AUD PRGX NIVEL SERVICIO 2025 | K42: 46104 | L42: 46035 | M42: 42025 | N42: ZD33 | O42: 2001 | S42: PROGRAMACION 2303 | T42: BOT_CARGOPRO
A43: 5100423890 | B43: 8593 | C43: RA | D43: 46035 | E43: 137365.91 | F43: MXN | G43: 1500034317 | H43: aplicado | I43: AUD PRGX NIVEL SERVICIO 2025 | K43: 46104 | L43: 46035 | M43: 42025 | N43: ZD33 | O43: 2001 | S43: PROGRAMACION 2303 | T43: BOT_CARGOPRO
A44: 5100423891 | B44: 8593 | C44: RA | D44: 46035 | E44: 5473.36 | F44: MXN | G44: 1500034317 | H44: aplicado | I44: AUD PRGX NIVEL SERVICIO 2025 | K44: 46104 | L44: 46035 | M44: 52025 | N44: ZD33 | O44: 2001 | S44: PROGRAMACION 2303 | T44: BOT_CARGOPRO
A45: 5100423892 | B45: 8593 | C45: RA | D45: 46035 | E45: 2690890.6 | F45: MXN | G45: 1500034317 | H45: aplicado | I45: AUD PRGX NIVEL SERVICIO 2025 | K45: 46104 | L45: 46035 | M45: 52025 | N45: ZD33 | O45: 2001 | S45: PROGRAMACION 2303 | T45: BOT_CARGOPRO
A46: 5100423893 | B46: 8593 | C46: RA | D46: 46035 | E46: 1068929.5 | F46: MXN | G46: 1500034317 | H46: aplicado | I46: AUD PRGX NIVEL SERVICIO 2025 | K46: 46104 | L46: 46035 | M46: 62025 | N46: ZD33 | O46: 2001 | S46: PROGRAMACION 2303 | T46: BOT_CARGOPRO
A47: 5100423894 | B47: 8593 | C47: RA | D47: 46035 | E47: 2473555.2 | F47: MXN | G47: 1500034317 | H47: aplicado | I47: AUD PRGX NIVEL SERVICIO 2025 | K47: 46104 | L47: 46035 | M47: 72025 | N47: ZD33 | O47: 2001 | S47: PROGRAMACION 2303 | T47: BOT_CARGOPRO
A48: 5100423895 | B48: 8593 | C48: RA | D48: 46035 | E48: 1553121.7 | F48: MXN | G48: 1500034317 | H48: aplicado | I48: AUD PRGX NIVEL SERVICIO 2025 | K48: 46104 | L48: 46035 | M48: 82025 | N48: ZD33 | O48: 2001 | S48: PROGRAMACION 2303 | T48: BOT_CARGOPRO
A49: 5100423896 | B49: 8593 | C49: RA | D49: 46035 | E49: 142383.25 | F49: MXN | G49: 1500034317 | H49: aplicado | I49: AUD PRGX NIVEL SERVICIO 2025 | K49: 46104 | L49: 46035 | M49: 92025 | N49: ZD33 | O49: 2001 | S49: PROGRAMACION 2303 | T49: BOT_CARGOPRO
A50: 5100424051 | B50: 9381 | C50: RA | D50: 46035 | E50: 93891.99 | F50: MXN | G50: 1500107413 | H50: aplicado | I50: AUD PRGX NIVEL SERVICIO 2025 | K50: 46090 | L50: 46035 | M50: 12025 | N50: ZD33 | O50: 2001 | S50: PROGRAMACION 0903 | T50: BOT_CARGOPRO
... A58: 5100424059 | B58: 9381 | C58: RA | D58: 46035 | E58: 128455.33 | F58: MXN | G58: 1500107413 | H58: aplicado | I58: AUD PRGX NIVEL SERVICIO 2025 | K58: 46090 | L58: 46035 | M58: 92025 | N58: ZD33 | O58: 2001 | S58: PROGRAMACION 0903 | T58: BOT_CARGOPRO
A59: 5100034806 | B59: 10348 | C59: RA | D59: 46035 | E59: 238787.34 | F59: MXN | G59: 5100052902 | H59: aplicado | I59: AUD PRGX NIVEL SERVICIO 2025 | J59: 8 | K59: 46035 | L59: 46035 | M59: 52025 | N59: 0 | O59: 2001 | S59: 0 | T59: BOT_CARGOPRO
A60: 5100052902 | B60: 10348 | C60: RA | D60: 46035 | E60: -238787.34 | F60: MXN | G60: 5100052902 | H60: aplicado | I60: AUD PRGX NIVEL SERVICIO 2025 | J60: 8 | K60: 46035 | L60: 46035 | M60: 52025 | N60: 0 | O60: 2001 | S60: 0 | T60: 900505604
A61: 5100227643 | B61: 11361 | C61: RA | D61: 46035 | E61: 64503.59 | F61: MXN | G61: 102143466 | H61: aplicado | I61: AUD PRGX NIVEL SERVICIO 2025 | J61: 0 | K61: 46160 | L61: 46035 | M61: 12025 | N61: ZD33 | O61: 2001 | S61: 2.00159e+17 | T61: BOT_CARGOPRO
A62: 5100227644 | B62: 11361 | C62: RA | D62: 46035 | E62: 402587.27 | F62: MXN | G62: 102143466 | H62: aplicado | I62: AUD PRGX NIVEL SERVICIO 2025 | J62: 0 | K62: 46160 | L62: 46035 | M62: 22025 | N62: ZD33 | O62: 2001 | S62: 2.00159e+17 | T62: BOT_CARGOPRO
A63: 5100227645 | B63: 11361 | C63: RA | D63: 46035 | E63: 70498.07 | F63: MXN | G63: 102143466 | H63: aplicado | I63: AUD PRGX NIVEL SERVICIO 2025 | J63: 0 | K63: 46160 | L63: 46035 | M63: 32025 | N63: ZD33 | O63: 2001 | S63: 2.00159e+17 | T63: BOT_CARGOPRO
A64: 5100227646 | B64: 11361 | C64: RA | D64: 46035 | E64: 5697.97 | F64: MXN | G64: 102143466 | H64: aplicado | I64: AUD PRGX NIVEL SERVICIO 2025 | J64: 0 | K64: 46160 | L64: 46035 | M64: 42025 | N64: ZD33 | O64: 2001 | S64: 2.00159e+17 | T64: BOT_CARGOPRO
A65: 5100227647 | B65: 11361 | C65: RA | D65: 46035 | E65: 207729.38 | F65: MXN | G65: 102143466 | H65: aplicado | I65: AUD PRGX NIVEL SERVICIO 2025 | J65: 0 | K65: 46160 | L65: 46035 | M65: 52025 | N65: ZD33 | O65: 2001 | S65: 2.00159e+17 | T65: BOT_CARGOPRO
A66: 5100227648 | B66: 11361 | C66: RA | D66: 46035 | E66: 125887.62 | F66: MXN | G66: 102143466 | H66: aplicado | I66: AUD PRGX NIVEL SERVICIO 2025 | J66: 0 | K66: 46160 | L66: 46035 | M66: 62025 | N66: ZD33 | O66: 2001 | S66: 2.00159e+17 | T66: BOT_CARGOPRO
A67: 5100227649 | B67: 11361 | C67: RA | D67: 46035 | E67: 19443.76 | F67: MXN | G67: 102143466 | H67: aplicado | I67: AUD PRGX NIVEL SERVICIO 2025 | J67: 0 | K67: 46160 | L67: 46035 | M67: 72025 | N67: ZD33 | O67: 2001 | S67: 2.00159e+17 | T67: BOT_CARGOPRO
A68: 5100227650 | B68: 11361 | C68: RA | D68: 46035 | E68: 16231.61 | F68: MXN | G68: 102143466 | H68: aplicado | I68: AUD PRGX NIVEL SERVICIO 2025 | J68: 0 | K68: 46160 | L68: 46035 | M68: 92025 | N68: ZD33 | O68: 2001 | S68: 2.00159e+17 | T68: BOT_CARGOPRO
A69: 5100034807 | B69: 12480 | C69: RA | D69: 46035 | E69: 159292.86 | F69: MXN | G69: 5100052903 | H69: aplicado | I69: AUD PRGX NIVEL SERVICIO 2025 | J69: 8 | K69: 46035 | L69: 46035 | M69: 62025 | N69: 0 | O69: 2001 | S69: 0 | T69: BOT_CARGOPRO
A70: 5100052903 | B70: 12480 | C70: RA | D70: 46035 | E70: -159292.86 | F70: MXN | G70: 5100052903 | H70: aplicado | I70: AUD PRGX NIVEL SERVICIO 2025 | J70: 8 | K70: 46035 | L70: 46035 | M70: 62025 | N70: 0 | O70: 2001 | S70: 0 | T70: 900505604
A71: 5100052904 | B71: 12995 | C71: RA | D71: 46035 | E71: -6301.55 | F71: MXN | G71: 5100052904 | H71: aplicado | I71: AUD PRGX NIVEL SERVICIO 2025 | J71: 8 | K71: 46035 | L71: 46035 | M71: 72025 | N71: 0 | O71: 2001 | S71: 0 | T71: 900505604
A72: 5100281706 | B72: 12995 | C72: RA | D72: 46035 | E72: 6301.55 | F72: MXN | G72: 5100052904 | H72: aplicado | I72: AUD PRGX NIVEL SERVICIO 2025 | J72: 8 | K72: 46035 | L72: 46035 | M72: 72025 | N72: 0 | O72: 2001 | S72: 0 | T72: BOT_CARGOPRO
A73: 5100421544 | B73: 13642 | C73: RA | D73: 46035 | E73: 109469.5 | F73: MXN | G73: 102043510 | H73: aplicado | I73: AUD PRGX NIVEL SERVICIO 2025 | J73: 0 | K73: 46153 | L73: 46035 | M73: 12025 | N73: ZD33 | O73: 2001 | S73: 2.00159e+17 | T73: BOT_CARGOPRO
A74: 5100421545 | B74: 13642 | C74: RA | D74: 46035 | E74: 216820.97 | F74: MXN | G74: 102043510 | H74: aplicado | I74: AUD PRGX NIVEL SERVICIO 2025 | J74: 0 | K74: 46153 | L74: 46035 | M74: 22025 | N74: ZD33 | O74: 2001 | S74: 2.00159e+17 | T74: BOT_CARGOPRO
A75: 5100421546 | B75: 13642 | C75: RA | D75: 46035 | E75: 6437.05 | F75: MXN | G75: 102043510 | H75: aplicado | I75: AUD PRGX NIVEL SERVICIO 2025 | J75: 0 | K75: 46153 | L75: 46035 | M75: 32025 | N75: ZD33 | O75: 2001 | S75: 2.00159e+17 | T75: BOT_CARGOPRO
A76: 5100421547 | B76: 13642 | C76: RA | D76: 46035 | E76: 8181.49 | F76: MXN | G76: 102043510 | H76: aplicado | I76: AUD PRGX NIVEL SERVICIO 2025 | J76: 0 | K76: 46153 | L76: 46035 | M76: 42025 | N76: ZD33 | O76: 2001 | S76: 2.00159e+17 | T76: BOT_CARGOPRO
A77: 5100421548 | B77: 13642 | C77: RA | D77: 46035 | E77: 112062.37 | F77: MXN | G77: 102043510 | H77: aplicado | I77: AUD PRGX NIVEL SERVICIO 2025 | J77: 0 | K77: 46153 | L77: 46035 | M77: 52025 | N77: ZD33 | O77: 2001 | S77: 2.00159e+17 | T77: BOT_CARGOPRO
A78: 5100421549 | B78: 13642 | C78: RA | D78: 46035 | E78: 192105.93 | F78: MXN | G78: 102043510 | H78: aplicado | I78: AUD PRGX NIVEL SERVICIO 2025 | J78: 0 | K78: 46153 | L78: 46035 | M78: 62025 | N78: ZD33 | O78: 2001 | S78: 2.00159e+17 | T78: BOT_CARGOPRO
A79: 5100421575 | B79: 13860 | C79: RA | D79: 46035 | E79: 290860.78 | F79: MXN | G79: 1500061114 | H79: aplicado | I79: AUD PRGX NIVEL SERVICIO 2025 | K79: 46098 | L79: 46035 | M79: 32025 | N79: ZD33 | O79: 2001 | S79: PROGRAMACION 1703 | T79: BOT_CARGOPRO
A80: 5100421576 | B80: 13860 | C80: RA | D80: 46035 | E80: 3043.35 | F80: MXN | G80: 1500061114 | H80: aplicado | I80: AUD PRGX NIVEL SERVICIO 2025 | K80: 46098 | L80: 46035 | M80: 32025 | N80: ZD33 | O80: 2001 | S80: PROGRAMACION 1703 | T80: BOT_CARGOPRO
A81: 5100421577 | B81: 13860 | C81: RA | D81: 46035 | E81: 162596.36 | F81: MXN | G81: 1500061114 | H81: aplicado | I81: AUD PRGX NIVEL SERVICIO 2025 | K81: 46098 | L81: 46035 | M81: 42025 | N81: ZD33 | O81: 2001 | S81: PROGRAMACION 1703 | T81: BOT_CARGOPRO
A82: 5100421578 | B82: 13860 | C82: RA | D82: 46035 | E82: 34570.64 | F82: MXN | G82: 1500061114 | H82: aplicado | I82: AUD PRGX NIVEL SERVICIO 2025 | K82: 46098 | L82: 46035 | M82: 92025 | N82: ZD33 | O82: 2001 | S82: PROGRAMACION 1703 | T82: BOT_CARGOPRO
A83: 5100421579 | B83: 13860 | C83: RA | D83: 46035 | E83: 194585.23 | F83: MXN | G83: 1500061114 | H83: aplicado | I83: AUD PRGX NIVEL SERVICIO 2025 | K83: 46098 | L83: 46035 | M83: 102025 | N83: ZD33 | O83: 2001 | S83: PROGRAMACION 1703 | T83: BOT_CARGOPRO
A84: 5100254307 | B84: 13860 | C84: RA | D84: 46035 | E84: -290860.78 | F84: MXN | G84: 5100254307 | H84: aplicado | I84: AUD PRGX NIVEL SERVICIO 2025 | J84: 8 | K84: 46035 | L84: 46035 | M84: 32025 | N84: 0 | O84: 2001 | S84: 0 | T84: 900505604
A85: 5100281707 | B85: 13860 | C85: RA | D85: 46035 | E85: 290860.78 | F85: MXN | G85: 5100254307 | H85: aplicado | I85: AUD PRGX NIVEL SERVICIO 2025 | J85: 8 | K85: 46035 | L85: 46035 | M85: 32025 | N85: 0 | O85: 2001 | S85: 0 | T85: BOT_CARGOPRO
A86: 5100254308 | B86: 13860 | C86: RA | D86: 46035 | E86: -162596.36 | F86: MXN | G86: 5100254308 | H86: aplicado | I86: AUD PRGX NIVEL SERVICIO 2025 | J86: 8 | K86: 46035 | L86: 46035 | M86: 42025 | N86: 0 | O86: 2001 | S86: 0 | T86: 900505604
A87: 5100281708 | B87: 13860 | C87: RA | D87: 46035 | E87: 162596.36 | F87: MXN | G87: 5100254308 | H87: aplicado | I87: AUD PRGX NIVEL SERVICIO 2025 | J87: 8 | K87: 46035 | L87: 46035 | M87: 42025 | N87: 0 | O87: 2001 | S87: 0 | T87: BOT_CARGOPRO
A88: 5100254309 | B88: 13860 | C88: RA | D88: 46035 | E88: -34570.64 | F88: MXN | G88: 5100254309 | H88: aplicado | I88: AUD PRGX NIVEL SERVICIO 2025 | J88: 8 | K88: 46035 | L88: 46035 | M88: 92025 | N88: 0 | O88: 2001 | S88: 0 | T88: 900505604
A89: 5100281709 | B89: 13860 | C89: RA | D89: 46035 | E89: 34570.64 | F89: MXN | G89: 5100254309 | H89: aplicado | I89: AUD PRGX NIVEL SERVICIO 2025 | J89: 8 | K89: 46035 | L89: 46035 | M89: 92025 | N89: 0 | O89: 2001 | S89: 0 | T89: BOT_CARGOPRO
A90: 5100254310 | B90: 13860 | C90: RA | D90: 46035 | E90: -194585.23 | F90: MXN | G90: 5100254310 | H90: aplicado | I90: AUD PRGX NIVEL SERVICIO 2025 | J90: 8 | K90: 46035 | L90: 46035 | M90: 102025 | N90: 0 | O90: 2001 | S90: 0 | T90: 900505604
A91: 5100281710 | B91: 13860 | C91: RA | D91: 46035 | E91: 194585.23 | F91: MXN | G91: 5100254310 | H91: aplicado | I91: AUD PRGX NIVEL SERVICIO 2025 | J91: 8 | K91: 46035 | L91: 46035 | M91: 102025 | N91: 0 | O91: 2001 | S91: 0 | T91: BOT_CARGOPRO
A92: 5100395307 | B92: 16747 | C92: RA | D92: 46035 | E92: 707358.82 | F92: MXN | G92: 5100420504 | H92: aplicado | I92: AUD PRGX NIVEL SERVICIO 2025 | J92: 8 | K92: 46035 | L92: 46035 | M92: 52025 | N92: 0 | O92: 2001 | S92: 0 | T92: BOT_CARGOPRO
A93: 5100420504 | B93: 16747 | C93: RA | D93: 46035 | E93: -707358.82 | F93: MXN | G93: 5100420504 | H93: aplicado | I93: AUD PRGX NIVEL SERVICIO 2025 | J93: 8 | K93: 46035 | L93: 46035 | M93: 52025 | N93: 0 | O93: 2001 | S93: 0 | T93: 900505604
A94: 5100395308 | B94: 16747 | C94: RA | D94: 46035 | E94: 55646.14 | F94: MXN | G94: 5100420505 | H94: aplicado | I94: AUD PRGX NIVEL SERVICIO 2025 | J94: 8 | K94: 46035 | L94: 46035 | M94: 62025 | N94: 0 | O94: 2001 | S94: 0 | T94: BOT_CARGOPRO
A95: 5100420505 | B95: 16747 | C95: RA | D95: 46035 | E95: -55646.14 | F95: MXN | G95: 5100420505 | H95: aplicado | I95: AUD PRGX NIVEL SERVICIO 2025 | J95: 8 | K95: 46035 | L95: 46035 | M95: 62025 | N95: 0 | O95: 2001 | S95: 0 | T95: 900505604
A96: 5100421927 | B96: 21943 | C96: RA | D96: 46035 | E96: 29816.84 | F96: MXN | G96: 1500098200 | H96: aplicado | I96: AUD PRGX NIVEL SERVICIO 2025 | K96: 46083 | L96: 46035 | M96: 12025 | N96: ZM33 | O96: 2001 | S96: 517727 | T96: BOT_CARGOPRO
A97: 5100421928 | B97: 21943 | C97: RA | D97: 46035 | E97: 6509.67 | F97: MXN | G97: 1500098200 | H97: aplicado | I97: AUD PRGX NIVEL SERVICIO 2025 | K97: 46083 | L97: 46035 | M97: 22025 | N97: ZM33 | O97: 2001 | S97: 517727 | T97: BOT_CARGOPRO
A98: 5100421929 | B98: 21943 | C98: RA | D98: 46035 | E98: 10061.04 | F98: MXN | G98: 1500098200 | H98: aplicado | I98: AUD PRGX NIVEL SERVICIO 2025 | K98: 46083 | L98: 46035 | M98: 32025 | N98: ZM33 | O98: 2001 | S98: 517727 | T98: BOT_CARGOPRO
A99: 5100421930 | B99: 21943 | C99: RA | D99: 46035 | E99: 449173.34 | F99: MXN | G99: 1500098200 | H99: aplicado | I99: AUD PRGX NIVEL SERVICIO 2025 | K99: 46083 | L99: 46035 | M99: 42025 | N99: ZM33 | O99: 2001 | S99: 517727 | T99: BOT_CARGOPRO
A100: 5100421931 | B100: 21943 | C100: RA | D100: 46035 | E100: 1284567.5 | F100: MXN | G100: 1500098200 | H100: aplicado | I100: AUD PRGX NIVEL SERVICIO 2025 | K100: 46083 | L100: 46035 | M100: 52025 | N100: ZM33 | O100: 2001 | S100: 517727 | T100: BOT_CARGOPRO
A101: 5100421932 | B101: 21943 | C101: RA | D101: 46035 | E101: 468819.82 | F101: MXN | G101: 1500098200 | H101: aplicado | I101: AUD PRGX NIVEL SERVICIO 2025 | K101: 46083 | L101: 46035 | M101: 62025 | N101: ZM33 | O101: 2001 | S101: 517727 | T101: BOT_CARGOPRO
A102: 5100421933 | B102: 21943 | C102: RA | D102: 46035 | E102: 161694.65 | F102: MXN | G102: 1500098200 | H102: aplicado | I102: AUD PRGX NIVEL SERVICIO 2025 | K102: 46083 | L102: 46035 | M102: 72025 | N102: ZM33 | O102: 2001 | S102: 517727 | T102: BOT_CARGOPRO
A103: 5100421934 | B103: 21943 | C103: RA | D103: 46035 | E103: 1155.88 | F103: MXN | G103: 1500098200 | H103: aplicado | I103: AUD PRGX NIVEL SERVICIO 2025 | K103: 46083 | L103: 46035 | M103: 82025 | N103: ZM33 | O103: 2001 | S103: 517727 | T103: BOT_CARGOPRO
A104: 5100421935 | B104: 21943 | C104: RA | D104: 46035 | E104: 248004.94 | F104: MXN | G104: 1500098200 | H104: aplicado | I104: AUD PRGX NIVEL SERVICIO 2025 | K104: 46083 | L104: 46035 | M104: 92025 | N104: ZM33 | O104: 2001 | S104: 517727 | T104: BOT_CARGOPRO
A105: 5100422790 | B105: 37481 | C105: RA | D105: 46035 | E105: 584.51 | F105: MXN | G105: 1500107415 | H105: aplicado | I105: AUD PRGX NIVEL SERVICIO 2025 | K105: 46090 | L105: 46035 | M105: 22025 | N105: ZD33 | O105: 2001 | S105: PROGRAMACION 0903 | T105: BOT_CARGOPRO
A106: 5100422791 | B106: 37481 | C106: RA | D106: 46035 | E106: 175.88 | F106: MXN | G106: 1500107415 | H106: aplicado | I106: AUD PRGX NIVEL SERVICIO 2025 | K106: 46090 | L106: 46035 | M106: 32025 | N106: ZD33 | O106: 2001 | S106: PROGRAMACION 0903 | T106: BOT_CARGOPRO
A107: 5100422792 | B107: 37481 | C107: RA | D107: 46035 | E107: 1520.74 | F107: MXN | G107: 1500107415 | H107: aplicado | I107: AUD PRGX NIVEL SERVICIO 2025 | K107: 46090 | L107: 46035 | M107: 42025 | N107: ZD33 | O107: 2001 | S107: PROGRAMACION 0903 | T107: BOT_CARGOPRO
A108: 5100422793 | B108: 37481 | C108: RA | D108: 46035 | E108: 620205.84 | F108: MXN | G108: 1500107415 | H108: aplicado | I108: AUD PRGX NIVEL SERVICIO 2025 | K108: 46090 | L108: 46035 | M108: 52025 | N108: ZD33 | O108: 2001 | S108: PROGRAMACION 0903 | T108: BOT_CARGOPRO
A109: 5100422794 | B109: 37481 | C109: RA | D109: 46035 | E109: 5810.8 | F109: MXN | G109: 1500107415 | H109: aplicado | I109: AUD PRGX NIVEL SERVICIO 2025 | K109: 46090 | L109: 46035 | M109: 62025 | N109: ZD33 | O109: 2001 | S109: PROGRAMACION 0903 | T109: BOT_CARGOPRO
A110: 5100422795 | B110: 37481 | C110: RA | D110: 46035 | E110: 11017.39 | F110: MXN | G110: 1500107415 | H110: aplicado | I110: AUD PRGX NIVEL SERVICIO 2025 | K110: 46090 | L110: 46035 | M110: 72025 | N110: ZD33 | O110: 2001 | S110: PROGRAMACION 0903 | T110: BOT_CARGOPRO
A111: 5100422796 | B111: 37481 | C111: RA | D111: 46035 | E111: 85676.81 | F111: MXN | G111: 1500107415 | H111: aplicado | I111: AUD PRGX NIVEL SERVICIO 2025 | K111: 46090 | L111: 46035 | M111: 82025 | N111: ZD33 | O111: 2001 | S111: PROGRAMACION 0903 | T111: BOT_CARGOPRO
...

Sheet Reembolsos
F1: 8613844.6 | G1: =F1-G2 -> -4686288.6 | I1: =H2+I2 -> 2468061.7
F2: =SUBTOTAL(9,F4:F1799) -> 15768095 | G2: =SUBTOTAL(9,G4:G1799) -> 13300133 | H2: =SUBTOTAL(9,H4:H1799) -> 810884.12 | I2: =SUBTOTAL(9,I4:I1799) -> 1657177.6
B3: Proveedor | C3: Nombre | D3: Aplicado con Impto | E3: Debe aplicar | F3: Total reembolsar | G3: subtotal | H3: IEPS | I3: IVA | J3: tasa IEPS | K3: tasa IVA | L3: enviado a contraloria | M3: Auditor | O3: comentario auditoria
B4: 696 | C4: INDUSTRIAL NOHRA SA DE CV | D4: 465639.16 | E4: 34914.5 | F4: 430724.66 | G4: 371314.36 | H4: 0 | I4: 59410.298 | J4: 0 | K4: 0.16 | L4: 46111 | M4: Perla | N4: Perla | O4: Monto no procedente informado el 19 de febrero 2026
B5: 3137 | C5: LETICIA PAMMY SA DE CV | D5: 671407.36 | E5: 299401.58 | F5: 372005.78 | G5: 320694.64 | H5: 0 | I5: 51311.14 | J5: 0 | K5: 0.15999999 | L5: 46111 | M5: Perla | N5: Jessica | O5: Monto no procedente informado el 19 de febrero 2026
B6: 48298 | C6: IMPULSORA CAMPIRANO SA DE CV | D6: 400141.22 | E6: 899.3 | F6: 399241.92 | G6: 344174.07 | H6: 0 | I6: 55067.851 | J6: 0 | K6: 0.16 | L6: 46111 | M6: Francisco | N6: Francisco | O6: Monto no procedente informado el 03 de marzo 2026
B7: 311159 | C7: SAUCEDO JAIME GUILLERMO JAVIER | D7: 219055.64 | E7: 0 | F7: 219055.64 | G7: 189068.27 | H7: 0 | I7: 29987.374 | J7: 0 | K7: 0.15860606 | L7: 46111 | M7: Luis | N7: Luis | O7: Monto no procedente informado el 03 de marzo 2026
B8: 8939 | C8: PRODUCTOS DASS SA DE CV | D8: 130896.48 | E8: 19272.7 | F8: 111623.78 | G8: 111623.78 | H8: 0 | I8: 0 | J8: 0 | K8: 0 | L8: 46111 | M8: Yessenia | N8: Samuel | O8: proveedor mandó soporte después del cargo
B9: 325258 | C9: SCHETTINO HERMANOS S DE RL DE CV | D9: 408636.88 | E9: 326883.88 | F9: 81753 | G9: 81753 | H9: 0 | I9: 0 | J9: 0 | K9: 0 | L9: 46111 | M9: Saree | N9: Sareé | O9: proveedor mandó soporte después del cargo
B10: 397984 | C10: COMARKET S.A. DE C.V. | D10: 53357.5 | E10: 0 | F10: 53357.5 | G10: 45997.84 | I10: 7359.66 | J10: 0 | K10: =I10/G10 -> 0.16000012 | L10: 46128 | M10: Yessenia | N10: Yessenia
B11: 397985 | C11: COMARKET S.A. DE C.V. | D11: 53535.64 | E11: 0 | F11: 53535.64 | G11: 46151.41 | I11: 7384.23 | J11: 0 | K11: =I11/G11 -> 0.1600001 | L11: 46128 | M11: Yessenia | N11: Yessenia
B12: 397986 | C12: COMARKET S.A. DE C.V. | D12: 542312.75 | E12: 0 | F12: 542312.75 | G12: 467510.99 | I12: 74801.76 | J12: 0 | K12: =I12/G12 -> 0.16 | L12: 46128 | M12: Yessenia | N12: Yessenia
B13: 397987 | C13: COMARKET S.A. DE C.V. | D13: 327055.94 | E13: 0 | F13: 327055.94 | G13: 281944.78 | I13: 45111.16 | J13: 0 | K13: =I13/G13 -> 0.15999998 | L13: 46128 | M13: Yessenia | N13: Yessenia
B14: 397988 | C14: COMARKET S.A. DE C.V. | D14: 175031.83 | E14: 0 | F14: 175031.83 | G14: 150889.51 | I14: 24142.32 | J14: 0 | K14: =I14/G14 -> 0.15999999 | L14: 46128 | M14: Yessenia | N14: Yessenia
B15: 76471 | C15: NEWELL BRANDS DE MEXICO SA DE CV | D15: 13439248 | F15: 7962909.7 | G15: 6864577.3 | I15: 1098332.4 | J15: 0 | K15: =I15/G15 -> 0.16 | L15: 46136 | M15: Olfi/Raul | N15: Olfi | O15: sistema STIBO errores de captura en unidades de medida INNER PACK y Master PACK
B16: 398024 | C16: PINSA COMERCIAL SA DE CV | D16: 4901364.6 | F16: 1669923.6 | G16: 1669923.6 | H16: 0 | I16: 0 | J16: 0 | K16: 0 | L16: 46142 | M16: Yessenia | N16: Yessenia | O16: Posterior al aviso, se enviaron los soportes correspondientes y se realizó la revisión de la información en conjunto con Controladuría y el área Comercial.
B17: 21869 | C17: PINSA COMERCIAL SA DE CV | D17: 621522.28 | F17: 604955.56 | G17: 604955.56 | H17: 0 | I17: 0 | J17: 0 | K17: 0 | L17: 46142 | M17: Yessenia | N17: Yessenia | O17: Posterior al aviso, se enviaron los soportes correspondientes y se realizó la revisión de la información en conjunto con Controladuría y el área Comercial.
B18: 308421 | C18: PEDRO DOMECQ SA DE CV | D18: 355418.28 | F18: 272767.77 | G18: 185885.08 | H18: 49259.546 | I18: 37623.14 | J18: 0.265 | K18: 0.16 | L18: 46154 | M18: Belem | N18: Belem | O18: Se duplicaron pedidos
B19: 308421 | C19: PEDRO DOMECQ SA DE CV | D19: 2431612.2 | F19: 2221130.6 | G19: 1251482.2 | H19: 663285.57 | I19: 306362.85 | J19: 0.53 | K19: 0.16 | L19: 46154 | M19: Belem | N19: Belem | O19: Se duplicaron pedidos
B20: 8593 | C20: VISION COMERCIAL DEPORTIVA SA DE CV | D20: 9992059.6 | F20: 4286462.2 | G20: 3695226.1 | H20: 0 | I20: 591236.17 | J20: 0 | K20: 0.16 | L20: 46148 | M20: Samuel | N20: Samuel | O20: Proveedor escalado, se reabrió la auditoría, proveedor manda soportes que ampara la improcedencia del saldo
B21: 384776 | C21: VINUX DE MEXICO SA DE CV | D21: 886120.12 | F21: 544536 | G21: 371089 | H21: 98339 | I21: 75108 | J21: 0.265 | K21: 0.16 | L21: 46154 | M21: Luis | N21: Marcela | O21: Posterior al aviso, se enviaron los soportes correspondientes y se realizó la revisión de la información en conjunto con Controladuría y el área Comercial.
B22: 77974 | C22: UNION KIDS SA DE CV | D22: 105820.43 | E22: 50210.2 | F22: 55610.23 | G22: 47939.85 | H22: 0 | I22: 7670.376 | J22: 0 | K22: 0.16 | L22: 46154 | M22: Luis | N22: Yessenia | O22: Posterior al aviso, se enviaron los soportes correspondientes y se realizó la revisión de la información
B23: 11361 | C23: COMERCIALIZADORA CANTU SA DE CV | D23: 1281387.9 | F23: 359375.63 | G23: 309806.59 | H23: 0 | I23: 49569.04 | J23: 0 | K23: 0.16 | L23: 46154 | M23: Luis | N23: Erika | O23: Posterior al aviso, se enviaron los soportes correspondientes y se realizó la revisión de la información en conjunto con Controladuría y el área Comercial.
B24: 13642 | C24: COMERCIALIZADORA CANTU SA DE CV | D24: 645077.31 | F24: 318786.82 | G24: 274816.25 | H24: 0 | I24: 43970.57 | J24: 0 | K24: 0.16 | L24: 46154 | M24: Luis | N24: Luis | O24: Posterior al aviso, se enviaron los soportes correspondientes y se realizó la revisión de la información en conjunto con Controladuría y el área Comercial.
B25: 11914 | C25: HALEON CONSUMER HEALTHCARE MEXICO | D25: 1868684 | F25: 528384.61 | G25: 455503.97 | H25: 0 | I25: 72880.64 | J25: 0 | K25: 0.16 | L25: 46154 | M25: Luis | N25: Luis | O25: Posterior al aviso, se enviaron los soportes correspondientes y se realizó la revisión de la información en conjunto con Controladuría y el área Comercial.
B26: 398024 | C26: PINSA COMERCIAL SA DE CV | D26: 3231441.1 | E26: 1444913.9 | F26: 1786527.1 | G26: 1786527.1 | H26: 0 | I26: 0 | J26: 0 | K26: 0 | L26: 46150 | M26: Yessenia | N26: Yessenia | O26: Posterior al aviso, se enviaron los soportes correspondientes y se realizó la revisión de la información en conjunto con Controladuría y el área Comercial.
B27: 318980 | C27: PRODUCTOS PECUARIOS ESPECIALIZADOS | D27: 245395.5 | E27: 27026.98 | F27: 80344.96 | G27: 69262.9 | H27: 0 | I27: 11082.06 | J27: 0 | K27: 0.16 | L27: 46154 | M27: Raul | N27: Francisco | O27: Proveedor comparte evidencia, en donde se informa sobre articulos inactivos, comercial esta enterado
B28: 3566 | C28: MERCANTIL CUAUTITLAN SA DE CV | D28: 16461.23 | F28: 11164.19 | G28: 11164.19 | H28: 0 | I28: 0 | J28: 0 | K28: 0 | M28: Yessica | N28: Yessica | O28: Después del aviso, el proveedor envió los soportes correspondientes, los cuales se consideran viables para la cancelación del saldo.
B29: 8593 | C29: VISION COMERCIAL DEPORTIVA SA DE CV | D29: 9992059.6 | E29: 0 | F29: 1887904.4 | G29: 1627603.8 | H29: 0 | I29: 260400.6 | J29: 0 | K29: 0.16 | L29: 46170 | M29: Samuel | N29: Samuel | O29: Proveedor escalado, se reabrió la auditoría, proveedor manda soportes que ampara la improcedencia del saldo
B30: 16747 | C30: HOME TEXTILE DESIGNS SA DE CV | D30: 1581808 | F30: 416296.52 | G30: 358876.33 | H30: 0 | I30: 57420.213 | J30: 0 | K30: 0.16 | M30: Yessenia | N30: Yessenia | O30: Posterior al aviso, se enviaron los soportes el area comercila es memo de un pedido
B31: 392092 | C31: ZUCARMEX SA DE CV | D31: 149810.21 | E31: 58894.96 | F31: =+D31-E31 -> 90915.25 | G31: 90915.25 | H31: 0 | I31: 0 | J31: 0 | K31: 0 | M31: Jessica | N31: Jessica | O31: Se recibieron soportes de improcedencia posterior al aviso de cargo
B32: 32953 | C32: FREUDENBERG PRODUCTOS DEL HOGAR SA | D32: 489083.38 | E32: 449226.58 | F32: 39856.8 | G32: 34359.31 | I32: 5497.4896 | K32: 0.16 | M32: Jessica | N32: Jessica | O32: Se recibieron soportes de improcedencia posterior al aviso de cargo
F33: =G33+I33 -> 39856.8 | G33: =F32/1.16 -> 34359.31 | I33: =G33*0.16 -> 5497.4896

Sheet reembolsoxproveedor
A3: Row Labels | B3: Sum of subtotal | C3: Sum of Total reembolsar
A4: 696 | B4: 371314.36 | C4: 430724.66
A5: 3137 | B5: 320694.64 | C5: 372005.78
A6: 3566 | B6: 7548.9 | C6: 7548.9
A7: 8593 | B7: 3695226.1 | C7: 4286462.2
A8: 8939 | B8: 111623.78 | C8: 111623.78
A9: 11361 | B9: 309806.59 | C9: 359375.63
A10: 11914 | B10: 455503.97 | C10: 528384.61
A11: 13642 | B11: 274816.25 | C11: 318786.82
A12: 21869 | B12: 604955.56 | C12: 604955.56
A13: 48298 | B13: 344174.07 | C13: 399241.92
A14: 76471 | B14: 6864577.3 | C14: 7962909.7
A15: 77974 | B15: 47939.85 | C15: 55610.23
... A26: 398024 | B26: 3456450.7 | C26: 3456450.7
A27: Grand Total | B27: 20005667 | C27: 23464962

Sheet reembolso 12May26
B1: Reembolsos Nivel de servicio Enero - Agosto 2025
B2: 12 de mayo 2026
B4: Proveedor | C4: Nombre | D4: Subtotal | E4: IEPS | F4: IVA | G4: Total reembolsar | H4: tasa IEPS | I4: tasa IVA
B5: 308421 | C5: PEDRO DOMECQ SA DE CV | D5: 185885.08 | E5: 49259.546 | F5: 37623.14 | G5: 272767.77 | H5: 0.265 | I5: 0.16
B6: 308421 | C6: PEDRO DOMECQ SA DE CV | D6: 1251482.2 | E6: 663285.57 | F6: 306362.85 | G6: 2221130.6 | H6: 0.53 | I6: 0.16
B7: 384776 | C7: VINUX DE MEXICO SA DE CV | D7: 371089 | E7: 98339 | F7: 75108 | G7: 544536 | H7: 0.265 | I7: 0.16
B8: 77974 | C8: UNION KIDS SA DE CV | D8: 47939.85 | E8: 0 | F8: 7670.376 | G8: 55610.23 | H8: 0 | I8: 0.16
B9: 11361 | C9: COMERCIALIZADORA CANTU SA DE CV | D9: 309806.59 | E9: 0 | F9: 49569.04 | G9: 359375.63 | H9: 0 | I9: 0.16
B10: 13642 | C10: COMERCIALIZADORA CANTU SA DE CV | D10: 274816.25 | E10: 0 | F10: 43970.57 | G10: 318786.82 | H10: 0 | I10: 0.16
B11: 11914 | C11: HALEON CONSUMER HEALTHCARE MEXICO | D11: 455503.97 | E11: 0 | F11: 72880.64 | G11: 528384.61 | H11: 0 | I11: 0.16
B12: 318980 | C12: PRODUCTOS PECUARIOS ESPECIALIZADOS | D12: 69262.9 | E12: 0 | F12: 11082.06 | G12: 80344.96 | H12: 0 | I12: 0.16
D13: =SUM(D5:D12) -> 2965785.9 | G13: =SUM(G5:G12) -> 4380936.7

Sheet aplicados 23feb2026
A2: Proveedor | B2: Nombre | C2: Cargo Publicado en Portal | D2: Penalizacion con Imptos | E2: Aceptado (antes impto) | F2: Pendiente (antes impto) | G2: Soportado (no procede antes impto) | H2: Parcialidad | I2: Observación | J2: contacto | K2: ESTATUS_1 | L2: Acción | M2: Aplicar antes Imptos | N2: Aplicar con Imptos | O2: comentario | P2: Compensado | Q2: Liberado | R2: Bloqueado
A3: 66738 | B3: MONDELEZ MEXICO S DE RL DE CV | C3: 89585265 | D3: 97167062 | F3: 89585265 | H3: - | I3: CARTA PROVEEDOR | J3: CON CONTACTO | K3: DEFINICION FINANZAS | L3: Revisión | P3: - | Q3: - | R3: 97746172
A4: 9647 | B4: FRABEL S.A. DE C.V. | C4: 37170940 | D4: 43117610 | F4: 37170940 | H4: - | I4: NEGATIVA | J4: CON CONTACTO | K4: NEGATIVA ACLARACIONES | L4: Revisión | P4: - | Q4: - | R4: 43117609
A5: 24232 | B5: GRISI HNOS SA DE CV | C5: 17089111 | D5: 19606922 | E5: 2911551.2 | F5: 13683024 | G5: 494535.93 | H5: - | I5: SOLICITA PRORROGA | J5: CON CONTACTO | K5: PDTE POR PROVEEDOR | L5: Aplicar | M5: 16594575 | N5: 19033261 | O5: 20-feb-2026 se informa a proveedor los soportes no son válidos. A reserva de recibir correo de cierre o soportes adicional. | P5: - | Q5: - | R5: 19606922
A6: 4077 | B6: BDF MEXICO S.A DE C.V | C6: 15564009 | D6: 18052536 | E6: 15564009 | F6: - | H6: - | I6: - | J6: CON CONTACTO | K6: CERRADO | L6: Cerrado/Aplicar | M6: 15564009 | N6: 18052537 | P6: - | Q6: - | R6: 18052536
A7: 76471 | B7: NEWELL BRANDS DE MEXICO SA DE CV | C7: 11585559 | D7: 13439248 | F7: 11585559 | H7: - | I7: CONTACTO 28-Ene-2026 | J7: CON CONTACTO | K7: SIN ACLARACION | L7: Aplicar | M7: 11585559 | N7: 13439248 | O7: Sin comentarios del proveedor. | P7: - | Q7: - | R7: 13439248
A8: 99457 | B8: ESSITY HIGIENE Y SALUD MEXICO SA DE | C8: 10217048 | D8: 11176891 | E8: 2126670.9 | F8: 0 | G8: 8090377.5 | H8: - | I8: CARTA OMISION | J8: CON CONTACTO | K8: CERRADO | L8: Cerrado/Aplicar | M8: 2126670.9 | N8: 2355254.9 | P8: - | Q8: - | R8: 11176891
A9: 8593 | B9: VISION COMERCIAL DEPORTIVA SA DE CV | C9: 8613844.6 | D9: 9992059.6 | F9: 8613844.6 | H9: - | I9: - | J9: CON CONTACTO | K9: PDTE POR PROVEEDOR | L9: Aplicar | M9: 8613844.6 | N9: 9992059.8 | O9: Proveedor menciona tiene reunión con dirección comercial Soriana el 19 de febrero. Al dia de hoy sin comentarios o soportes por parte del proveedor. | P9: - | Q9: - | R9: 9992059.6
A10: 90738 | B10: ESSITY HIGIENE Y SALUD MEXICO SA DE | C10: 7245863.5 | D10: 8405201.7 | E10: 3232317.2 | F10: 0 | G10: 4013546.3 | H10: - | I10: CARTA OMISION | J10: CON CONTACTO | K10: CERRADO | L10: Cerrado/Aplicar | M10: 3232317.2 | N10: 3749488.2 | P10: - | Q10: - | R10: 8405201.7
A11: 20125 | B11: MIDEA MEXICO S DE RL DE CV | C11: 7139158.8 | D11: 8281424.2 | F11: 4948440.3 | G11: 2190718.5 | H11: - | I11: - | J11: CON CONTACTO | K11: PDTE POR PROVEEDOR | L11: Aplicar | M11: 4948440.3 | N11: 5740190.7 | O11: 06-feb-2026 proveedor queda en compartir informacion adicional | P11: - | Q11: - | R11: 8281424.2
A12: 56150 | B12: Hershey Mexico SA de CV | C12: 5860104.5 | D12: 6277802.3 | E12: 4589868.4 | F12: 0 | G12: 1270236 | H12: - | I12: - | J12: CON CONTACTO | K12: CERRADO | L12: Cerrado/Aplicar | M12: 4589868.4 | N12: 4911449.5 | P12: - | Q12: - | R12: 6277802.3
A13: 81653 | B13: HEINZ MEXICO SA DE CV | C13: 5448761.5 | D13: 5458465.7 | F13: 5448761.5 | H13: - | I13: CONTACTO 28-Ene-2026 | J13: CON CONTACTO | K13: SIN ACLARACION | L13: Aplicar | M13: 5448761.5 | N13: 5458465.7 | O13: Sin comentarios del proveedor. | P13: - | Q13: - | R13: 5458465.8
A14: 61713 | B14: MALTA TEXO DE MEXICO SA DE CV | C14: 4432996.2 | D14: 5142275.5 | F14: 3568291.3 | G14: 864704.86 | H14: - | I14: CONTACTO 28-Ene-2026 | J14: CON CONTACTO | K14: PDTE POR PROVEEDOR | L14: Revisión | O14: Proveedor quedó en compartir evidencia adicional esta semana 23-feb-2026, aprobacion de compras Soriana de omisión de cobros. | P14: - | Q14: - | R14: 5142275.5
A15: 398024 | B15: PINSA COMERCIAL SA DE CV | C15: 4901364.6 | D15: 4901364.7 | F15: 4901364.6 | H15: - | I15: CONTACTO 28-Ene-2026 | J15: CON CONTACTO | K15: SIN ACLARACION | L15: Aplicar | M15: 4901364.6 | N15: 4901364.6 | P15: - | Q15: - | R15: 4901364.7
A16: 34934 | B16: CARVAJAL EDUCACION S.A. DE C.V. | C16: 4076300.2 | D16: 4728508.2 | E16: 1718185 | F16: 2358115.2 | H16: - | I16: - | J16: CON CONTACTO | K16: PDTE POR PROVEEDOR | L16: Aplicar | M16: 4076300.2 | N16: 4728508.2 | O16: 16-feb-2026 se informa a proveedor que el soporte que envia (Oleaje, resurtidos) no especicifa los pedidos publicados. | P16: - | Q16: - | R16: 4728508.2
A17: 38893 | B17: ABSORMEX CMPC TISSUE SA DE CV | C17: 3414125.4 | D17: 3960385.4 | F17: 3414125.4 | H17: Solicita Prorroga | I17: CONTACTO 28-Ene-2026 SOLICITA 30 DIAS PRORROGA | J17: CON CONTACTO | K17: PDTE POR PROVEEDOR | L17: Revisión | O17: 18-feb-2026 se aclaró con proveedor la metodología del calculo y se solicitó enviar evidencias. | P17: - | Q17: - | R17: 3960385.4
A18: 44040 | B18: LA MADRILENA, S.A. | C18: 2578675.1 | D18: 3794356.6 | F18: 359743.56 | G18: 2218931.6 | H18: - | I18: CONTACTO 28-Ene-2026 | J18: CON CONTACTO | K18: PDTE POR PROVEEDOR | L18: Revisión | P18: - | Q18: - | R18: 3794356.6
A19: 54569 | B19: FERRERO DE MEXICO SA DE CV | C19: 3454984.1 | D19: 3721358.3 | F19: 3454984.1 | H19: - | I19: CONTACTO 28-Ene-2026 | J19: CON CONTACTO | K19: SIN ACLARACION | L19: Revisión | P19: - | Q19: - | R19: 3721358.3
A20: 17921 | B20: PRODUCTOS INTERNACIONALES MABE S.A. | C20: 3189882.4 | D20: 3699944 | F20: 3189882.4 | H20: Solicita Prorroga | I20: CONTACTO 28-Ene-2026 SOLICITA 30 DIAS PRORROGA | J20: CON CONTACTO | K20: PDTE POR PROVEEDOR | L20: Revisión | O20: 18-feb-2026 se aclaró con proveedor la metodología del calculo y se solicitó enviar evidencias. | P20: - | Q20: - | R20: 3699944
A21: 9381 | B21: CHURCH & DWIGHT,S. DE R.L. DE C.V. | C21: 2846318.2 | D21: 3300750 | F21: 2846318.2 | H21: - | I21: - | J21: CON CONTACTO | K21: PDTE POR PROVEEDOR | L21: Aplicar | M21: 2846318.2 | N21: 3300750 | O21: 20-feb-2026 se aclara con proveedor la metodologia del calculo. Proveedor hace calculo a nivel pedido en lugar de hacerlo a nivel material. | P21: - | Q21: - | R21: 3300750
A22: 24489 | B22: REGALOS SIGLO XXI | C22: 2734026.4 | D22: 3171470.8 | F22: 2734026.4 | H22: - | I22: CONTACTO 28-Ene-2026 | J22: CON CONTACTO | K22: SIN ACLARACION | L22: Aplicar | M22: 2734026.4 | N22: 3171470.9 | P22: - | Q22: - | R22: 3171470.8
A23: 71217 | B23: EDGEWELL PERSONAL CARE MEXICO | C23: 2714666.1 | D23: 3145586 | F23: 2714666.1 | H23: - | I23: - | J23: CON CONTACTO | K23: PDTE POR PROVEEDOR | L23: Aplicar | M23: 2714666.1 | N23: 3145586.1 | P23: - | Q23: - | R23: 3145586
A24: 80622 | B24: 3M MEXICO SA DE CV | C24: 2556718.5 | D24: 2965793.5 | F24: 2556718.5 | H24: - | I24: - | J24: CON CONTACTO | K24: PDTE POR AUDITORIA | L24: Revisión | P24: - | Q24: - | R24: 2965793.5
A25: 7875 | B25: LINGERIX SA DE CV | C25: 2514428.2 | D25: 2916736.6 | F25: 2514428.2 | H25: - | I25: CONTACTO 28-Ene-2026 | J25: CON CONTACTO | K25: SIN ACLARACION | L25: Aplicar | M25: 2514428.2 | N25: 2916736.6 | P25: - | Q25: - | R25: 2916736.6
A26: 313387 | B26: NATURASOL S.A. DE C.V. | C26: 2678050.9 | D26: 2823876.7 | F26: 2678050.9 | H26: - | I26: CONTACTO 28-Ene-2026 | J26: CON CONTACTO | K26: SIN ACLARACION | L26: Aplicar | M26: 2678050.9 | N26: 2823876.7 | P26: - | Q26: - | R26: 2823876.7
A27: 308421 | B27: PEDRO DOMECQ SA DE CV | C27: 1612446.7 | D27: 2787030.5 | F27: 1612446.7 | H27: - | I27: CONTACTO 28-Ene-2026 | J27: CON CONTACTO | K27: SIN ACLARACION | L27: Aplicar | M27: 1612446.7 | N27: 2787030.4 | P27: - | Q27: - | R27: 2787030.5
A28: 82511 | B28: HENKEL CAPITAL SA DE CV | C28: 2380059.3 | D28: 2760868.8 | F28: 2380059.3 | H28: - | I28: CONTACTO 28-Ene-2026 | J28: CON CONTACTO | K28: SIN ACLARACION | L28: Aplicar | M28: 2380059.3 | N28: 2760868.8 | P28: - | Q28: - | R28: 2760868.9
A29: 21943 | B29: HENKEL CAPITAL SA DE CV | C29: 2292934.1 | D29: 2659803.7 | F29: 2292934.1 | H29: - | I29: CONTACTO 28-Ene-2026 | J29: CON CONTACTO | K29: SIN ACLARACION | L29: Aplicar | M29: 2292934.1 | N29: 2659803.6 | P29: - | Q29: - | R29: 2659803.7
A30: 364 | B30: MARINDUSTRIAS S.A. DE C.V. | C30: 2535880.7 | D30: 2535881.1 | F30: 2535880.7 | H30: - | I30: - | J30: CON CONTACTO | K30: PDTE POR PROVEEDOR | L30: Aplicar | M30: 2535880.7 | N30: 2535880.7 | P30: - | Q30: - | R30: 2535881.1
A31: 11914 | B31: HALEON CONSUMER HEALTHCARE MEXICO | C31: 2177336.9 | D31: 2525710.9 | F31: 2177336.9 | H31: - | I31: CONTACTO 28-Ene-2026 | J31: CON CONTACTO | K31: PDTE POR AUDITORIA | L31: Revisión | P31: - | Q31: - | R31: 2525710.9
A32: 51698 | B32: BARDAHL DE MEXICO S. A. DE C. V. | C32: 2017199.9 | D32: 2339951.9 | F32: 2017199.9 | H32: - | I32: CONTACTO 28-Ene-2026 | J32: CON CONTACTO | K32: SIN ACLARACION | L32: Aplicar | M32: 2017199.9 | N32: 2339951.9 | P32: - | Q32: - | R32: 2339951.9
A33: 12480 | B33: DETERGENTES Y JABONES SASIL SAPI SA | C33: 1963610.8 | D33: 2277788.4 | F33: 1963610.8 | H33: - | I33: - | J33: CON CONTACTO | K33: PDTE POR PROVEEDOR | L33: Aplicar | M33: 1963610.8 | N33: 2277788.5 | P33: - | Q33: - | R33: 2277788.4
A34: 11042 | B34: BEBIDAS INTERNACIONALES BEPENSA SA | C34: 1539286 | D34: 2258748.2 | F34: 1467671.4 | G34: 71614.62 | H34: - | I34: CONTACTO 28-Ene-2026 | J34: CON CONTACTO | K34: PDTE POR PROVEEDOR | L34: Aplicar | M34: 1467671.4 | N34: 2153661 | P34: - | Q34: - | R34: 2258748.2
A35: 307988 | B35: 4E GLOBAL SAPI DE CV | C35: 1768456.2 | D35: 2051409.4 | F35: 1768456.2 | H35: - | I35: CONTACTO 28-Ene-2026 | J35: CON CONTACTO | K35: SIN ACLARACION | L35: Aplicar | M35: 1768456.2 | N35: 2051409.2 | P35: - | Q35: - | R35: 2051409.4
A36: 319178 | B36: NISSIN FOODS DE MEXICO SA DE CV | C36: 1899275.9 | D36: 1899275.9 | F36: 1307819.1 | G36: 591456.77 | H36: - | I36: - | J36: CON CONTACTO | K36: PDTE POR PROVEEDOR | L36: Aplicar | M36: 1307819.1 | N36: 1307819.1 | P36: - | Q36: - | R36: 1899275.9
A37: 7410 | B37: PRODUCTOS INTERNACIONALES MABE S.A. | C37: 1677791 | D37: 1898195.6 | F37: 1677791 | H37: Solicita Prorroga | I37: CONTACTO 28-Ene-2026 SOLICITA 30 DIAS PRORROGA | J37: CON CONTACTO | K37: PDTE POR PROVEEDOR | L37: Revisión | O37: 18-feb-2026 se aclaró con proveedor la metodología del calculo y se solicitó enviar evidencias. | P37: - | Q37: - | R37: 1898195.6
A38: 303974 | B38: Sales del Istmo SA de CV | C38: 1805198.3 | D38: 1805198.3 | E38: 1799385 | F38: - | G38: 5813 | H38: - | I38: - | J38: CON CONTACTO | K38: CERRADO | L38: Cerrado/Aplicar | M38: 1799385 | N38: 1799385 | P38: - | Q38: - | R38: 1805198.3
A39: 29272 | B39: PRODUCTOS ALIMENTICIOS LA MODERNA S | C39: 1802449.2 | D39: 1802449.2 | F39: 1802449.2 | H39: - | I39: CONTACTO 28-Ene-2026 | J39: CON CONTACTO | K39: SIN ACLARACION | L39: Aplicar | M39: 1802449.2 | N39: 1802449.2 | P39: - | Q39: - | R39: 1802449.2
A40: 21367 | B40: RB HEALTH MEXICO SA DE CV | C40: 1641249.7 | D40: 1725862.8 | E40: 624456.69 | F40: 1016793 | H40: - | I40: CONTACTO 21-Ene-2026 | J40: CON CONTACTO | K40: PDTE POR PROVEEDOR | L40: Aplicar | M40: 1641249.7 | N40: 1725862.8 | P40: - | Q40: - | R40: 1725862.8
A41: 13835 | B41: PASTEURIZADORA MAULEC SA DE CV | C41: 1695399.2 | D41: 1695399.2 | E41: 1565314.2 | G41: 130085 | H41: - | I41: CONTACTO 29-Ene-2026 | J41: CON CONTACTO | K41: CERRADO | L41: Cerrado/Aplicar | M41: 1565314.2 | N41: 1565314.2 | P41: - | Q41: - | R41: 1695399.2
A42: 327197 | B42: H.U.T. INTERNACIONAL S.A. DE C.V. | C42: 1454493.1 | D42: 1687212 | E42: 1026732.7 | G42: 427760.43 | H42: - | I42: - | J42: CON CONTACTO | K42: CERRADO | L42: Cerrado/Aplicar | M42: 1026732.7 | N42: 1191009.9 | P42: - | Q42: - | R42: 1687212
A43: 16747 | B43: HOME TEXTILE DESIGNS SA DE CV | C43: 1363627.6 | D43: 1581808 | F43: 1363627.6 | H43: - | I43: - | J43: CON CONTACTO | K43: PDTE POR PROVEEDOR | L43: Aplicar | M43: 1363627.6 | N43: 1581808 | O43: 28-ene-2026 , se solicitó a proveedor los folios de aportacion del pago y evidencia de la omisión del cobro de otros pedidos. Sin respuesta al dia de hoy 23feb2026 | P43: - | Q43: - | R43: 1581808
A44: 83394 | B44: MARINTER, SA DE C.V | C44: 1061916 | D44: 1568113.2 | E44: 76727.77 | G44: 985188.19 | H44: - | I44: - | J44: CON CONTACTO | K44: CERRADO | L44: Cerrado/Aplicar | M44: 76727.77 | N44: 82743.29 | P44: - | Q44: - | R44: 1568113.2
A45: 305 | B45: PEPSICO STRAUSS FRESH DIPS & SPREAD | C45: 1561609.4 | D45: 1561608.6 | F45: 1561609.4 | H45: - | I45: CONTACTO 28-Ene-2026 | J45: CON CONTACTO | K45: SIN ACLARACION | L45: Aplicar | M45: 1561609.4 | N45: 1561609.4 | P45: - | Q45: - | R45: 1561608.6
A46: 34801 | B46: KOBLENZ ELECTRICA SA DE CV | C46: 1340024.6 | D46: 1554428.6 | F46: 1340024.6 | H46: - | I46: CONTACTO 28-Ene-2026 | J46: CON CONTACTO | K46: SIN ACLARACION | L46: Aplicar | M46: 1340024.6 | N46: 1554428.6 | P46: - | Q46: - | R46: 1554428.6
A47: 312231 | B47: ABBOTT LABORATORIES DE MEXICO SA DE | C47: 1362282.4 | D47: 1546284.5 | F47: 1362282.4 | H47: - | I47: - | J47: CON CONTACTO | K47: PDTE POR PROVEEDOR | L47: Aplicar | M47: 1362282.4 | N47: 1546284.6 | O47: Soporte incompleto no justifica la no entrega, no esta autorizado por comercial. | P47: - | Q47: - | R47: 1546284.5
A48: 75390 | B48: RAGASA INDUSTRIAS SA DE CV | C48: 1455353.9 | D48: 1455353.9 | F48: 1384859.8 | G48: 70494.15 | H48: - | I48: - | J48: CON CONTACTO | K48: PDTE POR PROVEEDOR | L48: Aplicar | M48: 1384859.8 | N48: 1384859.8 | O48: 19-feb-2026 Correo de área comercial Soriana, no está de acuerdo con los margenes del sistema y del cálculo. | P48: - | Q48: - | R48: 1455353.9
A49: 379495 | B49: CORPORACION BEKAX SA DE CV | C49: 1308098.3 | D49: 1406356.9 | F49: 1308098.3 | H49: - | I49: CONTACTO 28-Ene-2026 | J49: CON CONTACTO | K49: SIN ACLARACION | L49: Aplicar | M49: 1308098.3 | N49: 1406356.9 | P49: - | Q49: - | R49: 1406356.9
A50: 51987 | B50: CUETARA DISTRIBUCION SA DE CV | C50: 1298565.3 | D50: 1402450.6 | F50: 1298565.3 | H50: - | I50: CONTACTO 28-Ene-2026 | J50: CON CONTACTO | K50: SIN ACLARACION | L50: Aplicar | M50: 1298565.3 | N50: 1402450.6 | P50: - | Q50: - | R50: 1402450.7
A51: 14833 | B51: CIA SHERWIN WILLIAMS SA DE CV | C51: 1202006.4 | D51: 1394327.6 | F51: 1202006.4 | H51: - | I51: CONTACTO 28-Ene-2026 | J51: CON CONTACTO | K51: SIN ACLARACION | L51: Aplicar | M51: 1202006.4 | N51: 1394327.4 | P51: - | Q51: - | R51: 1394327.6
A52: 55780 | B52: CLOROX DE MEXICO S DE RL DE CV | C52: 1199171 | D52: 1391038.6 | F52: 1199171 | H52: - | I52: CONTACTO 28-Ene-2026 | J52: CON CONTACTO | K52: SIN ACLARACION | L52: Aplicar | M52: 1199171 | N52: 1391038.4 | P52: - | Q52: - | R52: 1391038.6
A53: 325258 | B53: SCHETTINO HERMANOS S DE RL DE CV | C53: 1374858.2 | D53: 1379211 | E53: 323466.15 | F53: 81753.82 | G53: 969638.19 | H53: - | I53: CONTACTO 28-Ene-2026 | J53: CON CONTACTO | K53: PDTE POR PROVEEDOR | L53: Aplicar | M53: 405219.97 | N53: 408637.7 | P53: - | Q53: - | R53: 1379211
A54: 137 | B54: SPECTRUM BRANDS DE MEXICO SA DE CV | C54: 1171057.7 | D54: 1358427 | F54: 1171057.7 | H54: - | I54: CONTACTO 28-Ene-2026 | J54: CON CONTACTO | K54: PDTE POR AUDITORIA | L54: Revisión | P54: - | Q54: - | R54: 1358427
A55: 389783 | B55: COMPA¥IA COMERCIALIZADORA PRODIN CE | C55: 1044840 | D55: 1212014.4 | F55: 1044840 | H55: - | I55: CONTACTO 28-Ene-2026 | J55: CON CONTACTO | K55: SIN ACLARACION | L55: Aplicar | M55: 1044840 | N55: 1212014.4 | P55: - | Q55: - | R55: 1212014.3
A56: 397984 | B56: COMARKET S.A. DE C.V. | C56: 1009288.6 | D56: 1170774.8 | F56: 996068.37 | G56: 13220.22 | H56: - | I56: - | J56: CON CONTACTO | K56: PDTE POR PROVEEDOR | L56: Aplicado | P56: - | Q56: 1170774.8 | R56: -
A57: 383349 | B57: CAPICO DISTRIBUCION S.A. DE C.V. | C57: 1141554 | D57: 1141554 | F57: 1141554 | H57: - | I57: - | J57: CON CONTACTO | K57: PDTE POR PROVEEDOR | L57: Aplicar | M57: 1141554 | N57: 1141554 | P57: - | Q57: - | R57: 1141554
A58: 5330 | B58: NOVELTY CORP.DE MEXICO S.A. DE C.V. | C58: 961798.11 | D58: 1115685.8 | F58: 961798.11 | H58: - | I58: - | J58: CON CONTACTO | K58: PDTE POR PROVEEDOR | L58: Aplicar | M58: 961798.11 | N58: 1115685.8 | P58: - | Q58: - | R58: 1115685.8
A59: 21845 | B59: PRODUCTORA MEXICANA DE ARROZ SAPI | C59: 1064364.9 | D59: 1064364.9 | F59: 1064364.9 | H59: - | I59: CONTACTO 28-Ene-2026 | J59: CON CONTACTO | K59: SIN ACLARACION | L59: Aplicar | M59: 1064364.9 | N59: 1064364.9 | P59: - | Q59: - | R59: 1064364.9
A60: 22068 | B60: ALTA EXTRACCION SA DE CV | C60: 1060303.7 | D60: 1060303.7 | F60: 1060303.7 | H60: - | I60: CONTACTO 28-Ene-2026 | J60: CON CONTACTO | K60: SIN ACLARACION | L60: Aplicar | M60: 1060303.7 | N60: 1060303.7 | P60: - | Q60: - | R60: 1060303.7
A61: 58958 | B61: CINSA SA DE CV | C61: 912839.39 | D61: 1058893.7 | F61: 912839.39 | H61: - | I61: - | J61: SIN CONTACTO | K61: SIN ACLARACION | L61: Aplicar | M61: 912839.39 | N61: 1058893.8 | P61: - | Q61: - | R61: 1058893.7
A62: 387183 | B62: CU FOUNDATIONS SA DE CV | C62: 866011.35 | D62: 1004572.6 | F62: 866011.35 | H62: - | I62: - | J62: CON CONTACTO | K62: PDTE POR PROVEEDOR | L62: Aplicar | M62: 866011.35 | N62: 1004572.6 | P62: - | Q62: - | R62: 1004572.6
A63: 81422 | B63: NO SABE FALLAR S.A DE C.V. | C63: 862425.72 | D63: 1000413.8 | F63: 862425.72 | H63: - | I63: - | J63: SIN CONTACTO | K63: SIN ACLARACION | L63: Aplicar | M63: 862425.72 | N63: 1000413.8 | P63: - | Q63: - | R63: 1000413.8
A64: 394189 | B64: US COTTON MEXICO S DE RL DE CV | C64: 861532.13 | D64: 999377.42 | F64: 861532.13 | H64: - | I64: - | J64: SIN CONTACTO | K64: SIN ACLARACION | L64: Aplicar | M64: 861532.13 | N64: 999377.43 | P64: - | Q64: - | R64: 999377.42
A65: 53256 | B65: PRONUA S.A. DE C.V. | C65: 825790.19 | D65: 957916.6 | E65: 701416.7 | F65: - | G65: 124373.49 | H65: - | I65: - | J65: CON CONTACTO | K65: CERRADO | L65: Cerrado/Aplicar | M65: 701416.7 | N65: 813643.37 | P65: - | Q65: - | R65: 957916.6
A66: 16068 | B66: REPUBLIC NAIL SA DE CV | C66: 821068.11 | D66: 952439.07 | F66: 821068.11 | H66: - | I66: - | J66: SIN CONTACTO | K66: SIN ACLARACION | L66: Aplicado | P66: - | Q66: 952439.05 | R66: -
A67: 33571 | B67: GS ALIMENTOS DE MEXICO SA DE CV | C67: 945096.76 | D67: 945096.76 | F67: 945096.76 | H67: - | I67: - | J67: SIN CONTACTO | K67: SIN ACLARACION | L67: Aplicar | M67: 945096.76 | N67: 945096.76 | P67: - | Q67: - | R67: 945096.76
A68: 304196 | B68: ALIMENTOS TRES G SA DE CV | C68: 927389.66 | D68: 927389.66 | F68: 927389.66 | H68: - | I68: - | J68: SIN CONTACTO | K68: SIN ACLARACION | L68: Aplicar | M68: 927389.66 | N68: 927389.66 | P68: - | Q68: - | R68: 927389.66
A69: 306225 | B69: GIFAN INTERNACIONAL S. DE R.L. DE C | C69: 803396.8 | D69: 916496.61 | F69: 803396.8 | H69: - | I69: - | J69: SIN CONTACTO | K69: SIN ACLARACION | L69: Aplicar | M69: 803396.8 | N69: 916496.88 | P69: - | Q69: - | R69: 916496.61
A70: 11361 | B70: COMERCIALIZADORA CANTU SA DE CV | C70: 786706.16 | D70: 912579.27 | F70: 786706.16 | H70: - | I70: SOLICITA PRORROGA | J70: CON CONTACTO | K70: PDTE POR PROVEEDOR | L70: Aplicar | M70: 786706.16 | N70: 912579.18 | P70: - | Q70: - | R70: 912579.27
A71: 384776 | B71: VINUX DE MEXICO SA DE CV | C71: 603036.43 | D71: 886120.12 | F71: 603036.43 | H71: - | I71: - | J71: CON CONTACTO | K71: PDTE POR PROVEEDOR | L71: Aplicar | M71: 603036.43 | N71: 886120.15 | P71: - | Q71: - | R71: 886120.12
A72: 55798 | B72: TOALLERA POPULAR SA DE CV | C72: 742175.07 | D72: 860923.08 | F72: 742175.07 | H72: - | I72: - | J72: SIN CONTACTO | K72: SIN ACLARACION | L72: Aplicar | M72: 742175.07 | N72: 860923.11 | P72: - | Q72: - | R72: 860923.08
A73: 85902 | B73: COMERCIAL IMPORTADORA S DE RL DE CV | C73: 725653.98 | D73: 841758.63 | F73: 725653.98 | H73: - | I73: - | J73: SIN CONTACTO | K73: SIN ACLARACION | L73: Aplicado | P73: 841758.63 | Q73: - | R73: -
A74: 62760 | B74: APOLO TEXTIL SA DE CV | C74: 721247.01 | D74: 836646.49 | F74: 721247.01 | H74: - | I74: - | J74: SIN CONTACTO | K74: SIN ACLARACION | L74: Aplicar | M74: 721247.01 | N74: 836646.53 | P74: - | Q74: - | R74: 836646.49
A75: 10348 | B75: CUBETAS Y BA¥OS S.A. DE C.V. | C75: 698397.79 | D75: 810141.4 | F75: 698397.79 | H75: - | I75: - | J75: SIN CONTACTO | K75: SIN ACLARACION | L75: Aplicar | M75: 698397.79 | N75: 810141.44 | P75: - | Q75: - | R75: 810141.4
A76: 39057 | B76: DISTRIBUIDORA DE TEXTILES AVANTE S. | C76: 678987.01 | D76: 787624.97 | F76: 678987.01 | H76: - | I76: - | J76: SIN CONTACTO | K76: SIN ACLARACION | L76: Aplicar | M76: 678987.01 | N76: 787625.07 | P76: - | Q76: - | R76: 787624.97
A77: 52480 | B77: EMPACADORA LA MERCED SA DE CV | C77: 740317.29 | D77: 740317.29 | F77: 740317.29 | H77: - | I77: - | J77: SIN CONTACTO | K77: SIN ACLARACION | L77: Aplicar | M77: 740317.29 | N77: 740317.29 | P77: - | Q77: - | R77: 740317.29
A78: 43463 | B78: DISTRIBUIDORA KROMA SA DE CV | C78: 631186.37 | D78: 732176.24 | F78: 631186.37 | H78: - | I78: - | J78: SIN CONTACTO | K78: SIN ACLARACION | L78: Aplicar | M78: 631186.37 | N78: 732176.25 | P78: - | Q78: - | R78: 732176.25
A79: 12995 | B79: PHILIPS MEXICO COMMERCIAL SA DE CV | C79: 630471.07 | D79: 731346.26 | F79: 630471.07 | H79: - | I79: - | J79: SIN CONTACTO | K79: SIN ACLARACION | L79: Aplicar | M79: 630471.07 | N79: 731346.44 | P79: - | Q79: - | R79: 731346.26
A80: 37481 | B80: ORGANIZACION REYNERA SA DE CV | C80: 624993.07 | D80: 724991.98 | F80: 624993.07 | H80: - | I80: - | J80: SIN CONTACTO | K80: SIN ACLARACION | L80: Aplicar | M80: 624993.07 | N80: 724991.97 | P80: - | Q80: - | R80: 724991.97
A81: 318196 | B81: SUNSTAR AMERICAS MEXICO S. de R.L. | C81: 624613.84 | D81: 724552.15 | E81: 584855.57 | G81: 39758.27 | H81: - | I81: - | J81: CON CONTACTO | K81: CERRADO | L81: Cerrado/Aplicar | M81: 584855.57 | N81: 678432.5 | P81: - | Q81: - | R81: 724552.12
A82: 48298 | B82: IMPULSORA CAMPIRANO SA DE CV | C82: 619104.25 | D82: 718160.95 | F82: 344949.32 | G82: 274154.93 | H82: - | I82: - | J82: CON CONTACTO | K82: PDTE POR AUDITORIA | L82: Revisión | P82: - | Q82: - | R82: 718160.95
A83: 44883 | B83: PERNOD RICARD MEXICO, S.A. DE C.V. | C83: 423883.77 | D83: 718071.01 | F83: 423883.77 | H83: - | I83: - | J83: SIN CONTACTO | K83: SIN ACLARACION | L83: Aplicar | M83: 423883.77 | N83: 718071 | P83: - | Q83: - | R83: 718071.01
A84: 316877 | B84: CANADIA DISTRIBUIDORES SA DE CV | C84: 616995.11 | D84: 715714.33 | F84: 616995.11 | H84: - | I84: - | J84: SIN CONTACTO | K84: SIN ACLARACION | L84: Aplicar | M84: 616995.11 | N84: 715714.32 | P84: - | Q84: - | R84: 715714.33
A85: 71233 | B85: STEREN PRODUCTO EMPACADO,S.A. DE C. | C85: 611494.4 | D85: 709333.64 | F85: 611494.4 | H85: - | I85: - | J85: SIN CONTACTO | K85: SIN ACLARACION | L85: Aplicar | M85: 611494.4 | N85: 709333.61 | P85: - | Q85: - | R85: 709333.64
A86: 208892 | B86: EMPACADORA THERBAL S.A. DE C.V. | C86: 686095.39 | D86: 686095.39 | F86: 686095.39 | H86: - | I86: - | J86: SIN CONTACTO | K86: SIN ACLARACION | L86: Aplicar | M86: 686095.39 | N86: 686095.39 | P86: - | Q86: - | R86: 686095.39
A87: 13860 | B87: PLO POP SA DE CV | C87: 591083.08 | D87: 685656.37 | F87: 591083.08 | H87: - | I87: - | J87: CON CONTACTO | K87: PDTE POR PROVEEDOR | L87: Aplicar | M87: 591083.08 | N87: 685656.37 | P87: - | Q87: - | R87: 685656.36
A88: 64014 | B88: CONAGRA FOODS MEXICO SA DE CV | C88: 665488.12 | D88: 679070.34 | E88: 661087.93 | G88: 4400.2 | H88: - | I88: - | J88: CON CONTACTO | K88: CERRADO | L88: Cerrado/Aplicar | M88: 661087.93 | N88: 674670.16 | P88: - | Q88: - | R88: 679070.31
A89: 21853 | B89: DISTRIBUIDORA COLOSO INTERNACIONAL | C89: 674473.88 | D89: 674473.88 | F89: 674473.88 | H89: - | I89: - | J89: SIN CONTACTO | K89: SIN ACLARACION | L89: Aplicar | M89: 674473.88 | N89: 674473.88 | P89: - | Q89: - | R89: 674473.88
A90: 3137 | B90: LETICIA PAMMY SA DE CV | C90: 578799.47 | D90: 671407.36 | E90: 258104.83 | F90: - | G90: 320694.64 | H90: - | I90: CONTACTO 06-Feb-2026 | J90: CON CONTACTO | K90: CERRADO | L90: Aplicado/Reembolsar | O90: Reembolsar $372,005.78 | P90: 671407.36 | Q90: - | R90: -
A91: 86520 | B91: LABORATORIOS AVANT S.A. DE C.V. | C91: 578790.19 | D91: 671396.61 | F91: 578790.19 | H91: - | I91: - | J91: SIN CONTACTO | K91: SIN ACLARACION | L91: Aplicar | M91: 578790.19 | N91: 671396.62 | P91: - | Q91: - | R91: 671396.61
A92: 306571 | B92: AJEMEX SA DE CV | C92: 597144.21 | D92: 660158.44 | F92: 597144.21 | H92: - | I92: - | J92: SIN CONTACTO | K92: SIN ACLARACION | L92: Aplicado | P92: 660158.44 | Q92: - | R92: -
A93: 13642 | B93: COMERCIALIZADORA CANTU SA DE CV | C93: 556101.18 | D93: 645077.31 | F93: 556101.18 | H93: - | I93: SOLICITA PRORROGA | J93: CON CONTACTO | K93: PDTE POR PROVEEDOR | L93: Aplicar | M93: 556101.18 | N93: 645077.31 | P93: - | Q93: - | R93: 645077.31
A94: 21869 | B94: PINSA COMERCIAL SA DE CV | C94: 621522.29 | D94: 621522.28 | F94: 621522.29 | H94: - | I94: - | J94: SIN CONTACTO | K94: SIN ACLARACION | L94: Aplicar | M94: 621522.29 | N94: 621522.29 | P94: - | Q94: - | R94: 621522.28
A95: 79087 | B95: GRUPO HB PS S.A. DE C.V. | C95: 532651.81 | D95: 617876.11 | F95: 101785.73 | G95: 430866.08 | H95: - | I95: CONTACTO 06-Feb-2026 | J95: CON CONTACTO | K95: PDTE POR AUDITORIA | L95: Revisión | P95: - | Q95: - | R95: 617876.11
A96: 32953 | B96: FREUDENBERG PRODUCTOS DEL HOGAR SA | C96: 526702.41 | D96: 610975.08 | E96: 356190 | F96: 65434.19 | G96: 105078.23 | H96: - | I96: - | J96: CON CONTACTO | K96: PDTE POR PROVEEDOR | L96: Aplicar | M96: 421624.19 | N96: 489084.05 | P96: - | Q96: - | R96: 610975.08
A97: 11716 | B97: ARTSANA MEXICO SA DE CV | C97: 507093.83 | D97: 588228.75 | F97: 507093.83 | H97: - | I97: - | J97: SIN CONTACTO | K97: SIN ACLARACION | L97: Aplicar | M97: 507093.83 | N97: 588228.81 | P97: - | Q97: - | R97: 588228.75
A98: 312397 | B98: STAR DEL NORTE S.A. DE C.V. | C98: 556338.23 | D98: 585969.03 | F98: 556338.23 | H98: - | I98: - | J98: SIN CONTACTO | K98: SIN ACLARACION | L98: Aplicado | P98: - | Q98: 585969.03 | R98: -
A99: 58487 | B99: GRUPO INDUSTRIAL CREYSI S.A. DE C.V | C99: 487893.67 | D99: 565956.6 | F99: 487893.67 | H99: - | I99: - | J99: SIN CONTACTO | K99: SIN ACLARACION | L99: Aplicar | M99: 487893.67 | N99: 565956.59 | P99: - | Q99: - | R99: 565956.6
A100: 82370 | B100: PRODUCTOS VERDE VALLE, S.A. DE C.V. | C100: 547009.9 | D100: 550125.82 | F100: 547009.9 | H100: - | I100: - | J100: CON CONTACTO | K100: PDTE POR PROVEEDOR | L100: Aplicar | M100: 547009.9 | N100: 550125.83 | P100: - | Q100: - | R100: 550125.81
A101: 328724 | B101: INDUSTRIAS LAVIN DE MEXICO SA DE CV | C101: 464092.44 | D101: 538347.22 | F101: 464092.44 | H101: - | I101: - | J101: SIN CONTACTO | K101: SIN ACLARACION | L101: Aplicar | M101: 464092.44 | N101: 538347.22 | P101: - | Q101: - | R101: 538347.22
...

Sheet Sheet3
A1: Proveedor | B1: Nombre | C1: Cargo Publicado en Portal | D1: IEPS | E1: IVA | F1: Penalizacion con Imptos | G1: Aceptado (antes impto) | H1: IEPS aceptado | I1: IVA aceptado | J1: Aceptado con Imptos | K1: Pendiente (antes impto) | L1: IEPS pendiente | M1: IVA pendiente | N1: Pendiente con Imptos | O1: Soportado (no procede antes impto) | P1: IEPS no procede | Q1: IVA no procede | R1: Soportado con Imptos | S1: Parcialidad | T1: Observación | U1: contacto | V1: ESTATUS_1 | W1: Avisos Portal | X1: Correos seguimiento | Y1: Acción | Z1: Aplicar antes Imptos | AA1: Aplicar con Imptos | AB1: Observacion actual | AC1: comentario | AD1: Compensado | AE1: Liberado | AF1: Bloqueado | AG1: validacion | AH1: Importe reclama proveedor | AI1: Folios en aclaración | AJ1: Fecha Contacto | AK1: Total_seguimientos_contactos_correos
A2: 66738 | B2: MONDELEZ MEXICO S DE RL DE CV | C2: 89585265 | D2: 2507350.6 | E2: 5074446 | F2: 97167062 | J2: 0 | K2: 89585265 | L2: 2507350.6 | M2: 5074446 | N2: 97167062 | R2: 0 | S2: 0 | T2: CARTA PROVEEDOR | U2: CON CONTACTO | V2: DEFINICION FINANZAS | W2: 4 | Y2: Revisión | AB2: 0 | AD2: 0 | AE2: 0 | AF2: 97746172 | AG2: 97167062 | AH2: 97167062 | AJ2: 46041 | AK2: 0
A3: 9647 | B3: FRABEL S.A. DE C.V. | C3: 37170940 | D3: 0 | E3: 5946668.2 | F3: 43117610 | J3: 0 | K3: 37170940 | L3: 0 | M3: 5946668.2 | N3: 43117608 | R3: 0 | S3: 0 | T3: NEGATIVA | U3: CON CONTACTO | V3: NEGATIVA ACLARACIONES | W3: 4 | Y3: Revisión | AB3: Tema interno | AD3: 0 | AE3: 0 | AF3: 43117609 | AG3: 43117610 | AH3: 43117609 | AJ3: 46043 | AK3: 0
A4: 24232 | B4: GRISI HNOS SA DE CV | C4: 17089111 | D4: 15021.684 | E4: 2502789.4 | F4: 19606922 | G4: 2911551.2 | H4: 0 | I4: 325961.06 | J4: 3237512.2 | K4: 13683024 | L4: 15021.684 | M4: 2097702.6 | N4: 15795748 | O4: 494535.93 | P4: 0 | Q4: 79125.75 | R4: 573661.68 | S4: 0 | T4: SOLICITA PRORROGA | U4: CON CONTACTO | V4: PDTE POR PROVEEDOR | W4: 4 | X4: 10 | Y4: Aplicar | Z4: 16594575 | AA4: 19033261 | AB4: 20-feb-2026 se comparte con proveedor saldo improcedente por 688K de acuerdo con soportes validados, en espera de soportes y respuesta del saldo restante (proveedor manda correo a Dir Comercial con la afectación al margen en caso de que se cobre el saldo) | AC4: 20-feb-2026 se informa a proveedor los soportes no son válidos. A reserva de recibir correo de cierre o soportes adicional. | AD4: 0 | AE4: 0 | AF4: 19606922 | AG4: 19606922 | AH4: 0 | AJ4: 46042 | AK4: 0
A5: 4077 | B5: BDF MEXICO S.A DE C.V | C5: 15564009 | D5: 0 | E5: 2488527.7 | F5: 18052536 | G5: 15564009 | H5: 0 | I5: 2488527.7 | J5: 18052537 | K5: 0 | L5: 0 | M5: 0 | N5: 0 | R5: 0 | S5: 0 | T5: 0 | U5: CON CONTACTO | V5: CERRADO | W5: 4 | Y5: Cerrado/Aplicar | Z5: 15564009 | AA5: 18052537 | AB5: 0 | AD5: 0 | AE5: 0 | AF5: 18052536 | AG5: 18052536 | AH5: 18052536 | AJ5: 46045 | AK5: 0
A6: 76471 | B6: NEWELL BRANDS DE MEXICO SA DE CV | C6: 11585559 | D6: 0 | E6: 1853689.4 | F6: 13439248 | J6: 0 | K6: 11585559 | L6: 0 | M6: 1853689.4 | N6: 13439248 | R6: 0 | S6: 0 | T6: CONTACTO 28-Ene-2026 | U6: CON CONTACTO | V6: SIN ACLARACION | W6: 4 | X6: 1 | Y6: Aplicar | Z6: 11585559 | AA6: 13439248 | AB6: Sin comentarios del proveedor. | AC6: Sin comentarios del proveedor. | AD6: 0 | AE6: 0 | AF6: 13439248 | AG6: 13439248 | AK6: 0
A7: 99457 | B7: ESSITY HIGIENE Y SALUD MEXICO SA DE | C7: 10217048 | D7: 0 | E7: 959842.67 | F7: 11176891 | G7: 2126670.9 | I7: 228584.06 | J7: 2355254.9 | K7: 0.0024101967 | L7: 0 | M7: -0.00067947659 | N7: 0.0017307201 | O7: 8090377.5 | Q7: 731258.61 | R7: 8821636.1 | S7: 0 | T7: CARTA OMISION | U7: CON CONTACTO | V7: CERRADO | W7: 4 | Y7: Cerrado/Aplicar | Z7: 2126670.9 | AA7: 2355254.9 | AB7: 0 | AD7: 0 | AE7: 0 | AF7: 11176891 | AG7: 11176891 | AH7: 9215790.6 | AJ7: 46049 | AK7: 0
A8: 8593 | B8: VISION COMERCIAL DEPORTIVA SA DE CV | C8: 8613844.6 | D8: 0 | E8: 1378215.1 | F8: 9992059.6 | J8: 0 | K8: 8613844.6 | L8: 0 | M8: 1378215.1 | N8: 9992059.8 | R8: 0 | S8: 0 | T8: 0 | U8: CON CONTACTO | V8: PDTE POR PROVEEDOR | W8: 4 | Y8: Aplicar | Z8: 8613844.6 | AA8: 9992059.8 | AB8: Proveedor menciona tiene reunión con dirección comercial Soriana el 19 de febrero. Al dia de hoy sin comentarios o soportes por parte del proveedor. | AC8: Proveedor menciona tiene reunión con dirección comercial Soriana el 19 de febrero. Al dia de hoy sin comentarios o soportes por parte del proveedor. | AD8: 0 | AE8: 0 | AF8: 9992059.6 | AG8: 9992059.6 | AH8: 9992059.6 | AI8: 11 | AJ8: 46042 | AK8: 0
A9: 90738 | B9: ESSITY HIGIENE Y SALUD MEXICO SA DE | C9: 7245863.5 | D9: 0 | E9: 1159338.2 | F9: 8405201.7 | G9: 3232317.2 | I9: 517170.75 | J9: 3749488 | K9: -0.002259267 | L9: 0 | M9: 0.21754143 | N9: 0.21528216 | O9: 4013546.3 | Q9: 642167.2 | R9: 4655713.5 | S9: 0 | T9: CARTA OMISION | U9: CON CONTACTO | V9: CERRADO | W9: 4 | Y9: Cerrado/Aplicar | Z9: 3232317.2 | AA9: 3749488.2 | AB9: 0 | AD9: 0 | AE9: 0 | AF9: 8405201.7 | AG9: 8405201.7 | AH9: 4650882.8 | AJ9: 46049 | AK9: 0
A10: 20125 | B10: MIDEA MEXICO S DE RL DE CV | C10: 7139158.7 | D10: 0 | E10: 1142265.4 | F10: 8281424.2 | J10: 0 | K10: 4948440.3 | L10: 0 | M10: 791750.45 | N10: 5740190.7 | O10: 2190718.5 | P10: 0 | Q10: 350514.95 | R10: 2541233.4 | S10: 0 | T10: 0 | U10: CON CONTACTO | V10: PDTE POR PROVEEDOR | W10: 4 | X10: 3 | Y10: Aplicar | Z10: 4948440.3 | AA10: 5740190.7 | AB10: 03 Contactos 28 ene: correo de contacto inicial 04 feb: reunión vía TEAMS 06 feb El proveedor envia soportes que desestima $2,541 incluido impuesto. Proveedor solicita 10 días adicionales para recabar el monto $5,740 incluido impuestos. El Proveedor copi | AC10: 06-feb-2026 proveedor queda en compartir informacion adicional | AD10: 0 | AE10: 0 | AF10: 8281424.1 | AG10: 8281424.2 | AH10: 544291.47 | AI10: 6 | AJ10: 46056 | AK10: 3
A11: 56150 | B11: Hershey Mexico SA de CV | C11: 5860104.4 | D11: 417698.04 | E11: 0 | F11: 6277802.3 | G11: 4589868.4 | H11: 321581.11 | I11: 0 | J11: 4911449.5 | K11: 0 | M11: 0 | N11: 0 | O11: 1270236 | P11: 96116.929 | Q11: 0 | R11: 1366352.9 | S11: 0 | T11: 0 | U11: CON CONTACTO | V11: CERRADO | W11: 4 | Y11: Cerrado/Aplicar | Z11: 4589868.4 | AA11: 4911449.5 | AB11: 0 | AD11: 0 | AE11: 0 | AF11: 6277802.3 | AG11: 6277802.3 | AH11: 6277802.3 | AJ11: 46042 | AK11: 0
A12: 81653 | B12: HEINZ MEXICO SA DE CV | C12: 5448761.5 | D12: 8396.2742 | E12: 1307.9177 | F12: 5458465.7 | J12: 0 | K12: 5448761.5 | L12: 8396.2742 | M12: 1307.9177 | N12: 5458465.7 | R12: 0 | S12: 0 | T12: CONTACTO 28-Ene-2026 | U12: CON CONTACTO | V12: SIN ACLARACION | W12: 4 | X12: 1 | Y12: Aplicar | Z12: 5448761.5 | AA12: 5458465.7 | AB12: Sin comentarios del proveedor.(1 correo seguimiento) | AC12: Sin comentarios del proveedor. | AD12: 0 | AE12: 0 | AF12: 5458465.8 | AG12: 5458465.7 | AK12: 1
A13: 61713 | B13: MALTA TEXO DE MEXICO SA DE CV | C13: 4432996.1 | D13: 0 | E13: 709279.41 | F13: 5142275.5 | J13: 0 | K13: 3568291.3 | L13: 0 | M13: 570926.64 | N13: 4139217.9 | O13: 864704.86 | Q13: 138352.78 | R13: 1003057.6 | S13: 0 | T13: CONTACTO 28-Ene-2026 | U13: CON CONTACTO | V13: PDTE POR PROVEEDOR | W13: 4 | Y13: Revisión | AB13: Proveedor quedó en compartir evidencia adicional esta semana 23-feb-2026, aprobacion de compras Soriana de omisión de cobros. | AC13: Proveedor quedó en compartir evidencia adicional esta semana 23-feb-2026, aprobacion de compras Soriana de omisión de cobros. | AD13: 0 | AE13: 0 | AF13: 5142275.6 | AG13: 5142275.5 | AH13: 0 | AK13: 0
A14: 398024 | B14: PINSA COMERCIAL SA DE CV | C14: 4901364.6 | D14: 0 | E14: 0 | F14: 4901364.6 | J14: 0 | K14: 4901364.6 | L14: 0 | M14: 0 | N14: 4901364.6 | R14: 0 | S14: 0 | T14: CONTACTO 28-Ene-2026 | U14: CON CONTACTO | V14: SIN ACLARACION | W14: 4 | X14: 1 | Y14: Aplicar | Z14: 4901364.6 | AA14: 4901364.6 | AB14: 0 | AD14: 0 | AE14: 0 | AF14: 4901364.7 | AG14: 4901364.6 | AK14: 0
A15: 34934 | B15: CARVAJAL EDUCACION S.A. DE C.V. | C15: 4076300.2 | D15: 0 | E15: 652208.03 | F15: 4728508.2 | G15: 1718185 | H15: 0 | I15: 274909.6 | J15: 1993094.6 | K15: 2358115.2 | L15: 0 | M15: 377298.43 | N15: 2735413.6 | R15: 0 | S15: 0 | T15: 0 | U15: CON CONTACTO | V15: PDTE POR PROVEEDOR | W15: 4 | Y15: Aplicar | Z15: 4076300.2 | AA15: 4728508.2 | AB15: 16-feb-2026 se informa a proveedor que el soporte que envia (Oleaje, resurtidos) no especicifa los pedidos publicados. | AC15: 16-feb-2026 se informa a proveedor que el soporte que envia (Oleaje, resurtidos) no especicifa los pedidos publicados. | AD15: 0 | AE15: 0 | AF15: 4728508.2 | AG15: 4728508.2 | AH15: 4728508.2 | AI15: 6 | AJ15: 46050 | AK15: 0
A16: 38893 | B16: ABSORMEX CMPC TISSUE SA DE CV | C16: 3414125.4 | D16: 0 | E16: 546260.19 | F16: 3960385.4 | J16: 0 | K16: 3414125.4 | L16: 0 | M16: 546260.19 | N16: 3960385.6 | R16: 0 | S16: Solicita Prorroga | T16: CONTACTO 28-Ene-2026 SOLICITA 30 DIAS PRORROGA | U16: CON CONTACTO | V16: PDTE POR PROVEEDOR | W16: 4 | Y16: Revisión | AB16: 18-feb-2026 se aclaró con proveedor la metodología del calculo y se solicitó enviar evidencias. | AC16: 18-feb-2026 se aclaró con proveedor la metodología del calculo y se solicitó enviar evidencias. | AD16: 0 | AE16: 0 | AF16: 3960385.4 | AG16: 3960385.4 | AH16: 0 | AK16: 0
A17: 44040 | B17: LA MADRILENA, S.A. | C17: 2578675.1 | D17: 692321.96 | E17: 523359.53 | F17: 3794356.6 | J17: 0 | K17: 359743.56 | L17: 99003.45 | M17: 73399.52 | N17: 532146.53 | O17: 2218931.6 | P17: 593318.51 | Q17: 449960.01 | R17: 3262210.1 | S17: 0 | T17: CONTACTO 28-Ene-2026 | U17: CON CONTACTO | V17: PDTE POR PROVEEDOR | W17: 4 | Y17: Revisión | AB17: Se envìo correo el 20-feb-26 nitificando el resultado despues de realizar la revisión de la inforamación recibida,se solicto soportes del saldo pendiente | AD17: 0 | AE17: 0 | AF17: 3794356.6 | AG17: 3794356.6 | AK17: 0
A18: 54569 | B18: FERRERO DE MEXICO SA DE CV | C18: 3454984.1 | D18: 266374.18 | E18: 0 | F18: 3721358.3 | J18: 0 | K18: 3454984.1 | L18: 266374.18 | M18: 0 | N18: 3721358.3 | R18: 0 | S18: 0 | T18: CONTACTO 28-Ene-2026 | U18: CON CONTACTO | V18: SIN ACLARACION | W18: 4 | Y18: Revisión | AB18: 20 de febrero Carmen de aclaraciones solicita nos acerquemos con proveedor para compartir detalle de pedidos, se manda información a proveedor información el 24 de febrero | AD18: 0 | AE18: 0 | AF18: 3721358.3 | AG18: 3721358.3 | AK18: 0
A19: 17921 | B19: PRODUCTOS INTERNACIONALES MABE S.A. | C19: 3189882.4 | D19: 0 | E19: 510061.55 | F19: 3699944 | J19: 0 | K19: 3189882.4 | L19: 0 | M19: 510061.55 | N19: 3699944 | R19: 0 | S19: Solicita Prorroga | T19: CONTACTO 28-Ene-2026 SOLICITA 30 DIAS PRORROGA | U19: CON CONTACTO | V19: PDTE POR PROVEEDOR | W19: 4 | Y19: Revisión | AB19: 18-feb-2026 se aclaró con proveedor la metodología del calculo y se solicitó enviar evidencias. | AC19: 18-feb-2026 se aclaró con proveedor la metodología del calculo y se solicitó enviar evidencias. | AD19: 0 | AE19: 0 | AF19: 3699944 | AG19: 3699944 | AH19: 0 | AK19: 0
A20: 9381 | B20: CHURCH & DWIGHT,S. DE R.L. DE C.V. | C20: 2846318.2 | D20: 0 | E20: 454431.78 | F20: 3300750 | J20: 0 | K20: 2846318.2 | L20: 0 | M20: 454431.78 | N20: 3300750 | R20: 0 | S20: 0 | T20: 0 | U20: CON CONTACTO | V20: PDTE POR PROVEEDOR | W20: 4 | Y20: Aplicar | Z20: 2846318.2 | AA20: 3300750 | AB20: No aplicar todavía el proveedor está dando seguimiento para lass auditorías 2020-2024 y 2025. 20-feb-2026 se aclara con proveedor la metodologia del calculo. Proveedor hace calculo a nivel pedido en lugar de hacerlo a nivel material. | AC20: 20-feb-2026 se aclara con proveedor la metodologia del calculo. Proveedor hace calculo a nivel pedido en lugar de hacerlo a nivel material. | AD20: 0 | AE20: 0 | AF20: 3300750 | AG20: 3300750 | AH20: 0 | AJ20: 46044 | AK20: 0
A21: 24489 | B21: REGALOS SIGLO XXI | C21: 2734026.4 | D21: 0 | E21: 437444.47 | F21: 3171470.8 | J21: 0 | K21: 2734026.4 | L21: 0 | M21: 437444.47 | N21: 3171470.9 | R21: 0 | S21: 0 | T21: CONTACTO 28-Ene-2026 | U21: CON CONTACTO | V21: SIN ACLARACION | W21: 4 | X21: 1 | Y21: Aplicar | Z21: 2734026.4 | AA21: 3171470.9 | AB21: seguimiento se da semanal en conjunto con el tema del 2024, aun sin avance alguno | AD21: 0 | AE21: 0 | AF21: 3171470.8 | AG21: 3171470.8 | AK21: 0
A22: 71217 | B22: EDGEWELL PERSONAL CARE MEXICO | C22: 2714666.1 | D22: 0 | E22: 430920.01 | F22: 3145586 | J22: 0 | K22: 2714666.1 | L22: 0 | M22: 430920.01 | N22: 3145586.1 | R22: 0 | S22: 0 | T22: 0 | U22: CON CONTACTO | V22: PDTE POR PROVEEDOR | W22: 4 | Y22: Aplicar | Z22: 2714666.1 | AA22: 3145586.1 | AB22: 20-Feb-26 Se le envio información que solicitó. En espera de su respuesta. | AD22: 0 | AE22: 0 | AF22: 3145586 | AG22: 3145586 | AH22: 0 | AJ22: 46048 | AK22: 0
A23: 80622 | B23: 3M MEXICO SA DE CV | C23: 2556718.5 | D23: 0 | E23: 409074.99 | F23: 2965793.5 | J23: 0 | K23: 2556718.5 | L23: 0 | M23: 409074.99 | N23: 2965793.5 | R23: 0 | S23: 0 | T23: 0 | U23: CON CONTACTO | V23: PDTE POR AUDITORIA | W23: 4 | Y23: Revisión | AB23: 0 | AD23: 0 | AE23: 0 | AF23: 2965793.5 | AG23: 2965793.5 | AH23: 2362760 | AI23: 4 | AJ23: 46058 | AK23: 0
A24: 7875 | B24: LINGERIX SA DE CV | C24: 2514428.2 | D24: 0 | E24: 402308.46 | F24: 2916736.6 | J24: 0 | K24: 2514428.2 | L24: 0 | M24: 402308.46 | N24: 2916736.6 | R24: 0 | S24: 0 | T24: CONTACTO 28-Ene-2026 | U24: CON CONTACTO | V24: SIN ACLARACION | W24: 4 | X24: 1 | Y24: Aplicar | Z24: 2514428.2 | AA24: 2916736.6 | AB24: 3- feb -2026, Sin respuesta al dia hoy, se le solicito los soportes de cancelacion (1 correos de Seguimiento) | AD24: 0 | AE24: 0 | AF24: 2916736.6 | AG24: 2916736.6 | AK24: 1
A25: 313387 | B25: NATURASOL S.A. DE C.V. | C25: 2678050.9 | D25: 145825.82 | E25: 0 | F25: 2823876.7 | J25: 0 | K25: 2678050.9 | L25: 145825.82 | M25: 0 | N25: 2823876.7 | R25: 0 | S25: 0 | T25: CONTACTO 28-Ene-2026 | U25: CON CONTACTO | V25: SIN ACLARACION | W25: 4 | X25: 1 | Y25: Aplicar | Z25: 2678050.9 | AA25: 2823876.7 | AB25: 1 contacto, se le informa al proveedor de la auditoria | AD25: 0 | AE25: 0 | AF25: 2823876.7 | AG25: 2823876.7 | AK25: 1
A26: 308421 | B26: PEDRO DOMECQ SA DE CV | C26: 1612446.7 | D26: 790165.74 | E26: 384417.99 | F26: 2787030.5 | J26: 0 | K26: 1612446.7 | L26: 790165.74 | M26: 384417.99 | N26: 2787030.4 | R26: 0 | S26: 0 | T26: CONTACTO 28-Ene-2026 | U26: CON CONTACTO | V26: SIN ACLARACION | W26: 4 | X26: 1 | Y26: Aplicar | Z26: 1612446.7 | AA26: 2787030.4 | AB26: 0 | AD26: 0 | AE26: 0 | AF26: 2787030.5 | AG26: 2787030.5 | AK26: 0
A27: 82511 | B27: HENKEL CAPITAL SA DE CV | C27: 2380059.3 | D27: 0 | E27: 380809.51 | F27: 2760868.8 | J27: 0 | K27: 2380059.3 | L27: 0 | M27: 380809.51 | N27: 2760868.8 | R27: 0 | S27: 0 | T27: CONTACTO 28-Ene-2026 | U27: CON CONTACTO | V27: SIN ACLARACION | W27: 4 | X27: 1 | Y27: Aplicar | Z27: 2380059.3 | AA27: 2760868.8 | AB27: 1 contacto se le informa de la auditoria | AD27: 0 | AE27: 0 | AF27: 2760868.9 | AG27: 2760868.8 | AK27: 1
A28: 21943 | B28: HENKEL CAPITAL SA DE CV | C28: 2292934.1 | D28: 0 | E28: 366869.46 | F28: 2659803.7 | J28: 0 | K28: 2292934.1 | L28: 0 | M28: 366869.46 | N28: 2659803.6 | R28: 0 | S28: 0 | T28: CONTACTO 28-Ene-2026 | U28: CON CONTACTO | V28: SIN ACLARACION | W28: 4 | X28: 1 | Y28: Aplicar | Z28: 2292934.1 | AA28: 2659803.6 | AB28: 1 contacto se le informa de la auditoria | AD28: 0 | AE28: 0 | AF28: 2659803.7 | AG28: 2659803.7 | AK28: 1
A29: 364 | B29: MARINDUSTRIAS S.A. DE C.V. | C29: 2535880.7 | D29: 0 | E29: 0 | F29: 2535881.1 | J29: 0 | K29: 2535880.7 | L29: 0 | M29: 0 | N29: 2535880.7 | R29: 0 | S29: 0 | T29: 0 | U29: CON CONTACTO | V29: PDTE POR PROVEEDOR | W29: 4 | Y29: Aplicar | Z29: 2535880.7 | AA29: 2535880.7 | AB29: 6 - feb -2026, Sin respuesta al dia hoy, se le solicito los soportes de cancelacion (1 correos de Seguimiento) | AD29: 0 | AE29: 0 | AF29: 2535881.1 | AG29: 2535881.1 | AH29: 260797.11 | AI29: 1 | AJ29: 46059 | AK29: 1
A30: 11914 | B30: HALEON CONSUMER HEALTHCARE MEXICO | C30: 2177336.9 | D30: 0 | E30: 348373.9 | F30: 2525710.9 | J30: 0 | K30: 2177336.9 | L30: 0 | M30: 348373.9 | N30: 2525710.8 | R30: 0 | S30: 0 | T30: CONTACTO 28-Ene-2026 | U30: CON CONTACTO | V30: PDTE POR AUDITORIA | W30: 4 | Y30: Revisión | AB30: Reunión con proveedor 24 feb 26, menciona saldo procedente, y confirmación de soportes que amparan improcedencia de 110K antes de imp, se dieron 3 seguimiento, una reunión presencial y una sesión | AD30: 0 | AE30: 0 | AF30: 2525710.9 | AG30: 2525710.9 | AK30: 3
A31: 51698 | B31: BARDAHL DE MEXICO S. A. DE C. V. | C31: 2017199.9 | D31: 0 | E31: 322752 | F31: 2339951.9 | J31: 0 | K31: 2017199.9 | L31: 0 | M31: 322752 | N31: 2339951.9 | R31: 0 | S31: 0 | T31: CONTACTO 28-Ene-2026 | U31: CON CONTACTO | V31: SIN ACLARACION | W31: 4 | X31: 1 | Y31: Aplicar | Z31: 2017199.9 | AA31: 2339951.9 | AB31: Proveedor no mandas soportes de improcedencia se tuvo un contacto en correo el 28 de enero en el que se compartió la información de pedidos, en seguimiento del 2020-2024 proveedor hace una llamada el 20 de febrero pero no menciona nada con relación al eje | AD31: 0 | AE31: 0 | AF31: 2339951.9 | AG31: 2339951.9 | AK31: 1
A32: 12480 | B32: DETERGENTES Y JABONES SASIL SAPI SA | C32: 1963610.8 | D32: 0 | E32: 314177.73 | F32: 2277788.4 | J32: 0 | K32: 1963610.8 | L32: 0 | M32: 314177.73 | N32: 2277788.5 | R32: 0 | S32: 0 | T32: 0 | U32: CON CONTACTO | V32: PDTE POR PROVEEDOR | W32: 4 | Y32: Aplicar | Z32: 1963610.8 | AA32: 2277788.5 | AB32: Se enviò correo el 17-feb-26 indicando que se requiere la autorización del area comercial para desestimar unos pedidos que indican que se realizó una solicitud de configuración | AD32: 0 | AE32: 0 | AF32: 2277788.4 | AG32: 2277788.4 | AH32: 2277788.4 | AJ32: 46038 | AK32: 0
A33: 11042 | B33: BEBIDAS INTERNACIONALES BEPENSA SA | C33: 1539286 | D33: 407910.77 | E33: 311551.54 | F33: 2258748.2 | J33: 0 | K33: 1467671.4 | L33: 388932.9 | M33: 297056.74 | N33: 2153661 | O33: 71614.62 | P33: 18977.87 | Q33: 14494.8 | R33: 105087.29 | S33: 0 | T33: CONTACTO 28-Ene-2026 | U33: CON CONTACTO | V33: PDTE POR PROVEEDOR | W33: 4 | Y33: Revisión | AB33: En revisión OC restantes | AD33: 0 | AE33: 0 | AF33: 2258748.2 | AG33: 2258748.2 | AK33: 0
A34: 307988 | B34: 4E GLOBAL SAPI DE CV | C34: 1768456.2 | D34: 0 | E34: 282953 | F34: 2051409.4 | J34: 0 | K34: 1768456.2 | L34: 0 | M34: 282953 | N34: 2051409.2 | R34: 0 | S34: 0 | T34: CONTACTO 28-Ene-2026 | U34: CON CONTACTO | V34: SIN ACLARACION | W34: 4 | X34: 1 | Y34: Aplicar | Z34: 1768456.2 | AA34: 2051409.2 | AB34: 0 | AD34: 0 | AE34: 0 | AF34: 2051409.4 | AG34: 2051409.4 | AK34: 0
A35: 319178 | B35: NISSIN FOODS DE MEXICO SA DE CV | C35: 1899275.9 | D35: 0 | E35: 0 | F35: 1899275.9 | J35: 0 | K35: 1307819.2 | L35: 0 | M35: 0 | N35: 1307819.2 | O35: 591456.77 | P35: 0 | Q35: 0 | R35: 591456.77 | S35: 0 | T35: 0 | U35: CON CONTACTO | V35: PDTE POR PROVEEDOR | W35: 4 | Y35: Revisión | AB35: En revisión OC restantes | AD35: 0 | AE35: 0 | AF35: 1899275.9 | AG35: 1899275.9 | AJ35: 46042 | AK35: 0
A36: 7410 | B36: PRODUCTOS INTERNACIONALES MABE S.A. | C36: 1677791 | D36: 0 | E36: 220404.51 | F36: 1898195.6 | J36: 0 | K36: 1677791 | L36: 0 | M36: 220404.51 | N36: 1898195.5 | R36: 0 | S36: Solicita Prorroga | T36: CONTACTO 28-Ene-2026 SOLICITA 30 DIAS PRORROGA | U36: CON CONTACTO | V36: PDTE POR PROVEEDOR | W36: 4 | X36: 5 | Y36: Revisión | AB36: 05 contactos 29 ene: Agenda de reunion via TEAMs 03 feb: reunion via TEAMS donde se deja claro que el tiempo estimado para NS2025 no se mueve. 04 feb: Proveedor indica que la metodologia de liquidacion presenta diferencias.Se solicita compartir el detall | AC36: 18-feb-2026 se aclaró con proveedor la metodología del calculo y se solicitó enviar evidencias. | AD36: 0 | AE36: 0 | AF36: 1898195.6 | AG36: 1898195.6 | AH36: 0 | AK36: 5
A37: 303974 | B37: Sales del Istmo SA de CV | C37: 1805198.3 | D37: 0 | E37: 0 | F37: 1805198.3 | G37: 1799385 | J37: 1799385 | K37: 0 | L37: 0 | M37: 0 | N37: 0 | O37: 5813 | R37: 5813 | S37: 0 | T37: 0 | U37: CON CONTACTO | V37: CERRADO | W37: 4 | Y37: Cerrado/Aplicar | Z37: 1799385 | AA37: 1799385 | AB37: 0 | AD37: 0 | AE37: 0 | AF37: 1805198.3 | AG37: 1805198.3 | AH37: 1805198.3 | AI37: 16 | AJ37: 46041 | AK37: 0
A38: 29272 | B38: PRODUCTOS ALIMENTICIOS LA MODERNA S | C38: 1802449.2 | D38: 0 | E38: 0 | F38: 1802449.2 | J38: 0 | K38: 1802449.2 | L38: 0 | M38: 0 | N38: 1802449.2 | R38: 0 | S38: 0 | T38: CONTACTO 28-Ene-2026 | U38: CON CONTACTO | V38: SIN ACLARACION | W38: 4 | X38: 1 | Y38: Aplicar | Z38: 1802449.2 | AA38: 1802449.2 | AB38: 28 de enero se envió correo de que se tenian 15 días para la revisión no se ha recibido respuesta | AD38: 0 | AE38: 0 | AF38: 1802449.2 | AG38: 1802449.2 | AK38: 0
A39: 21367 | B39: RB HEALTH MEXICO SA DE CV | C39: 1641249.7 | D39: 0 | E39: 84613.103 | F39: 1725862.8 | G39: 624456.69 | I39: 63085.57 | J39: 687542.26 | K39: 1016793 | L39: 0 | M39: 21527.533 | N39: 1038320.6 | R39: 0 | S39: 0 | T39: CONTACTO 21-Ene-2026 | U39: CON CONTACTO | V39: PDTE POR PROVEEDOR | W39: 4 | Y39: Aplicar | Z39: 1641249.7 | AA39: 1725862.8 | AB39: Se envio ultima notificación el 20 de feb con el resultado del analisis y se solicito soportes de lo que esta pendiente | AD39: 0 | AE39: 0 | AF39: 1725862.8 | AG39: 1725862.8 | AK39: 0
A40: 13835 | B40: PASTEURIZADORA MAULEC SA DE CV | C40: 1695399.3 | D40: 0 | E40: 0 | F40: 1695399.2 | G40: 1565314.3 | J40: 1565314.3 | L40: 0 | M40: 0 | N40: 0 | O40: 130085 | P40: 0 | Q40: 0 | R40: 130085 | S40: 0 | T40: CONTACTO 29-Ene-2026 | U40: CON CONTACTO | V40: CERRADO | W40: 4 | Y40: Cerrado/Aplicar | Z40: 1565314.3 | AA40: 1565314.3 | AB40: 0 | AD40: 0 | AE40: 0 | AF40: 1695399.2 | AG40: 1695399.2 | AK40: 0
A41: 327197 | B41: H.U.T. INTERNACIONAL S.A. DE C.V. | C41: 1454493.1 | D41: 0 | E41: 232718.9 | F41: 1687212 | G41: 1026732.7 | I41: 164277.23 | J41: 1191009.9 | L41: 0 | M41: 0.0028253258 | N41: 0.0028253258 | O41: 427760.43 | Q41: 68441.67 | R41: 496202.1 | S41: 0 | T41: 0 | U41: CON CONTACTO | V41: CERRADO | W41: 4 | Y41: Cerrado/Aplicar | Z41: 1026732.7 | AA41: 1191009.9 | AB41: 0 | AD41: 0 | AE41: 0 | AF41: 1687212 | AG41: 1687212 | AH41: 1228466.7 | AI41: 9 | AJ41: 46049 | AK41: 0
A42: 16747 | B42: HOME TEXTILE DESIGNS SA DE CV | C42: 1363627.6 | D42: 0 | E42: 218180.43 | F42: 1581808 | J42: 0 | K42: 1363627.6 | L42: 0 | M42: 218180.43 | N42: 1581808 | R42: 0 | S42: 0 | T42: 0 | U42: CON CONTACTO | V42: PDTE POR PROVEEDOR | W42: 4 | Y42: Aplicar | Z42: 1363627.6 | AA42: 1581808 | AB42: 28-ene-2026 , se solicitó a proveedor los folios de aportacion del pago y evidencia de la omisión del cobro de otros pedidos. Sin respuesta al dia de hoy 23feb2026 | AC42: 28-ene-2026 , se solicitó a proveedor los folios de aportacion del pago y evidencia de la omisión del cobro de otros pedidos. Sin respuesta al dia de hoy 23feb2026 | AD42: 0 | AE42: 0 | AF42: 1581808 | AG42: 1581808 | AH42: 1581808 | AI42: 1 | AJ42: 46041 | AK42: 0
A43: 83394 | B43: MARINTER, SA DE C.V | C43: 1061916 | D43: 298798.97 | E43: 207398.18 | F43: 1568113.2 | G43: 76727.77 | H43: 3495.93 | I43: 2519.59 | J43: 82743.29 | L43: 0.0040086854 | M43: -0.0074996305 | N43: -0.0034909451 | O43: 985188.19 | P43: 295303.04 | Q43: 204878.6 | R43: 1485369.8 | S43: 0 | T43: 0 | U43: CON CONTACTO | V43: CERRADO | W43: 4 | Y43: Cerrado/Aplicar | Z43: 76727.77 | AA43: 82743.287 | AB43: 0 | AD43: 0 | AE43: 0 | AF43: 1568113.2 | AG43: 1568113.2 | AH43: 1484390.6 | AI43: 2 | AJ43: 46042 | AK43: 0
A44: 305 | B44: PEPSICO STRAUSS FRESH DIPS & SPREAD | C44: 1561609.4 | D44: 0 | E44: 0 | F44: 1561608.6 | J44: 0 | K44: 1561609.4 | L44: 0 | M44: 0 | N44: 1561609.4 | R44: 0 | S44: 0 | T44: CONTACTO 28-Ene-2026 | U44: CON CONTACTO | V44: SIN ACLARACION | W44: 4 | X44: 1 | Y44: Aplicar | Z44: 1561609.4 | AA44: 1561609.4 | AB44: Sin contacto de proveedor | AD44: 0 | AE44: 0 | AF44: 1561608.6 | AG44: 1561608.6 | AK44: 0
A45: 34801 | B45: KOBLENZ ELECTRICA SA DE CV | C45: 1340024.6 | D45: 0 | E45: 214403.94 | F45: 1554428.6 | J45: 0 | K45: 1340024.6 | L45: 0 | M45: 214403.94 | N45: 1554428.6 | R45: 0 | S45: 0 | T45: CONTACTO 28-Ene-2026 | U45: CON CONTACTO | V45: SIN ACLARACION | W45: 4 | X45: 1 | Y45: Aplicar | Z45: 1340024.6 | AA45: 1554428.6 | AB45: 1 contacto se le informa de la publicación de pedidos en el portal | AD45: 0 | AE45: 0 | AF45: 1554428.6 | AG45: 1554428.6 | AK45: 1
A46: 312231 | B46: ABBOTT LABORATORIES DE MEXICO SA DE | C46: 1362282.4 | D46: 0 | E46: 184002.29 | F46: 1546284.5 | J46: 0 | K46: 1362282.4 | L46: 0 | M46: 184002.29 | N46: 1546284.6 | R46: 0 | S46: 0 | T46: 0 | U46: CON CONTACTO | V46: PDTE POR PROVEEDOR | W46: 4 | Y46: Aplicar | Z46: 1362282.4 | AA46: 1546284.6 | AB46: Soporte incompleto no justifica la no entrega, no esta autorizado por comercial. | AC46: Soporte incompleto no justifica la no entrega, no esta autorizado por comercial. | AD46: 0 | AE46: 0 | AF46: 1546284.5 | AG46: 1546284.5 | AH46: 0 | AJ46: 46042 | AK46: 0
A47: 75390 | B47: RAGASA INDUSTRIAS SA DE CV | C47: 1455353.9 | D47: 0 | E47: 0 | F47: 1455353.9 | J47: 0 | K47: 1384859.8 | L47: 0 | M47: 0 | N47: 1384859.8 | O47: 70494.15 | R47: 70494.15 | S47: 0 | T47: 0 | U47: CON CONTACTO | V47: PDTE POR PROVEEDOR | W47: 4 | Y47: Aplicar | Z47: 1384859.8 | AA47: 1384859.8 | AB47: 19-feb-2026 Correo de área comercial Soriana, no está de acuerdo con los margenes del sistema y del cálculo. | AC47: 19-feb-2026 Correo de área comercial Soriana, no está de acuerdo con los margenes del sistema y del cálculo. | AD47: 0 | AE47: 0 | AF47: 1455353.9 | AG47: 1455353.9 | AH47: 0 | AJ47: 46041 | AK47: 26
A48: 379495 | B48: CORPORACION BEKAX SA DE CV | C48: 1308098.3 | D48: 92146.032 | E48: 6112.632 | F48: 1406356.9 | J48: 0 | K48: 1308098.3 | L48: 92146.032 | M48: 6112.632 | N48: 1406356.9 | R48: 0 | S48: 0 | T48: CONTACTO 28-Ene-2026 | U48: CON CONTACTO | V48: SIN ACLARACION | W48: 4 | X48: 1 | Y48: Aplicar | Z48: 1308098.3 | AA48: 1406356.9 | AB48: 0 | AD48: 0 | AE48: 0 | AF48: 1406356.9 | AG48: 1406356.9 | AK48: 0
A49: 51987 | B49: CUETARA DISTRIBUCION SA DE CV | C49: 1298565.3 | D49: 103885.25 | E49: 0 | F49: 1402450.6 | J49: 0 | K49: 1298565.3 | L49: 103885.25 | M49: 0 | N49: 1402450.6 | R49: 0 | S49: 0 | T49: CONTACTO 28-Ene-2026 | U49: CON CONTACTO | V49: SIN ACLARACION | W49: 4 | X49: 1 | Y49: Aplicar | Z49: 1298565.3 | AA49: 1402450.6 | AB49: 1 contacto se le informa de la auditoria | AD49: 0 | AE49: 0 | AF49: 1402450.7 | AG49: 1402450.6 | AK49: 1
A50: 14833 | B50: CIA SHERWIN WILLIAMS SA DE CV | C50: 1202006.4 | D50: 0 | E50: 192321.03 | F50: 1394327.6 | J50: 0 | K50: 1202006.4 | L50: 0 | M50: 192321.03 | N50: 1394327.4 | R50: 0 | S50: 0 | T50: CONTACTO 28-Ene-2026 | U50: CON CONTACTO | V50: SIN ACLARACION | W50: 4 | X50: 1 | Y50: Aplicar | Z50: 1202006.4 | AA50: 1394327.4 | AB50: 0 | AD50: 0 | AE50: 0 | AF50: 1394327.6 | AG50: 1394327.6 | AK50: 0
A51: 55780 | B51: CLOROX DE MEXICO S DE RL DE CV | C51: 1199171 | D51: 0 | E51: 191867.47 | F51: 1391038.6 | J51: 0 | K51: 1199171 | L51: 0 | M51: 191867.47 | N51: 1391038.4 | R51: 0 | S51: 0 | T51: CONTACTO 28-Ene-2026 | U51: CON CONTACTO | V51: SIN ACLARACION | W51: 4 | X51: 1 | Y51: Aplicar | Z51: 1199171 | AA51: 1391038.4 | AB51: 01 contacto: envio de correo incial informando el detalle y adjuntando manual | AD51: 0 | AE51: 0 | AF51: 1391038.6 | AG51: 1391038.6 | AK51: 1
A52: 325258 | B52: SCHETTINO HERMANOS S DE RL DE CV | C52: 1374858.2 | D52: 0 | E52: 4352.8736 | F52: 1379211 | G52: 323466.15 | H52: 0 | I52: 3417.73 | J52: 326883.88 | K52: 81753.818 | L52: 0 | M52: 0.0036 | N52: 81753.822 | O52: 969638.19 | P52: 0 | Q52: 935.14 | R52: 970573.33 | S52: 0 | T52: CONTACTO 28-Ene-2026 | U52: CON CONTACTO | V52: PDTE POR PROVEEDOR | W52: 4 | Y52: Revisión | AB52: En revisión OC que se cobran 100% | AD52: 0 | AE52: 0 | AF52: 1379211 | AG52: 1379211 | AK52: 0
A53: 137 | B53: SPECTRUM BRANDS DE MEXICO SA DE CV | C53: 1171057.7 | D53: 0 | E53: 187369.24 | F53: 1358427 | J53: 0 | K53: 1171057.7 | L53: 0 | M53: 187369.24 | N53: 1358427 | R53: 0 | S53: 0 | T53: CONTACTO 28-Ene-2026 | U53: CON CONTACTO | V53: PDTE POR AUDITORIA | W53: 4 | Y53: Aplicar | Z53: 1171057.7 | AA53: 1358427 | AB53: Proveedor no da respuesta, no presenta soportes, un seguimiento con la notificación del importe | AD53: 0 | AE53: 0 | AF53: 1358427 | AG53: 1358427 | AK53: 1
A54: 389783 | B54: COMPA¥IA COMERCIALIZADORA PRODIN CE | C54: 1044840 | D54: 0 | E54: 167174.4 | F54: 1212014.4 | J54: 0 | K54: 1044840 | L54: 0 | M54: 167174.4 | N54: 1212014.4 | R54: 0 | S54: 0 | T54: CONTACTO 28-Ene-2026 | U54: CON CONTACTO | V54: SIN ACLARACION | W54: 4 | X54: 1 | Y54: Aplicar | Z54: 1044840 | AA54: 1212014.4 | AB54: 1 contacto, se le informa al proveedor de la auditoria, proveedor comenta que si tiene alguna duda nos contacta. | AD54: 0 | AE54: 0 | AF54: 1212014.3 | AG54: 1212014.4 | AK54: 1
A55: 397984 | B55: COMARKET S.A. DE C.V. | C55: 1009288.6 | D55: 0 | E55: 161486.17 | F55: 1170774.8 | J55: 0 | K55: 996068.37 | L55: 0 | M55: 159370.93 | N55: 1155439.3 | O55: 13220.22 | P55: 0 | Q55: 2115.24 | R55: 15335.46 | S55: 0 | T55: 0 | U55: CON CONTACTO | V55: PDTE POR PROVEEDOR | W55: 4 | Y55: Aplicado | AB55: 0 | AD55: 0 | AE55: 1170774.8 | AF55: 0 | AG55: 0 | AH55: 1170774.8 | AI55: 6 | AJ55: 46058 | AK55: 0
A56: 383349 | B56: CAPICO DISTRIBUCION S.A. DE C.V. | C56: 1141554 | D56: 0 | E56: 0 | F56: 1141554 | J56: 0 | K56: 1141554 | L56: 0 | M56: 0 | N56: 1141554 | R56: 0 | S56: 0 | T56: 0 | U56: CON CONTACTO | V56: PDTE POR PROVEEDOR | W56: 4 | Y56: Aplicar | Z56: 1141554 | AA56: 1141554 | AB56: Proveedor información no contundente, dice tener un convenio actualizado de no negociación de FR se solicitó y aún no lo envía | AD56: 0 | AE56: 0 | AF56: 1141554 | AG56: 1141554 | AJ56: 46048 | AK56: 0
A57: 5330 | B57: NOVELTY CORP.DE MEXICO S.A. DE C.V. | C57: 961798.11 | D57: 0 | E57: 153887.7 | F57: 1115685.8 | J57: 0 | K57: 961798.11 | L57: 0 | M57: 153887.7 | N57: 1115685.8 | R57: 0 | S57: 0 | T57: 0 | U57: CON CONTACTO | V57: PDTE POR PROVEEDOR | W57: 4 | Y57: Aplicar | Z57: 961798.11 | AA57: 1115685.8 | AB57: Proveedor no presenta soportes de improcedenica, ultima fecha de seguimiento 20 de febrero 2026, tres correos de seguimiento | AD57: 0 | AE57: 0 | AF57: 1115685.8 | AG57: 1115685.8 | AH57: 1115685.8 | AI57: 3 | AJ57: 46041 | AK57: 3
A58: 21845 | B58: PRODUCTORA MEXICANA DE ARROZ SAPI | C58: 1064364.9 | D58: 0 | E58: 0 | F58: 1064364.9 | J58: 0 | K58: 1064364.9 | L58: 0 | M58: 0 | N58: 1064364.9 | R58: 0 | S58: 0 | T58: CONTACTO 28-Ene-2026 | U58: CON CONTACTO | V58: SIN ACLARACION | W58: 4 | X58: 1 | Y58: Aplicar | Z58: 1064364.9 | AA58: 1064364.9 | AB58: 0 | AD58: 0 | AE58: 0 | AF58: 1064364.9 | AG58: 1064364.9 | AK58: 0
A59: 22068 | B59: ALTA EXTRACCION SA DE CV | C59: 1060303.7 | D59: 0 | E59: 0 | F59: 1060303.7 | J59: 0 | K59: 1060303.7 | L59: 0 | M59: 0 | N59: 1060303.7 | R59: 0 | S59: 0 | T59: CONTACTO 28-Ene-2026 | U59: CON CONTACTO | V59: SIN ACLARACION | W59: 4 | X59: 1 | Y59: Aplicar | Z59: 1060303.7 | AA59: 1060303.7 | AB59: 0 | AD59: 0 | AE59: 0 | AF59: 1060303.7 | AG59: 1060303.7 | AK59: 0
A60: 58958 | B60: CINSA SA DE CV | C60: 912839.39 | D60: 0 | E60: 146054.36 | F60: 1058893.7 | J60: 0 | K60: 912839.39 | L60: 0 | M60: 146054.36 | N60: 1058893.7 | R60: 0 | S60: 0 | T60: 0 | U60: SIN CONTACTO | V60: SIN ACLARACION | W60: 4 | Y60: Aplicar | Z60: 912839.39 | AA60: 1058893.7 | AB60: Se le informa a proveedor sobre el comunicado dentro del portal | AD60: 0 | AE60: 0 | AF60: 1058893.7 | AG60: 1058893.7 | AK60: 0
A61: 387183 | B61: CU FOUNDATIONS SA DE CV | C61: 866011.35 | D61: 0 | E61: 138561.24 | F61: 1004572.6 | J61: 0 | K61: 866011.35 | L61: 0 | M61: 138561.24 | N61: 1004572.6 | R61: 0 | S61: 0 | T61: 0 | U61: CON CONTACTO | V61: PDTE POR PROVEEDOR | W61: 4 | X61: 1 | Y61: Aplicar | Z61: 866011.35 | AA61: 1004572.6 | AB61: 1 contacto se le informa de la publicación de pedidos en el portal | AD61: 0 | AE61: 0 | AF61: 1004572.6 | AG61: 1004572.6 | AH61: 1004572.6 | AI61: 7 | AJ61: 46042 | AK61: 1
A62: 81422 | B62: NO SABE FALLAR S.A DE C.V. | C62: 862425.72 | D62: 0 | E62: 137988.12 | F62: 1000413.8 | J62: 0 | K62: 862425.72 | L62: 0 | M62: 137988.12 | N62: 1000413.8 | R62: 0 | S62: 0 | T62: 0 | U62: SIN CONTACTO | V62: SIN ACLARACION | W62: 4 | Y62: Aplicar | Z62: 862425.72 | AA62: 1000413.8 | AB62: 0 | AD62: 0 | AE62: 0 | AF62: 1000413.8 | AG62: 1000413.8 | AK62: 0
A63: 394189 | B63: US COTTON MEXICO S DE RL DE CV | C63: 861532.13 | D63: 0 | E63: 137845.3 | F63: 999377.42 | J63: 0 | K63: 861532.13 | L63: 0 | M63: 137845.3 | N63: 999377.43 | R63: 0 | S63: 0 | T63: 0 | U63: SIN CONTACTO | V63: SIN ACLARACION | W63: 4 | Y63: Aplicar | Z63: 861532.13 | AA63: 999377.43 | AB63: Sin acercamiento por parte del proveedor, actualmente pendiente auditoria del 2020-2024 | AD63: 0 | AE63: 0 | AF63: 999377.42 | AG63: 999377.42 | AK63: 0
A64: 53256 | B64: PRONUA S.A. DE C.V. | C64: 825790.19 | D64: 0 | E64: 132126.43 | F64: 957916.6 | G64: 701416.7 | H64: 0 | I64: 112226.67 | J64: 813643.37 | K64: 0 | L64: 0 | M64: 0 | N64: 0 | O64: 124373.49 | P64: 0 | Q64: 19899.76 | R64: 144273.25 | S64: 0 | T64: 0 | U64: CON CONTACTO | V64: CERRADO | W64: 4 | Y64: Cerrado/Aplicar | Z64: 701416.7 | AA64: 813643.37 | AB64: 0 | AD64: 0 | AE64: 0 | AF64: 957916.6 | AG64: 957916.6 | AH64: 268439.49 | AI64: 1 | AJ64: 46048 | AK64: 0
A65: 16068 | B65: REPUBLIC NAIL SA DE CV | C65: 821068.11 | D65: 0 | E65: 131370.88 | F65: 952439.07 | J65: 0 | K65: 821068.11 | L65: 0 | M65: 131370.88 | N65: 952438.99 | R65: 0 | S65: 0 | T65: 0 | U65: SIN CONTACTO | V65: SIN ACLARACION | W65: 4 | Y65: Aplicado | AB65: Sin contacto de proveedor | AD65: 0 | AE65: 952439.05 | AF65: 0 | AG65: 0.0178 | AK65: 0
A66: 33571 | B66: GS ALIMENTOS DE MEXICO SA DE CV | C66: 945096.76 | D66: 0 | E66: 0 | F66: 945096.76 | J66: 0 | K66: 945096.76 | L66: 0 | M66: 0 | N66: 945096.76 | R66: 0 | S66: 0 | T66: 0 | U66: SIN CONTACTO | V66: SIN ACLARACION | W66: 4 | Y66: Aplicar | Z66: 945096.76 | AA66: 945096.76 | AB66: 0 | AD66: 0 | AE66: 0 | AF66: 945096.76 | AG66: 945096.76 | AK66: 0
A67: 304196 | B67: ALIMENTOS TRES G SA DE CV | C67: 927389.66 | D67: 0 | E67: 0 | F67: 927389.66 | J67: 0 | K67: 927389.66 | L67: 0 | M67: 0 | N67: 927389.66 | R67: 0 | S67: 0 | T67: 0 | U67: SIN CONTACTO | V67: SIN ACLARACION | W67: 4 | Y67: Aplicar | Z67: 927389.66 | AA67: 927389.66 | AB67: 0 | AD67: 0 | AE67: 0 | AF67: 927389.66 | AG67: 927389.66 | AK67: 0
A68: 306225 | B68: GIFAN INTERNACIONAL S. DE R.L. DE C | C68: 803396.8 | D68: 6186.5016 | E68: 106913.58 | F68: 916496.61 | J68: 0 | K68: 803396.8 | L68: 6186.5016 | M68: 106913.58 | N68: 916496.88 | R68: 0 | S68: 0 | T68: 0 | U68: SIN CONTACTO | V68: SIN ACLARACION | W68: 4 | Y68: Aplicar | Z68: 803396.8 | AA68: 916496.88 | AB68: Proveedor no presenta soportes de improcedencia, ultima fecha de seguimiento 16 de febrero 2026 | AD68: 0 | AE68: 0 | AF68: 916496.61 | AG68: 916496.61 | AK68: 0
A69: 11361 | B69: COMERCIALIZADORA CANTU SA DE CV | C69: 786706.16 | D69: 0 | E69: 125873.02 | F69: 912579.27 | J69: 0 | K69: 786706.16 | L69: 0 | M69: 125873.02 | N69: 912579.18 | R69: 0 | S69: 0 | T69: SOLICITA PRORROGA | U69: CON CONTACTO | V69: PDTE POR PROVEEDOR | W69: 4 | X69: 10 | Y69: Aplicar | Z69: 786706.16 | AA69: 912579.18 | AB69: 10 contactos, se involucra Ana Ruth, proveedor informa que no tiene como absorber el saldo pendiente, los demas convenios los acepta | AD69: 0 | AE69: 0 | AF69: 912579.27 | AG69: 912579.27 | AK69: 10
